Workbook

Sheet README
A1: DCCA Salesforce Data Dictionary | C1: accenture >
A2: Hawaii DCCA Salesforce platform · objects, fields, relationships, record types, picklists and entity-relationship diagrams
A4: About this workbook
A5: Prepared | B5: 2026-10-05 (reverse-engineered from code; not yet validated with business owners)
A6: Source repository | B6: DCCA Salesforce DX project, force-app/main/default (API v67.0)
A7: Custom objects & fields | B7: Parsed from every *.object-meta.xml, *.field-meta.xml, recordTypes and globalValueSets file in source.
A8: Account, Contact, Case, Payment | B8: Not stored in source. Fields, lookups, picklists and record types taken from a read-only "sf sobject describe" of the DCCA sandbox.
A9: Code references | B9: Count of non-test Apex classes/triggers, LWC/Aura bundles and Flows that mention the object or field API name.
A10: Diagrams | B10: Generated from the relationship metadata (Mermaid ER, ELK layout) and embedded as 2× resolution images. Interactive version: analysis/10-data-model.html.
A12: Key figures (live formulas)
A13: Objects catalogued | C13: =COUNTA('Object Catalogue'!A6:A1000)
A14: Custom objects | C14: =COUNTIF('Object Catalogue'!E:E,"Custom object")
A15: Custom metadata types | C15: =COUNTIF('Object Catalogue'!E:E,"Custom metadata")
A16: Platform events | C16: =COUNTIF('Object Catalogue'!E:E,"Platform event")
A17: Fields documented | C17: =COUNTA('Field Dictionary'!A6:A20000)
A18: Relationship fields | C18: =COUNTA(Relationships!A6:A5000)
A19: Master-detail relationships | C19: =COUNTIF(Relationships!E:E,"Master-detail")
A20: Record types | C20: =COUNTA('Record Types'!A6:A5000)
A21: Picklist value rows | C21: =COUNTA('Picklist Values'!A6:A50000)
A22: Custom objects with no code references | C22: =COUNTIF('Object Catalogue'!Q:Q,"No code references")
A24: Tabs
A25: Domain Summary | B25: The 13 business domains with object, field and relationship counts, and a link to each ERD.
A26: Object Catalogue | B26: Every object: label, domain, type, description, sharing, field / record-type / relationship counts, code usage.
A27: Field Dictionary | B27: Every field: type, length, required, unique, reference target, picklist values, formula, default, description, help text.
A28: Relationships | B28: Every lookup and master-detail field with child/parent object and domain, and whether it crosses domains.
A29: Core Object References | B29: All objects that look up to Account, Contact or Case, plus the custom lookups those three objects hold.
A30: Record Types | B30: All record types per object, active flag and description.
A31: Picklist Values | B31: Every picklist value (field-specific, org-described and Global Value Sets).
A32: ERD - Overview | B32: Entity-relationship diagram: Domain overview
A33: ERD - Core Acct-Contact-Case | B33: Entity-relationship diagram: Core: Account · Contact · Case
A34: ERD - BREG Registration | B34: Entity-relationship diagram: BREG: Business Registration
A35: ERD - BREG Web Staging | B35: Entity-relationship diagram: BREG: Legacy Web Filing Staging
A36: ERD - PVL Applications | B36: Entity-relationship diagram: PVL: Applications & Portal
... A44: ERD - Service & Work Mgmt | B44: Entity-relationship diagram: Service & Work Management
A46: ERD legend
B47: Legend: solid line = master-detail (child owned by parent) · dashed line = lookup · crow's foot = "many" side · boxes with attribute rows = objects in this domain (Label, Fields, CodeRefs) · plain boxes = objects from other domains or managed packages. Lookups to User are omitted.
A49: Caveats
B50: • Configuration (profiles, sharing rules, FLS) is not covered here; see analysis/05-access-control.md.
B51: • Managed-package objects other than pymt__PaymentX__c (DocuSign dsfs__, UJET__, cterminal__) appear only as relationship targets.
B52: • "No code references" means no Apex, LWC/Aura or Flow mentions the API name. The object may still be used through page layouts, reports or integrations.

Sheet Domain Summary
A1: Domain Summary
A2: Objects grouped into business domains. All counts are live formulas over the Object Catalogue.
A3: ‹ Back to README
A5: Domain | B5: Description | C5: Objects | D5: Fields | E5: Relationship Fields (to parents) | F5: Objects with No Code References | G5: ERD Tab
A6: Core: Account · Contact · Case | B6: Shared CRM backbone used by every division. | C6: =COUNTIF('Object Catalogue'!$D:$D,A6) | D6: =SUMIF('Object Catalogue'!$D:$D,A6,'Object Catalogue'!$H:$H) | E6: =SUMIF('Object Catalogue'!$D:$D,A6,'Object Catalogue'!$K:$K) | F6: =COUNTIFS('Object Catalogue'!$D:$D,A6,'Object Catalogue'!$Q:$Q,"No code references") | G6: ERD - Core Acct-Contact-Case
A7: BREG: Business Registration | B7: Entities, filings, transactions, annuals, certificates and documents for the Business Registration Division. | C7: =COUNTIF('Object Catalogue'!$D:$D,A7) | D7: =SUMIF('Object Catalogue'!$D:$D,A7,'Object Catalogue'!$H:$H) | E7: =SUMIF('Object Catalogue'!$D:$D,A7,'Object Catalogue'!$K:$K) | F7: =COUNTIFS('Object Catalogue'!$D:$D,A7,'Object Catalogue'!$Q:$Q,"No code references") | G7: ERD - BREG Registration
A8: BREG: Legacy Web Filing Staging | B8: Staging tables that receive legacy RDPMS web filings before they are mapped onto a Case. | C8: =COUNTIF('Object Catalogue'!$D:$D,A8) | D8: =SUMIF('Object Catalogue'!$D:$D,A8,'Object Catalogue'!$H:$H) | E8: =SUMIF('Object Catalogue'!$D:$D,A8,'Object Catalogue'!$K:$K) | F8: =COUNTIFS('Object Catalogue'!$D:$D,A8,'Object Catalogue'!$Q:$Q,"No code references") | G8: ERD - BREG Web Staging
A9: PVL: Applications & Portal | B9: Professional & Vocational Licensing applications, draft/metadata-driven online forms and portal users. | C9: =COUNTIF('Object Catalogue'!$D:$D,A9) | D9: =SUMIF('Object Catalogue'!$D:$D,A9,'Object Catalogue'!$H:$H) | E9: =SUMIF('Object Catalogue'!$D:$D,A9,'Object Catalogue'!$K:$K) | F9: =COUNTIFS('Object Catalogue'!$D:$D,A9,'Object Catalogue'!$Q:$Q,"No code references") | G9: ERD - PVL Applications
A10: PVL: Licenses & License Types | B10: Issued licenses, license-type configuration, requirements, insurance/bonds and notifications. | C10: =COUNTIF('Object Catalogue'!$D:$D,A10) | D10: =SUMIF('Object Catalogue'!$D:$D,A10,'Object Catalogue'!$H:$H) | E10: =SUMIF('Object Catalogue'!$D:$D,A10,'Object Catalogue'!$K:$K) | F10: =COUNTIFS('Object Catalogue'!$D:$D,A10,'Object Catalogue'!$Q:$Q,"No code references") | G10: ERD - PVL Licenses
A11: PVL: Exams & Continuing Education | B11: Licensing exam requirements, courses, schools, instructors and earned CE / pre-licence credit. | C11: =COUNTIF('Object Catalogue'!$D:$D,A11) | D11: =SUMIF('Object Catalogue'!$D:$D,A11,'Object Catalogue'!$H:$H) | E11: =SUMIF('Object Catalogue'!$D:$D,A11,'Object Catalogue'!$K:$K) | F11: =COUNTIFS('Object Catalogue'!$D:$D,A11,'Object Catalogue'!$Q:$Q,"No code references") | G11: ERD - PVL Exams & CE
A12: Payments & Finance | B12: Transactions, line items, PaymentConnect payments, fees, deposits and reconciliation. | C12: =COUNTIF('Object Catalogue'!$D:$D,A12) | D12: =SUMIF('Object Catalogue'!$D:$D,A12,'Object Catalogue'!$H:$H) | E12: =SUMIF('Object Catalogue'!$D:$D,A12,'Object Catalogue'!$K:$K) | F12: =COUNTIFS('Object Catalogue'!$D:$D,A12,'Object Catalogue'!$Q:$Q,"No code references") | G12: ERD - Payments & Finance
A13: Securities: Filings & Exams | B13: Securities registrations (broker-dealer, investment adviser, offerings) and compliance examinations. | C13: =COUNTIF('Object Catalogue'!$D:$D,A13) | D13: =SUMIF('Object Catalogue'!$D:$D,A13,'Object Catalogue'!$H:$H) | E13: =SUMIF('Object Catalogue'!$D:$D,A13,'Object Catalogue'!$K:$K) | F13: =COUNTIFS('Object Catalogue'!$D:$D,A13,'Object Catalogue'!$Q:$Q,"No code references") | G13: ERD - Securities
A14: Enforcement: SEB & RICO | B14: Securities Enforcement Branch cases, investigations, sanctions and RICO referrals. | C14: =COUNTIF('Object Catalogue'!$D:$D,A14) | D14: =SUMIF('Object Catalogue'!$D:$D,A14,'Object Catalogue'!$H:$H) | E14: =SUMIF('Object Catalogue'!$D:$D,A14,'Object Catalogue'!$K:$K) | F14: =COUNTIFS('Object Catalogue'!$D:$D,A14,'Object Catalogue'!$Q:$Q,"No code references") | G14: ERD - Enforcement SEB-RICO
A15: CATV / INET | B15: Cable TV portal access requests and INET (Institutional Network) requests, quotes, POs and invoices. | C15: =COUNTIF('Object Catalogue'!$D:$D,A15) | D15: =SUMIF('Object Catalogue'!$D:$D,A15,'Object Catalogue'!$H:$H) | E15: =SUMIF('Object Catalogue'!$D:$D,A15,'Object Catalogue'!$K:$K) | F15: =COUNTIFS('Object Catalogue'!$D:$D,A15,'Object Catalogue'!$Q:$Q,"No code references") | G15: ERD - CATV INET
A16: Travel & Expense | B16: Staff travel approval with expense worksheets (DocuSign approval). | C16: =COUNTIF('Object Catalogue'!$D:$D,A16) | D16: =SUMIF('Object Catalogue'!$D:$D,A16,'Object Catalogue'!$H:$H) | E16: =SUMIF('Object Catalogue'!$D:$D,A16,'Object Catalogue'!$K:$K) | F16: =COUNTIFS('Object Catalogue'!$D:$D,A16,'Object Catalogue'!$Q:$Q,"No code references") | G16: ERD - Travel & Expense
A17: Service & Work Management | B17: Work items, case teams, internal IT tickets, Qualtrics logs, case auto-closer and alerts. | C17: =COUNTIF('Object Catalogue'!$D:$D,A17) | D17: =SUMIF('Object Catalogue'!$D:$D,A17,'Object Catalogue'!$H:$H) | E17: =SUMIF('Object Catalogue'!$D:$D,A17,'Object Catalogue'!$K:$K) | F17: =COUNTIFS('Object Catalogue'!$D:$D,A17,'Object Catalogue'!$Q:$Q,"No code references") | G17: ERD - Service & Work Mgmt
A18: Configuration, Logs & Metadata | B18: Custom settings, logs, custom metadata types and platform events. Not drawn as ER. | C18: =COUNTIF('Object Catalogue'!$D:$D,A18) | D18: =SUMIF('Object Catalogue'!$D:$D,A18,'Object Catalogue'!$H:$H) | E18: =SUMIF('Object Catalogue'!$D:$D,A18,'Object Catalogue'!$K:$K) | F18: =COUNTIFS('Object Catalogue'!$D:$D,A18,'Object Catalogue'!$Q:$Q,"No code references") | G18: n/a (reference only)
A19: Total | C19: =SUM(C6:C18) | D19: =SUM(D6:D18) | E19: =SUM(E6:E18) | F19: =SUM(F6:F18)
A20: "Managed package" rows (e.g. pymt__PaymentX__c) sit in Payments & Finance.

Sheet Object Catalogue
A1: Object Catalogue
A2: One row per object. Counts in columns H–K and P–Q are live formulas over the Field Dictionary, Record Types and Relationships tabs.
A3: ‹ Back to README
A5: Object API Name | B5: Label | C5: Plural Label | D5: Domain | E5: Object Type | F5: Description | G5: Sharing Model | H5: Total Fields | I5: Custom Fields | J5: Record Types | K5: Relationship Fields (to parents) | L5: Apex Files | M5: LWC / Aura Bundles | N5: Flows | O5: Total Code References | P5: Referenced By (child lookups) | Q5: Code Usage Flag | R5: ERD Tab
A6: Account | B6: Account | C6: Accounts | D6: Core: Account · Contact · Case | E6: Standard | F6: Described from DCCA sandbox (not in source) | H6: =COUNTIF('Field Dictionary'!$A:$A,A6) | I6: =COUNTIFS('Field Dictionary'!$A:$A,A6,'Field Dictionary'!$T:$T,"Custom") | J6: =COUNTIF('Record Types'!$A:$A,A6) | K6: =COUNTIF(Relationships!$A:$A,A6) | L6: 144 | M6: 68 | N6: 42 | O6: =SUM(L6:N6) | P6: =COUNTIF(Relationships!$F:$F,A6) | Q6: =IF(AND(O6=0,E6="Custom object"),"No code references","") | R6: ERD - Core Acct-Contact-Case
A7: Case | B7: Case | C7: Cases | D7: Core: Account · Contact · Case | E7: Standard | F7: Described from DCCA sandbox (not in source) | H7: =COUNTIF('Field Dictionary'!$A:$A,A7) | I7: =COUNTIFS('Field Dictionary'!$A:$A,A7,'Field Dictionary'!$T:$T,"Custom") | J7: =COUNTIF('Record Types'!$A:$A,A7) | K7: =COUNTIF(Relationships!$A:$A,A7) | L7: 170 | M7: 71 | N7: 102 | O7: =SUM(L7:N7) | P7: =COUNTIF(Relationships!$F:$F,A7) | Q7: =IF(AND(O7=0,E7="Custom object"),"No code references","") | R7: ERD - Core Acct-Contact-Case
A8: Contact | B8: Contact | C8: Contacts | D8: Core: Account · Contact · Case | E8: Standard | F8: Described from DCCA sandbox (not in source) | H8: =COUNTIF('Field Dictionary'!$A:$A,A8) | I8: =COUNTIFS('Field Dictionary'!$A:$A,A8,'Field Dictionary'!$T:$T,"Custom") | J8: =COUNTIF('Record Types'!$A:$A,A8) | K8: =COUNTIF(Relationships!$A:$A,A8) | L8: 50 | M8: 24 | N8: 19 | O8: =SUM(L8:N8) | P8: =COUNTIF(Relationships!$F:$F,A8) | Q8: =IF(AND(O8=0,E8="Custom object"),"No code references","") | R8: ERD - Core Acct-Contact-Case
A9: BREG_ADDRESS_PROTECTION__c | B9: ADDRESS PROTECTION | C9: ADDRESS PROTECTIONs | D9: BREG: Business Registration | E9: Custom object | G9: ReadWrite | H9: =COUNTIF('Field Dictionary'!$A:$A,A9) | I9: =COUNTIFS('Field Dictionary'!$A:$A,A9,'Field Dictionary'!$T:$T,"Custom") | J9: =COUNTIF('Record Types'!$A:$A,A9) | K9: =COUNTIF(Relationships!$A:$A,A9) | L9: 1 | M9: 0 | N9: 0 | O9: =SUM(L9:N9) | P9: =COUNTIF(Relationships!$F:$F,A9) | Q9: =IF(AND(O9=0,E9="Custom object"),"No code references","") | R9: ERD - BREG Registration
A10: BREG_File_Number_Sequence__c | B10: BREG File Number Sequence | D10: BREG: Business Registration | E10: Custom object | H10: =COUNTIF('Field Dictionary'!$A:$A,A10) | I10: =COUNTIFS('Field Dictionary'!$A:$A,A10,'Field Dictionary'!$T:$T,"Custom") | J10: =COUNTIF('Record Types'!$A:$A,A10) | K10: =COUNTIF(Relationships!$A:$A,A10) | L10: 1 | M10: 0 | N10: 0 | O10: =SUM(L10:N10) | P10: =COUNTIF(Relationships!$F:$F,A10) | Q10: =IF(AND(O10=0,E10="Custom object"),"No code references","") | R10: ERD - BREG Registration
A11: breg_Account_Affiliation__c | B11: Account Affiliation | C11: Account Affiliations | D11: BREG: Business Registration | E11: Custom object | F11: Aalta BREG-59 | G11: ReadWrite | H11: =COUNTIF('Field Dictionary'!$A:$A,A11) | I11: =COUNTIFS('Field Dictionary'!$A:$A,A11,'Field Dictionary'!$T:$T,"Custom") | J11: =COUNTIF('Record Types'!$A:$A,A11) | K11: =COUNTIF(Relationships!$A:$A,A11) | L11: 43 | M11: 7 | N11: 5 | O11: =SUM(L11:N11) | P11: =COUNTIF(Relationships!$F:$F,A11) | Q11: =IF(AND(O11=0,E11="Custom object"),"No code references","") | R11: ERD - BREG Registration
A12: breg_Acquisition_Transaction__c | B12: Acquisition Transaction | C12: Acquisition Transactions | D12: BREG: Business Registration | E12: Custom object | F12: Aalta BREG-2653 | G12: ReadWrite | H12: =COUNTIF('Field Dictionary'!$A:$A,A12) | I12: =COUNTIFS('Field Dictionary'!$A:$A,A12,'Field Dictionary'!$T:$T,"Custom") | J12: =COUNTIF('Record Types'!$A:$A,A12) | K12: =COUNTIF(Relationships!$A:$A,A12) | L12: 0 | M12: 0 | N12: 0 | O12: =SUM(L12:N12) | P12: =COUNTIF(Relationships!$F:$F,A12) | Q12: =IF(AND(O12=0,E12="Custom object"),"No code references","") | R12: ERD - BREG Registration
A13: breg_Agent_Search_List__c | B13: Agent Search List | C13: Agent Search Lists | D13: BREG: Business Registration | E13: Custom object | G13: ReadWrite | H13: =COUNTIF('Field Dictionary'!$A:$A,A13) | I13: =COUNTIFS('Field Dictionary'!$A:$A,A13,'Field Dictionary'!$T:$T,"Custom") | J13: =COUNTIF('Record Types'!$A:$A,A13) | K13: =COUNTIF(Relationships!$A:$A,A13) | L13: 4 | M13: 0 | N13: 1 | O13: =SUM(L13:N13) | P13: =COUNTIF(Relationships!$F:$F,A13) | Q13: =IF(AND(O13=0,E13="Custom object"),"No code references","") | R13: ERD - BREG Registration
A14: breg_Agent_Search_Result__c | B14: Agent Search Result | C14: Agent Search Results | D14: BREG: Business Registration | E14: Custom object | G14: ControlledByParent | H14: =COUNTIF('Field Dictionary'!$A:$A,A14) | I14: =COUNTIFS('Field Dictionary'!$A:$A,A14,'Field Dictionary'!$T:$T,"Custom") | J14: =COUNTIF('Record Types'!$A:$A,A14) | K14: =COUNTIF(Relationships!$A:$A,A14) | L14: 1 | M14: 0 | N14: 0 | O14: =SUM(L14:N14) | P14: =COUNTIF(Relationships!$F:$F,A14) | Q14: =IF(AND(O14=0,E14="Custom object"),"No code references","") | R14: ERD - BREG Registration
A15: breg_Annual__c | B15: Annual | C15: Annuals | D15: BREG: Business Registration | E15: Custom object | F15: Aalta BREG-60 | G15: ReadWrite | H15: =COUNTIF('Field Dictionary'!$A:$A,A15) | I15: =COUNTIFS('Field Dictionary'!$A:$A,A15,'Field Dictionary'!$T:$T,"Custom") | J15: =COUNTIF('Record Types'!$A:$A,A15) | K15: =COUNTIF(Relationships!$A:$A,A15) | L15: 24 | M15: 4 | N15: 8 | O15: =SUM(L15:N15) | P15: =COUNTIF(Relationships!$F:$F,A15) | Q15: =IF(AND(O15=0,E15="Custom object"),"No code references","") | R15: ERD - BREG Registration
A16: breg_BRIM_Transaction_Event__b | B16: Transaction Event | C16: Transaction Events | D16: BREG: Business Registration | E16: Big object | H16: =COUNTIF('Field Dictionary'!$A:$A,A16) | I16: =COUNTIFS('Field Dictionary'!$A:$A,A16,'Field Dictionary'!$T:$T,"Custom") | J16: =COUNTIF('Record Types'!$A:$A,A16) | K16: =COUNTIF(Relationships!$A:$A,A16) | L16: 0 | M16: 0 | N16: 0 | O16: =SUM(L16:N16) | P16: =COUNTIF(Relationships!$F:$F,A16) | Q16: =IF(AND(O16=0,E16="Custom object"),"No code references","") | R16: ERD - BREG Registration
A17: breg_Batch_Job_Execution__c | B17: Batch Job Execution | C17: Batch Job Executions | D17: BREG: Business Registration | E17: Custom object | F17: Universal object for storing batch job execution results and logs | G17: ReadWrite | H17: =COUNTIF('Field Dictionary'!$A:$A,A17) | I17: =COUNTIFS('Field Dictionary'!$A:$A,A17,'Field Dictionary'!$T:$T,"Custom") | J17: =COUNTIF('Record Types'!$A:$A,A17) | K17: =COUNTIF(Relationships!$A:$A,A17) | L17: 8 | M17: 0 | N17: 0 | O17: =SUM(L17:N17) | P17: =COUNTIF(Relationships!$F:$F,A17) | Q17: =IF(AND(O17=0,E17="Custom object"),"No code references","") | R17: ERD - BREG Registration
A18: breg_Case_Staging__c | B18: Case Staging | C18: Case Staging | D18: BREG: Business Registration | E18: Custom object | G18: ReadWrite | H18: =COUNTIF('Field Dictionary'!$A:$A,A18) | I18: =COUNTIFS('Field Dictionary'!$A:$A,A18,'Field Dictionary'!$T:$T,"Custom") | J18: =COUNTIF('Record Types'!$A:$A,A18) | K18: =COUNTIF(Relationships!$A:$A,A18) | L18: 3 | M18: 0 | N18: 0 | O18: =SUM(L18:N18) | P18: =COUNTIF(Relationships!$F:$F,A18) | Q18: =IF(AND(O18=0,E18="Custom object"),"No code references","") | R18: ERD - BREG Registration
A19: breg_Certificate__c | B19: Certificate | C19: Certificates | D19: BREG: Business Registration | E19: Custom object | G19: ReadWrite | H19: =COUNTIF('Field Dictionary'!$A:$A,A19) | I19: =COUNTIFS('Field Dictionary'!$A:$A,A19,'Field Dictionary'!$T:$T,"Custom") | J19: =COUNTIF('Record Types'!$A:$A,A19) | K19: =COUNTIF(Relationships!$A:$A,A19) | L19: 7 | M19: 0 | N19: 1 | O19: =SUM(L19:N19) | P19: =COUNTIF(Relationships!$F:$F,A19) | Q19: =IF(AND(O19=0,E19="Custom object"),"No code references","") | R19: ERD - BREG Registration
A20: breg_DBEDT_Report__c | B20: DBEDT Report | C20: DBEDT Reports | D20: BREG: Business Registration | E20: Custom object | G20: ReadWrite | H20: =COUNTIF('Field Dictionary'!$A:$A,A20) | I20: =COUNTIFS('Field Dictionary'!$A:$A,A20,'Field Dictionary'!$T:$T,"Custom") | J20: =COUNTIF('Record Types'!$A:$A,A20) | K20: =COUNTIF(Relationships!$A:$A,A20) | L20: 1 | M20: 0 | N20: 0 | O20: =SUM(L20:N20) | P20: =COUNTIF(Relationships!$F:$F,A20) | Q20: =IF(AND(O20=0,E20="Custom object"),"No code references","") | R20: ERD - BREG Registration
A21: breg_Document__c | B21: Document | C21: Documents | D21: BREG: Business Registration | E21: Custom object | G21: ReadWrite | H21: =COUNTIF('Field Dictionary'!$A:$A,A21) | I21: =COUNTIFS('Field Dictionary'!$A:$A,A21,'Field Dictionary'!$T:$T,"Custom") | J21: =COUNTIF('Record Types'!$A:$A,A21) | K21: =COUNTIF(Relationships!$A:$A,A21) | L21: 25 | M21: 1 | N21: 4 | O21: =SUM(L21:N21) | P21: =COUNTIF(Relationships!$F:$F,A21) | Q21: =IF(AND(O21=0,E21="Custom object"),"No code references","") | R21: ERD - BREG Registration
A22: breg_Email_Log__c | B22: Email Log | C22: Email Logs | D22: BREG: Business Registration | E22: Custom object | G22: ReadWrite | H22: =COUNTIF('Field Dictionary'!$A:$A,A22) | I22: =COUNTIFS('Field Dictionary'!$A:$A,A22,'Field Dictionary'!$T:$T,"Custom") | J22: =COUNTIF('Record Types'!$A:$A,A22) | K22: =COUNTIF(Relationships!$A:$A,A22) | L22: 1 | M22: 0 | N22: 1 | O22: =SUM(L22:N22) | P22: =COUNTIF(Relationships!$F:$F,A22) | Q22: =IF(AND(O22=0,E22="Custom object"),"No code references","") | R22: ERD - BREG Registration
A23: breg_Entity_List_Item__c | B23: Entity List Item | C23: Entity List Items | D23: BREG: Business Registration | E23: Custom object | F23: Aalta BREG-58 | G23: ControlledByParent | H23: =COUNTIF('Field Dictionary'!$A:$A,A23) | I23: =COUNTIFS('Field Dictionary'!$A:$A,A23,'Field Dictionary'!$T:$T,"Custom") | J23: =COUNTIF('Record Types'!$A:$A,A23) | K23: =COUNTIF(Relationships!$A:$A,A23) | L23: 0 | M23: 0 | N23: 0 | O23: =SUM(L23:N23) | P23: =COUNTIF(Relationships!$F:$F,A23) | Q23: =IF(AND(O23=0,E23="Custom object"),"No code references","") | R23: ERD - BREG Registration
A24: breg_Entity_List_Result__c | B24: Entity List Result | C24: Entity List Results | D24: BREG: Business Registration | E24: Custom object | F24: Aalta BREG-58 | G24: ControlledByParent | H24: =COUNTIF('Field Dictionary'!$A:$A,A24) | I24: =COUNTIFS('Field Dictionary'!$A:$A,A24,'Field Dictionary'!$T:$T,"Custom") | J24: =COUNTIF('Record Types'!$A:$A,A24) | K24: =COUNTIF(Relationships!$A:$A,A24) | L24: 5 | M24: 0 | N24: 0 | O24: =SUM(L24:N24) | P24: =COUNTIF(Relationships!$F:$F,A24) | Q24: =IF(AND(O24=0,E24="Custom object"),"No code references","") | R24: ERD - BREG Registration
A25: breg_Entity_List__c | B25: Entity List | C25: Entity Lists | D25: BREG: Business Registration | E25: Custom object | F25: Aalta BREG-58 | G25: ReadWrite | H25: =COUNTIF('Field Dictionary'!$A:$A,A25) | I25: =COUNTIFS('Field Dictionary'!$A:$A,A25,'Field Dictionary'!$T:$T,"Custom") | J25: =COUNTIF('Record Types'!$A:$A,A25) | K25: =COUNTIF(Relationships!$A:$A,A25) | L25: 5 | M25: 0 | N25: 1 | O25: =SUM(L25:N25) | P25: =COUNTIF(Relationships!$F:$F,A25) | Q25: =IF(AND(O25=0,E25="Custom object"),"No code references","") | R25: ERD - BREG Registration
A26: breg_Fee__c | B26: Fee | C26: Fees | D26: BREG: Business Registration | E26: Custom object | F26: Aalta BREG-933 | G26: ReadWrite | H26: =COUNTIF('Field Dictionary'!$A:$A,A26) | I26: =COUNTIFS('Field Dictionary'!$A:$A,A26,'Field Dictionary'!$T:$T,"Custom") | J26: =COUNTIF('Record Types'!$A:$A,A26) | K26: =COUNTIF(Relationships!$A:$A,A26) | L26: 8 | M26: 0 | N26: 0 | O26: =SUM(L26:N26) | P26: =COUNTIF(Relationships!$F:$F,A26) | Q26: =IF(AND(O26=0,E26="Custom object"),"No code references","") | R26: ERD - BREG Registration
A27: breg_Form_Configuration_Item__c | B27: Form Configuration Item | C27: Form Configuration Items | D27: BREG: Business Registration | E27: Custom object | G27: ControlledByParent | H27: =COUNTIF('Field Dictionary'!$A:$A,A27) | I27: =COUNTIFS('Field Dictionary'!$A:$A,A27,'Field Dictionary'!$T:$T,"Custom") | J27: =COUNTIF('Record Types'!$A:$A,A27) | K27: =COUNTIF(Relationships!$A:$A,A27) | L27: 4 | M27: 1 | N27: 0 | O27: =SUM(L27:N27) | P27: =COUNTIF(Relationships!$F:$F,A27) | Q27: =IF(AND(O27=0,E27="Custom object"),"No code references","") | R27: ERD - BREG Registration
A28: breg_Form_Configuration__c | B28: Form Configuration | C28: Form Configurations | D28: BREG: Business Registration | E28: Custom object | G28: ReadWrite | H28: =COUNTIF('Field Dictionary'!$A:$A,A28) | I28: =COUNTIFS('Field Dictionary'!$A:$A,A28,'Field Dictionary'!$T:$T,"Custom") | J28: =COUNTIF('Record Types'!$A:$A,A28) | K28: =COUNTIF(Relationships!$A:$A,A28) | L28: 16 | M28: 4 | N28: 7 | O28: =SUM(L28:N28) | P28: =COUNTIF(Relationships!$F:$F,A28) | Q28: =IF(AND(O28=0,E28="Custom object"),"No code references","") | R28: ERD - BREG Registration
A29: breg_Log__c | B29: Log | C29: Logs | D29: BREG: Business Registration | E29: Custom object | F29: Aalta BREGMO-57 | G29: ReadWrite | H29: =COUNTIF('Field Dictionary'!$A:$A,A29) | I29: =COUNTIFS('Field Dictionary'!$A:$A,A29,'Field Dictionary'!$T:$T,"Custom") | J29: =COUNTIF('Record Types'!$A:$A,A29) | K29: =COUNTIF(Relationships!$A:$A,A29) | L29: 2 | M29: 0 | N29: 1 | O29: =SUM(L29:N29) | P29: =COUNTIF(Relationships!$F:$F,A29) | Q29: =IF(AND(O29=0,E29="Custom object"),"No code references","") | R29: ERD - BREG Registration
A30: breg_Notification__c | B30: Notification | C30: Notifications | D30: BREG: Business Registration | E30: Custom object | F30: Allta BREG-972 | G30: ReadWrite | H30: =COUNTIF('Field Dictionary'!$A:$A,A30) | I30: =COUNTIFS('Field Dictionary'!$A:$A,A30,'Field Dictionary'!$T:$T,"Custom") | J30: =COUNTIF('Record Types'!$A:$A,A30) | K30: =COUNTIF(Relationships!$A:$A,A30) | L30: 2 | M30: 0 | N30: 5 | O30: =SUM(L30:N30) | P30: =COUNTIF(Relationships!$F:$F,A30) | Q30: =IF(AND(O30=0,E30="Custom object"),"No code references","") | R30: ERD - BREG Registration
A31: breg_RDPMS_Adhoc_Request__c | B31: RDPMS Adhoc Request | C31: RDPMS Adhoc Requests | D31: BREG: Business Registration | E31: Custom object | G31: ReadWrite | H31: =COUNTIF('Field Dictionary'!$A:$A,A31) | I31: =COUNTIFS('Field Dictionary'!$A:$A,A31,'Field Dictionary'!$T:$T,"Custom") | J31: =COUNTIF('Record Types'!$A:$A,A31) | K31: =COUNTIF(Relationships!$A:$A,A31) | L31: 1 | M31: 0 | N31: 2 | O31: =SUM(L31:N31) | P31: =COUNTIF(Relationships!$F:$F,A31) | Q31: =IF(AND(O31=0,E31="Custom object"),"No code references","") | R31: ERD - BREG Registration
A32: breg_Rejection_Reason__c | B32: Rejection Reason | C32: Rejection Reasons | D32: BREG: Business Registration | E32: Custom object | G32: ReadWrite | H32: =COUNTIF('Field Dictionary'!$A:$A,A32) | I32: =COUNTIFS('Field Dictionary'!$A:$A,A32,'Field Dictionary'!$T:$T,"Custom") | J32: =COUNTIF('Record Types'!$A:$A,A32) | K32: =COUNTIF(Relationships!$A:$A,A32) | L32: 0 | M32: 0 | N32: 1 | O32: =SUM(L32:N32) | P32: =COUNTIF(Relationships!$F:$F,A32) | Q32: =IF(AND(O32=0,E32="Custom object"),"No code references","") | R32: ERD - BREG Registration
A33: breg_Search_Log__c | B33: BREG Search Log | C33: BREG Search Logs | D33: BREG: Business Registration | E33: Custom object | F33: Stores search log entries for BREG Name Clearance searches including search terms, filters, and request details | G33: ReadWrite | H33: =COUNTIF('Field Dictionary'!$A:$A,A33) | I33: =COUNTIFS('Field Dictionary'!$A:$A,A33,'Field Dictionary'!$T:$T,"Custom") | J33: =COUNTIF('Record Types'!$A:$A,A33) | K33: =COUNTIF(Relationships!$A:$A,A33) | L33: 3 | M33: 0 | N33: 0 | O33: =SUM(L33:N33) | P33: =COUNTIF(Relationships!$F:$F,A33) | Q33: =IF(AND(O33=0,E33="Custom object"),"No code references","") | R33: ERD - BREG Registration
A34: breg_Stock__c | B34: Stock | C34: Stocks | D34: BREG: Business Registration | E34: Custom object | F34: Aalta BREG-64 | G34: ReadWrite | H34: =COUNTIF('Field Dictionary'!$A:$A,A34) | I34: =COUNTIFS('Field Dictionary'!$A:$A,A34,'Field Dictionary'!$T:$T,"Custom") | J34: =COUNTIF('Record Types'!$A:$A,A34) | K34: =COUNTIF(Relationships!$A:$A,A34) | L34: 15 | M34: 5 | N34: 0 | O34: =SUM(L34:N34) | P34: =COUNTIF(Relationships!$F:$F,A34) | Q34: =IF(AND(O34=0,E34="Custom object"),"No code references","") | R34: ERD - BREG Registration
A35: breg_TN_TM_SM__c | B35: TN/TM/SM | C35: TN/TM/SM | D35: BREG: Business Registration | E35: Custom object | G35: ReadWrite | H35: =COUNTIF('Field Dictionary'!$A:$A,A35) | I35: =COUNTIFS('Field Dictionary'!$A:$A,A35,'Field Dictionary'!$T:$T,"Custom") | J35: =COUNTIF('Record Types'!$A:$A,A35) | K35: =COUNTIF(Relationships!$A:$A,A35) | L35: 34 | M35: 5 | N35: 10 | O35: =SUM(L35:N35) | P35: =COUNTIF(Relationships!$F:$F,A35) | Q35: =IF(AND(O35=0,E35="Custom object"),"No code references","") | R35: ERD - BREG Registration
A36: breg_Test_Annual__c | B36: Test Annual | C36: Test Annuals | D36: BREG: Business Registration | E36: Custom object | F36: Aalta BREG-60 | G36: ReadWrite | H36: =COUNTIF('Field Dictionary'!$A:$A,A36) | I36: =COUNTIFS('Field Dictionary'!$A:$A,A36,'Field Dictionary'!$T:$T,"Custom") | J36: =COUNTIF('Record Types'!$A:$A,A36) | K36: =COUNTIF(Relationships!$A:$A,A36) | L36: 1 | M36: 0 | N36: 0 | O36: =SUM(L36:N36) | P36: =COUNTIF(Relationships!$F:$F,A36) | Q36: =IF(AND(O36=0,E36="Custom object"),"No code references","") | R36: ERD - BREG Registration
A37: breg_Transaction_Address__c | B37: BREG Transaction Address | C37: BREG Transaction Addresses | D37: BREG: Business Registration | E37: Custom object | G37: ControlledByParent | H37: =COUNTIF('Field Dictionary'!$A:$A,A37) | I37: =COUNTIFS('Field Dictionary'!$A:$A,A37,'Field Dictionary'!$T:$T,"Custom") | J37: =COUNTIF('Record Types'!$A:$A,A37) | K37: =COUNTIF(Relationships!$A:$A,A37) | L37: 5 | M37: 0 | N37: 0 | O37: =SUM(L37:N37) | P37: =COUNTIF(Relationships!$F:$F,A37) | Q37: =IF(AND(O37=0,E37="Custom object"),"No code references","") | R37: ERD - BREG Registration
A38: breg_Transaction_Business_Info__c | B38: Transaction Business Info | C38: Transaction Business Info | D38: BREG: Business Registration | E38: Custom object | F38: Aalta BREG-2269 | G38: ReadWrite | H38: =COUNTIF('Field Dictionary'!$A:$A,A38) | I38: =COUNTIFS('Field Dictionary'!$A:$A,A38,'Field Dictionary'!$T:$T,"Custom") | J38: =COUNTIF('Record Types'!$A:$A,A38) | K38: =COUNTIF(Relationships!$A:$A,A38) | L38: 5 | M38: 0 | N38: 0 | O38: =SUM(L38:N38) | P38: =COUNTIF(Relationships!$F:$F,A38) | Q38: =IF(AND(O38=0,E38="Custom object"),"No code references","") | R38: ERD - BREG Registration
A39: breg_Transaction__c | B39: BREG Transaction | C39: BREG Transactions | D39: BREG: Business Registration | E39: Custom object | F39: Aalta BREG-62 | G39: ReadWrite | H39: =COUNTIF('Field Dictionary'!$A:$A,A39) | I39: =COUNTIFS('Field Dictionary'!$A:$A,A39,'Field Dictionary'!$T:$T,"Custom") | J39: =COUNTIF('Record Types'!$A:$A,A39) | K39: =COUNTIF(Relationships!$A:$A,A39) | L39: 28 | M39: 0 | N39: 5 | O39: =SUM(L39:N39) | P39: =COUNTIF(Relationships!$F:$F,A39) | Q39: =IF(AND(O39=0,E39="Custom object"),"No code references","") | R39: ERD - BREG Registration
A40: breg_WEB_WEB_ADDRESSES__c | B40: WEB ADDRESSES | C40: WEB ADDRESSESs | D40: BREG: Legacy Web Filing Staging | E40: Custom object | G40: ReadWrite | H40: =COUNTIF('Field Dictionary'!$A:$A,A40) | I40: =COUNTIFS('Field Dictionary'!$A:$A,A40,'Field Dictionary'!$T:$T,"Custom") | J40: =COUNTIF('Record Types'!$A:$A,A40) | K40: =COUNTIF(Relationships!$A:$A,A40) | L40: 2 | M40: 0 | N40: 0 | O40: =SUM(L40:N40) | P40: =COUNTIF(Relationships!$F:$F,A40) | Q40: =IF(AND(O40=0,E40="Custom object"),"No code references","") | R40: ERD - BREG Web Staging
A41: breg_WEB_WEB_BUSINESS_INFO__c | B41: WEB BUSINESS INFO | C41: WEB BUSINESS INFOs | D41: BREG: Legacy Web Filing Staging | E41: Custom object | G41: ReadWrite | H41: =COUNTIF('Field Dictionary'!$A:$A,A41) | I41: =COUNTIFS('Field Dictionary'!$A:$A,A41,'Field Dictionary'!$T:$T,"Custom") | J41: =COUNTIF('Record Types'!$A:$A,A41) | K41: =COUNTIF(Relationships!$A:$A,A41) | L41: 1 | M41: 0 | N41: 0 | O41: =SUM(L41:N41) | P41: =COUNTIF(Relationships!$F:$F,A41) | Q41: =IF(AND(O41=0,E41="Custom object"),"No code references","") | R41: ERD - BREG Web Staging
A42: breg_WEB_WEB_FILING_INFO__c | B42: WEB FILING INFO | C42: WEB FILING INFOs | D42: BREG: Legacy Web Filing Staging | E42: Custom object | G42: ReadWrite | H42: =COUNTIF('Field Dictionary'!$A:$A,A42) | I42: =COUNTIFS('Field Dictionary'!$A:$A,A42,'Field Dictionary'!$T:$T,"Custom") | J42: =COUNTIF('Record Types'!$A:$A,A42) | K42: =COUNTIF(Relationships!$A:$A,A42) | L42: 7 | M42: 0 | N42: 1 | O42: =SUM(L42:N42) | P42: =COUNTIF(Relationships!$F:$F,A42) | Q42: =IF(AND(O42=0,E42="Custom object"),"No code references","") | R42: ERD - BREG Web Staging
A43: breg_WEB_WEB_FILING_YEARS__c | B43: WEB FILING YEARS | C43: WEB FILING YEARSs | D43: BREG: Legacy Web Filing Staging | E43: Custom object | G43: ReadWrite | H43: =COUNTIF('Field Dictionary'!$A:$A,A43) | I43: =COUNTIFS('Field Dictionary'!$A:$A,A43,'Field Dictionary'!$T:$T,"Custom") | J43: =COUNTIF('Record Types'!$A:$A,A43) | K43: =COUNTIF(Relationships!$A:$A,A43) | L43: 0 | M43: 0 | N43: 0 | O43: =SUM(L43:N43) | P43: =COUNTIF(Relationships!$F:$F,A43) | Q43: =IF(AND(O43=0,E43="Custom object"),"No code references","") | R43: ERD - BREG Web Staging
A44: breg_WEB_WEB_PERSONS__c | B44: WEB PERSONS | C44: WEB PERSONSs | D44: BREG: Legacy Web Filing Staging | E44: Custom object | G44: ReadWrite | H44: =COUNTIF('Field Dictionary'!$A:$A,A44) | I44: =COUNTIFS('Field Dictionary'!$A:$A,A44,'Field Dictionary'!$T:$T,"Custom") | J44: =COUNTIF('Record Types'!$A:$A,A44) | K44: =COUNTIF(Relationships!$A:$A,A44) | L44: 1 | M44: 0 | N44: 0 | O44: =SUM(L44:N44) | P44: =COUNTIF(Relationships!$F:$F,A44) | Q44: =IF(AND(O44=0,E44="Custom object"),"No code references","") | R44: ERD - BREG Web Staging
A45: breg_WEB_WEB_RESUB__c | B45: WEB RESUB | C45: WEB RESUBs | D45: BREG: Legacy Web Filing Staging | E45: Custom object | G45: ReadWrite | H45: =COUNTIF('Field Dictionary'!$A:$A,A45) | I45: =COUNTIFS('Field Dictionary'!$A:$A,A45,'Field Dictionary'!$T:$T,"Custom") | J45: =COUNTIF('Record Types'!$A:$A,A45) | K45: =COUNTIF(Relationships!$A:$A,A45) | L45: 0 | M45: 0 | N45: 0 | O45: =SUM(L45:N45) | P45: =COUNTIF(Relationships!$F:$F,A45) | Q45: =IF(AND(O45=0,E45="Custom object"),"No code references","") | R45: ERD - BREG Web Staging
A46: breg_WEB_WEB_STOCKS__c | B46: WEB STOCKS | C46: WEB STOCKSs | D46: BREG: Legacy Web Filing Staging | E46: Custom object | G46: ReadWrite | H46: =COUNTIF('Field Dictionary'!$A:$A,A46) | I46: =COUNTIFS('Field Dictionary'!$A:$A,A46,'Field Dictionary'!$T:$T,"Custom") | J46: =COUNTIF('Record Types'!$A:$A,A46) | K46: =COUNTIF(Relationships!$A:$A,A46) | L46: 1 | M46: 0 | N46: 0 | O46: =SUM(L46:N46) | P46: =COUNTIF(Relationships!$F:$F,A46) | Q46: =IF(AND(O46=0,E46="Custom object"),"No code references","") | R46: ERD - BREG Web Staging
A47: breg_WEB_WEB_TRADE_MARKS__c | B47: WEB TRADE MARKS | C47: WEB TRADE MARKSs | D47: BREG: Legacy Web Filing Staging | E47: Custom object | G47: ReadWrite | H47: =COUNTIF('Field Dictionary'!$A:$A,A47) | I47: =COUNTIFS('Field Dictionary'!$A:$A,A47,'Field Dictionary'!$T:$T,"Custom") | J47: =COUNTIF('Record Types'!$A:$A,A47) | K47: =COUNTIF(Relationships!$A:$A,A47) | L47: 1 | M47: 0 | N47: 0 | O47: =SUM(L47:N47) | P47: =COUNTIF(Relationships!$F:$F,A47) | Q47: =IF(AND(O47=0,E47="Custom object"),"No code references","") | R47: ERD - BREG Web Staging
A48: AdditionalDependentAppsLicenses__c | B48: Additional Dependent Apps / Licenses | C48: Additional Dependent Apps / Licenses | D48: PVL: Applications & Portal | E48: Custom object | G48: ReadWrite | H48: =COUNTIF('Field Dictionary'!$A:$A,A48) | I48: =COUNTIFS('Field Dictionary'!$A:$A,A48,'Field Dictionary'!$T:$T,"Custom") | J48: =COUNTIF('Record Types'!$A:$A,A48) | K48: =COUNTIF(Relationships!$A:$A,A48) | L48: 0 | M48: 0 | N48: 0 | O48: =SUM(L48:N48) | P48: =COUNTIF(Relationships!$F:$F,A48) | Q48: =IF(AND(O48=0,E48="Custom object"),"No code references","") | R48: ERD - PVL Applications
A49: ApplicationClassifications__c | B49: Application Classifications | C49: Application Classifications | D49: PVL: Applications & Portal | E49: Custom object | F49: PacPoint-FT070119 - Created for PVL phase 1 | G49: ControlledByParent | H49: =COUNTIF('Field Dictionary'!$A:$A,A49) | I49: =COUNTIFS('Field Dictionary'!$A:$A,A49,'Field Dictionary'!$T:$T,"Custom") | J49: =COUNTIF('Record Types'!$A:$A,A49) | K49: =COUNTIF(Relationships!$A:$A,A49) | L49: 17 | M49: 1 | N49: 8 | O49: =SUM(L49:N49) | P49: =COUNTIF(Relationships!$F:$F,A49) | Q49: =IF(AND(O49=0,E49="Custom object"),"No code references","") | R49: ERD - PVL Applications
A50: ApplicationRequirement__c | B50: Application Requirement | C50: Application Requirements | D50: PVL: Applications & Portal | E50: Custom object | F50: PacPoint-FT070119 - Created for PVL phase 1 | G50: ControlledByParent | H50: =COUNTIF('Field Dictionary'!$A:$A,A50) | I50: =COUNTIFS('Field Dictionary'!$A:$A,A50,'Field Dictionary'!$T:$T,"Custom") | J50: =COUNTIF('Record Types'!$A:$A,A50) | K50: =COUNTIF(Relationships!$A:$A,A50) | L50: 12 | M50: 1 | N50: 3 | O50: =SUM(L50:N50) | P50: =COUNTIF(Relationships!$F:$F,A50) | Q50: =IF(AND(O50=0,E50="Custom object"),"No code references","") | R50: ERD - PVL Applications
A51: Application_Cache__c | B51: Draft Application | C51: Draft Applications | D51: PVL: Applications & Portal | E51: Custom object | F51: Form Builder App | G51: Read | H51: =COUNTIF('Field Dictionary'!$A:$A,A51) | I51: =COUNTIFS('Field Dictionary'!$A:$A,A51,'Field Dictionary'!$T:$T,"Custom") | J51: =COUNTIF('Record Types'!$A:$A,A51) | K51: =COUNTIF(Relationships!$A:$A,A51) | L51: 17 | M51: 0 | N51: 0 | O51: =SUM(L51:N51) | P51: =COUNTIF(Relationships!$F:$F,A51) | Q51: =IF(AND(O51=0,E51="Custom object"),"No code references","") | R51: ERD - PVL Applications
A52: Application_Log__c | B52: Application Log | C52: Application Logs | D52: PVL: Applications & Portal | E52: Custom object | F52: Used to capture system errors | G52: Private | H52: =COUNTIF('Field Dictionary'!$A:$A,A52) | I52: =COUNTIFS('Field Dictionary'!$A:$A,A52,'Field Dictionary'!$T:$T,"Custom") | J52: =COUNTIF('Record Types'!$A:$A,A52) | K52: =COUNTIF(Relationships!$A:$A,A52) | L52: 5 | M52: 0 | N52: 1 | O52: =SUM(L52:N52) | P52: =COUNTIF(Relationships!$F:$F,A52) | Q52: =IF(AND(O52=0,E52="Custom object"),"No code references","") | R52: ERD - PVL Applications
A53: Application_Meta_Data__c | B53: Application Meta Data | C53: Application Meta Data | D53: PVL: Applications & Portal | E53: Custom object | G53: Read | H53: =COUNTIF('Field Dictionary'!$A:$A,A53) | I53: =COUNTIFS('Field Dictionary'!$A:$A,A53,'Field Dictionary'!$T:$T,"Custom") | J53: =COUNTIF('Record Types'!$A:$A,A53) | K53: =COUNTIF(Relationships!$A:$A,A53) | L53: 13 | M53: 1 | N53: 0 | O53: =SUM(L53:N53) | P53: =COUNTIF(Relationships!$F:$F,A53) | Q53: =IF(AND(O53=0,E53="Custom object"),"No code references","") | R53: ERD - PVL Applications
A54: Application__c | B54: Application | C54: Applications | D54: PVL: Applications & Portal | E54: Custom object | F54: PacPoint-FT070119 - Created for PVL phase 1 | G54: ReadWrite | H54: =COUNTIF('Field Dictionary'!$A:$A,A54) | I54: =COUNTIFS('Field Dictionary'!$A:$A,A54,'Field Dictionary'!$T:$T,"Custom") | J54: =COUNTIF('Record Types'!$A:$A,A54) | K54: =COUNTIF(Relationships!$A:$A,A54) | L54: 103 | M54: 6 | N54: 68 | O54: =SUM(L54:N54) | P54: =COUNTIF(Relationships!$F:$F,A54) | Q54: =IF(AND(O54=0,E54="Custom object"),"No code references","") | R54: ERD - PVL Applications
A55: ApprenticeApplicationCounter__c | B55: Apprentice Application Counter | D55: PVL: Applications & Portal | E55: Custom object | F55: PacPoint-MV112719 - Created for PVL phase 1 | H55: =COUNTIF('Field Dictionary'!$A:$A,A55) | I55: =COUNTIFS('Field Dictionary'!$A:$A,A55,'Field Dictionary'!$T:$T,"Custom") | J55: =COUNTIF('Record Types'!$A:$A,A55) | K55: =COUNTIF(Relationships!$A:$A,A55) | L55: 1 | M55: 0 | N55: 0 | O55: =SUM(L55:N55) | P55: =COUNTIF(Relationships!$F:$F,A55) | Q55: =IF(AND(O55=0,E55="Custom object"),"No code references","") | R55: ERD - PVL Applications
A56: Card_Cache__c | B56: Card Cache | C56: Card Cache | D56: PVL: Applications & Portal | E56: Custom object | F56: Form Builder App - Stores temp JSON | G56: ControlledByParent | H56: =COUNTIF('Field Dictionary'!$A:$A,A56) | I56: =COUNTIFS('Field Dictionary'!$A:$A,A56,'Field Dictionary'!$T:$T,"Custom") | J56: =COUNTIF('Record Types'!$A:$A,A56) | K56: =COUNTIF(Relationships!$A:$A,A56) | L56: 9 | M56: 0 | N56: 0 | O56: =SUM(L56:N56) | P56: =COUNTIF(Relationships!$F:$F,A56) | Q56: =IF(AND(O56=0,E56="Custom object"),"No code references","") | R56: ERD - PVL Applications
A57: Card_Meta_Data__c | B57: Card Meta Data | C57: Card Meta Data | D57: PVL: Applications & Portal | E57: Custom object | F57: Contains the section data for each card on an application | G57: Read | H57: =COUNTIF('Field Dictionary'!$A:$A,A57) | I57: =COUNTIFS('Field Dictionary'!$A:$A,A57,'Field Dictionary'!$T:$T,"Custom") | J57: =COUNTIF('Record Types'!$A:$A,A57) | K57: =COUNTIF(Relationships!$A:$A,A57) | L57: 12 | M57: 0 | N57: 0 | O57: =SUM(L57:N57) | P57: =COUNTIF(Relationships!$F:$F,A57) | Q57: =IF(AND(O57=0,E57="Custom object"),"No code references","") | R57: ERD - PVL Applications
A58: Education__c | B58: Education | C58: Educations | D58: PVL: Applications & Portal | E58: Custom object | G58: ControlledByParent | H58: =COUNTIF('Field Dictionary'!$A:$A,A58) | I58: =COUNTIFS('Field Dictionary'!$A:$A,A58,'Field Dictionary'!$T:$T,"Custom") | J58: =COUNTIF('Record Types'!$A:$A,A58) | K58: =COUNTIF(Relationships!$A:$A,A58) | L58: 1 | M58: 0 | N58: 0 | O58: =SUM(L58:N58) | P58: =COUNTIF(Relationships!$F:$F,A58) | Q58: =IF(AND(O58=0,E58="Custom object"),"No code references","") | R58: ERD - PVL Applications
A59: Field_Filter__c | B59: Field Filter | C59: Field Filters | D59: PVL: Applications & Portal | E59: Custom object | G59: ReadWrite | H59: =COUNTIF('Field Dictionary'!$A:$A,A59) | I59: =COUNTIFS('Field Dictionary'!$A:$A,A59,'Field Dictionary'!$T:$T,"Custom") | J59: =COUNTIF('Record Types'!$A:$A,A59) | K59: =COUNTIF(Relationships!$A:$A,A59) | L59: 6 | M59: 0 | N59: 0 | O59: =SUM(L59:N59) | P59: =COUNTIF(Relationships!$F:$F,A59) | Q59: =IF(AND(O59=0,E59="Custom object"),"No code references","") | R59: ERD - PVL Applications
A60: Field_Meta_Data__c | B60: Field Meta Data | C60: Field Meta Data | D60: PVL: Applications & Portal | E60: Custom object | F60: Contains UI information for each field | G60: Read | H60: =COUNTIF('Field Dictionary'!$A:$A,A60) | I60: =COUNTIFS('Field Dictionary'!$A:$A,A60,'Field Dictionary'!$T:$T,"Custom") | J60: =COUNTIF('Record Types'!$A:$A,A60) | K60: =COUNTIF(Relationships!$A:$A,A60) | L60: 17 | M60: 0 | N60: 0 | O60: =SUM(L60:N60) | P60: =COUNTIF(Relationships!$F:$F,A60) | Q60: =IF(AND(O60=0,E60="Custom object"),"No code references","") | R60: ERD - PVL Applications
A61: IVR_Application_Status_Snapshot__c | B61: IVR Application Status Snapshot | C61: IVR Application Status Snapshots | D61: PVL: Applications & Portal | E61: Custom object | F61: Caller-safe PVL application status snapshot for IVR playback decisions. | G61: ReadWrite | H61: =COUNTIF('Field Dictionary'!$A:$A,A61) | I61: =COUNTIFS('Field Dictionary'!$A:$A,A61,'Field Dictionary'!$T:$T,"Custom") | J61: =COUNTIF('Record Types'!$A:$A,A61) | K61: =COUNTIF(Relationships!$A:$A,A61) | L61: 4 | M61: 0 | N61: 0 | O61: =SUM(L61:N61) | P61: =COUNTIF(Relationships!$F:$F,A61) | Q61: =IF(AND(O61=0,E61="Custom object"),"No code references","") | R61: ERD - PVL Applications
A62: OtherStateLicenses__c | B62: Other State Licenses | C62: Other State Licenses | D62: PVL: Applications & Portal | E62: Custom object | G62: ReadWrite | H62: =COUNTIF('Field Dictionary'!$A:$A,A62) | I62: =COUNTIFS('Field Dictionary'!$A:$A,A62,'Field Dictionary'!$T:$T,"Custom") | J62: =COUNTIF('Record Types'!$A:$A,A62) | K62: =COUNTIF(Relationships!$A:$A,A62) | L62: 1 | M62: 0 | N62: 0 | O62: =SUM(L62:N62) | P62: =COUNTIF(Relationships!$F:$F,A62) | Q62: =IF(AND(O62=0,E62="Custom object"),"No code references","") | R62: ERD - PVL Applications
A63: PVL_Board_Assignment__c | B63: Work Item Assignment | C63: Work Item Assignments | D63: PVL: Applications & Portal | E63: Custom object | G63: ReadWrite | H63: =COUNTIF('Field Dictionary'!$A:$A,A63) | I63: =COUNTIFS('Field Dictionary'!$A:$A,A63,'Field Dictionary'!$T:$T,"Custom") | J63: =COUNTIF('Record Types'!$A:$A,A63) | K63: =COUNTIF(Relationships!$A:$A,A63) | L63: 0 | M63: 0 | N63: 3 | O63: =SUM(L63:N63) | P63: =COUNTIF(Relationships!$F:$F,A63) | Q63: =IF(AND(O63=0,E63="Custom object"),"No code references","") | R63: ERD - PVL Applications
A64: PVL_Portal_Persona__c | B64: PVL Portal Persona | C64: PVL Portal Personas | D64: PVL: Applications & Portal | E64: Custom object | F64: PacPoint-KN08192020-Created for CE and INS | G64: ReadWrite | H64: =COUNTIF('Field Dictionary'!$A:$A,A64) | I64: =COUNTIFS('Field Dictionary'!$A:$A,A64,'Field Dictionary'!$T:$T,"Custom") | J64: =COUNTIF('Record Types'!$A:$A,A64) | K64: =COUNTIF(Relationships!$A:$A,A64) | L64: 0 | M64: 0 | N64: 0 | O64: =SUM(L64:N64) | P64: =COUNTIF(Relationships!$F:$F,A64) | Q64: =IF(AND(O64=0,E64="Custom object"),"No code references","") | R64: ERD - PVL Applications
A65: PVL_Portal_User__c | B65: PVL Portal User | C65: PVL Portal Users | D65: PVL: Applications & Portal | E65: Custom object | G65: ReadWrite | H65: =COUNTIF('Field Dictionary'!$A:$A,A65) | I65: =COUNTIFS('Field Dictionary'!$A:$A,A65,'Field Dictionary'!$T:$T,"Custom") | J65: =COUNTIF('Record Types'!$A:$A,A65) | K65: =COUNTIF(Relationships!$A:$A,A65) | L65: 6 | M65: 0 | N65: 6 | O65: =SUM(L65:N65) | P65: =COUNTIF(Relationships!$F:$F,A65) | Q65: =IF(AND(O65=0,E65="Custom object"),"No code references","") | R65: ERD - PVL Applications
A66: PVL_Portal__c | B66: PVL Portal | C66: PVL Portals | D66: PVL: Applications & Portal | E66: Custom object | F66: PacPoint-KN08192020-Created for PVL CE and INS Portal | G66: ReadWrite | H66: =COUNTIF('Field Dictionary'!$A:$A,A66) | I66: =COUNTIFS('Field Dictionary'!$A:$A,A66,'Field Dictionary'!$T:$T,"Custom") | J66: =COUNTIF('Record Types'!$A:$A,A66) | K66: =COUNTIF(Relationships!$A:$A,A66) | L66: 0 | M66: 0 | N66: 0 | O66: =SUM(L66:N66) | P66: =COUNTIF(Relationships!$F:$F,A66) | Q66: =IF(AND(O66=0,E66="Custom object"),"No code references","") | R66: ERD - PVL Applications
A67: Partner_Officer__c | B67: Partner/Officer | C67: Partners/Officers | D67: PVL: Applications & Portal | E67: Custom object | F67: Houses all Partner/Officer Relationships | G67: ControlledByParent | H67: =COUNTIF('Field Dictionary'!$A:$A,A67) | I67: =COUNTIFS('Field Dictionary'!$A:$A,A67,'Field Dictionary'!$T:$T,"Custom") | J67: =COUNTIF('Record Types'!$A:$A,A67) | K67: =COUNTIF(Relationships!$A:$A,A67) | L67: 0 | M67: 0 | N67: 0 | O67: =SUM(L67:N67) | P67: =COUNTIF(Relationships!$F:$F,A67) | Q67: =IF(AND(O67=0,E67="Custom object"),"No code references","") | R67: ERD - PVL Applications
A68: Requisition__c | B68: Requisition | C68: Requisition | D68: PVL: Applications & Portal | E68: Custom object | F68: PacPoint-FT120419 - Created for PVL phase 1 | G68: ReadWrite | H68: =COUNTIF('Field Dictionary'!$A:$A,A68) | I68: =COUNTIFS('Field Dictionary'!$A:$A,A68,'Field Dictionary'!$T:$T,"Custom") | J68: =COUNTIF('Record Types'!$A:$A,A68) | K68: =COUNTIF(Relationships!$A:$A,A68) | L68: 0 | M68: 0 | N68: 5 | O68: =SUM(L68:N68) | P68: =COUNTIF(Relationships!$F:$F,A68) | Q68: =IF(AND(O68=0,E68="Custom object"),"No code references","") | R68: ERD - PVL Applications
A69: AccountName__c | B69: Account Name | C69: Account Names | D69: PVL: Licenses & License Types | E69: Custom object | F69: PacPoint-FT041820- Created for PVL phase 1 | G69: ReadWrite | H69: =COUNTIF('Field Dictionary'!$A:$A,A69) | I69: =COUNTIFS('Field Dictionary'!$A:$A,A69,'Field Dictionary'!$T:$T,"Custom") | J69: =COUNTIF('Record Types'!$A:$A,A69) | K69: =COUNTIF(Relationships!$A:$A,A69) | L69: 3 | M69: 0 | N69: 1 | O69: =SUM(L69:N69) | P69: =COUNTIF(Relationships!$F:$F,A69) | Q69: =IF(AND(O69=0,E69="Custom object"),"No code references","") | R69: ERD - PVL Licenses
A70: AssociatedLicense__c | B70: Associated License | C70: Associated Licenses | D70: PVL: Licenses & License Types | E70: Custom object | F70: PacPoint-IC071619- Created for PVL phase 1 | G70: ControlledByParent | H70: =COUNTIF('Field Dictionary'!$A:$A,A70) | I70: =COUNTIFS('Field Dictionary'!$A:$A,A70,'Field Dictionary'!$T:$T,"Custom") | J70: =COUNTIF('Record Types'!$A:$A,A70) | K70: =COUNTIF(Relationships!$A:$A,A70) | L70: 51 | M70: 1 | N70: 24 | O70: =SUM(L70:N70) | P70: =COUNTIF(Relationships!$F:$F,A70) | Q70: =IF(AND(O70=0,E70="Custom object"),"No code references","") | R70: ERD - PVL Licenses
A71: Associated_Account__c | B71: Associated Account | C71: Associated Accounts | D71: PVL: Licenses & License Types | E71: Custom object | G71: ReadWrite | H71: =COUNTIF('Field Dictionary'!$A:$A,A71) | I71: =COUNTIFS('Field Dictionary'!$A:$A,A71,'Field Dictionary'!$T:$T,"Custom") | J71: =COUNTIF('Record Types'!$A:$A,A71) | K71: =COUNTIF(Relationships!$A:$A,A71) | L71: 0 | M71: 0 | N71: 1 | O71: =SUM(L71:N71) | P71: =COUNTIF(Relationships!$F:$F,A71) | Q71: =IF(AND(O71=0,E71="Custom object"),"No code references","") | R71: ERD - PVL Licenses
A72: BoardProgram__c | B72: Board / Program | C72: Boards / Programs | D72: PVL: Licenses & License Types | E72: Custom object | F72: PacPoint-FT070119 - Created for PVL phase 1 | G72: ReadWrite | H72: =COUNTIF('Field Dictionary'!$A:$A,A72) | I72: =COUNTIFS('Field Dictionary'!$A:$A,A72,'Field Dictionary'!$T:$T,"Custom") | J72: =COUNTIF('Record Types'!$A:$A,A72) | K72: =COUNTIF(Relationships!$A:$A,A72) | L72: 9 | M72: 0 | N72: 8 | O72: =SUM(L72:N72) | P72: =COUNTIF(Relationships!$F:$F,A72) | Q72: =IF(AND(O72=0,E72="Custom object"),"No code references","") | R72: ERD - PVL Licenses
A73: BusinessAccountCounter__c | B73: Business Account Counter | D73: PVL: Licenses & License Types | E73: Custom object | F73: PacPoint-MV100319 - Created for PVL phase 1 | H73: =COUNTIF('Field Dictionary'!$A:$A,A73) | I73: =COUNTIFS('Field Dictionary'!$A:$A,A73,'Field Dictionary'!$T:$T,"Custom") | J73: =COUNTIF('Record Types'!$A:$A,A73) | K73: =COUNTIF(Relationships!$A:$A,A73) | L73: 2 | M73: 0 | N73: 0 | O73: =SUM(L73:N73) | P73: =COUNTIF(Relationships!$F:$F,A73) | Q73: =IF(AND(O73=0,E73="Custom object"),"No code references","") | R73: ERD - PVL Licenses
A74: CertificateRequest__c | B74: Certificate Request | C74: Certificate Requests | D74: PVL: Licenses & License Types | E74: Custom object | F74: PacPoint-FT041820- Created for PVL phase 1 | G74: ReadWrite | H74: =COUNTIF('Field Dictionary'!$A:$A,A74) | I74: =COUNTIFS('Field Dictionary'!$A:$A,A74,'Field Dictionary'!$T:$T,"Custom") | J74: =COUNTIF('Record Types'!$A:$A,A74) | K74: =COUNTIF(Relationships!$A:$A,A74) | L74: 3 | M74: 0 | N74: 2 | O74: =SUM(L74:N74) | P74: =COUNTIF(Relationships!$F:$F,A74) | Q74: =IF(AND(O74=0,E74="Custom object"),"No code references","") | R74: ERD - PVL Licenses
A75: Classification__c | B75: Classification | C75: Classifications | D75: PVL: Licenses & License Types | E75: Custom object | F75: PacPoint-FT070119 - Created for PVL phase 1 | G75: ControlledByParent | H75: =COUNTIF('Field Dictionary'!$A:$A,A75) | I75: =COUNTIFS('Field Dictionary'!$A:$A,A75,'Field Dictionary'!$T:$T,"Custom") | J75: =COUNTIF('Record Types'!$A:$A,A75) | K75: =COUNTIF(Relationships!$A:$A,A75) | L75: 21 | M75: 2 | N75: 6 | O75: =SUM(L75:N75) | P75: =COUNTIF(Relationships!$F:$F,A75) | Q75: =IF(AND(O75=0,E75="Custom object"),"No code references","") | R75: ERD - PVL Licenses
A76: DocGeneratorDataSource__c | B76: Doc Generator Data Source | C76: Doc Generator Data Sources | D76: PVL: Licenses & License Types | E76: Custom object | F76: PacPoint-AZ102419 - Created for PVL phase 1 | G76: ReadWrite | H76: =COUNTIF('Field Dictionary'!$A:$A,A76) | I76: =COUNTIFS('Field Dictionary'!$A:$A,A76,'Field Dictionary'!$T:$T,"Custom") | J76: =COUNTIF('Record Types'!$A:$A,A76) | K76: =COUNTIF(Relationships!$A:$A,A76) | L76: 4 | M76: 0 | N76: 0 | O76: =SUM(L76:N76) | P76: =COUNTIF(Relationships!$F:$F,A76) | Q76: =IF(AND(O76=0,E76="Custom object"),"No code references","") | R76: ERD - PVL Licenses
A77: DocGeneratorSettings__c | B77: Doc Generator Settings | C77: Doc Generator Settings | D77: PVL: Licenses & License Types | E77: Custom object | F77: PacPoint-FT10179 - Created for PVL phase 1 | G77: ReadWrite | H77: =COUNTIF('Field Dictionary'!$A:$A,A77) | I77: =COUNTIFS('Field Dictionary'!$A:$A,A77,'Field Dictionary'!$T:$T,"Custom") | J77: =COUNTIF('Record Types'!$A:$A,A77) | K77: =COUNTIF(Relationships!$A:$A,A77) | L77: 11 | M77: 0 | N77: 7 | O77: =SUM(L77:N77) | P77: =COUNTIF(Relationships!$F:$F,A77) | Q77: =IF(AND(O77=0,E77="Custom object"),"No code references","") | R77: ERD - PVL Licenses
A78: Express_Change_Broker_History__c | B78: Express Change Broker History | C78: Express Change Broker History | D78: PVL: Licenses & License Types | E78: Custom object | G78: ControlledByParent | H78: =COUNTIF('Field Dictionary'!$A:$A,A78) | I78: =COUNTIFS('Field Dictionary'!$A:$A,A78,'Field Dictionary'!$T:$T,"Custom") | J78: =COUNTIF('Record Types'!$A:$A,A78) | K78: =COUNTIF(Relationships!$A:$A,A78) | L78: 0 | M78: 0 | N78: 2 | O78: =SUM(L78:N78) | P78: =COUNTIF(Relationships!$F:$F,A78) | Q78: =IF(AND(O78=0,E78="Custom object"),"No code references","") | R78: ERD - PVL Licenses
A79: Inspections__c | B79: Inspections | C79: Inspections | D79: PVL: Licenses & License Types | E79: Custom object | F79: PacPoint-FT050230 - Created for phase 1 | G79: ReadWrite | H79: =COUNTIF('Field Dictionary'!$A:$A,A79) | I79: =COUNTIFS('Field Dictionary'!$A:$A,A79,'Field Dictionary'!$T:$T,"Custom") | J79: =COUNTIF('Record Types'!$A:$A,A79) | K79: =COUNTIF(Relationships!$A:$A,A79) | L79: 0 | M79: 0 | N79: 0 | O79: =SUM(L79:N79) | P79: =COUNTIF(Relationships!$F:$F,A79) | Q79: =IF(AND(O79=0,E79="Custom object"),"No code references","") | R79: ERD - PVL Licenses
A80: InsuranceBond__c | B80: Insurance & Bond | C80: Insurance & Bonds | D80: PVL: Licenses & License Types | E80: Custom object | F80: PacPoint-FT070119 - Created for PVL phase 1 | G80: ControlledByParent | H80: =COUNTIF('Field Dictionary'!$A:$A,A80) | I80: =COUNTIFS('Field Dictionary'!$A:$A,A80,'Field Dictionary'!$T:$T,"Custom") | J80: =COUNTIF('Record Types'!$A:$A,A80) | K80: =COUNTIF(Relationships!$A:$A,A80) | L80: 21 | M80: 0 | N80: 7 | O80: =SUM(L80:N80) | P80: =COUNTIF(Relationships!$F:$F,A80) | Q80: =IF(AND(O80=0,E80="Custom object"),"No code references","") | R80: ERD - PVL Licenses
A81: InsurancePortalSubmission__c | B81: Insurance Portal Submission | C81: Insurance Portal Submissions | D81: PVL: Licenses & License Types | E81: Custom object | G81: ReadWrite | H81: =COUNTIF('Field Dictionary'!$A:$A,A81) | I81: =COUNTIFS('Field Dictionary'!$A:$A,A81,'Field Dictionary'!$T:$T,"Custom") | J81: =COUNTIF('Record Types'!$A:$A,A81) | K81: =COUNTIF(Relationships!$A:$A,A81) | L81: 4 | M81: 0 | N81: 1 | O81: =SUM(L81:N81) | P81: =COUNTIF(Relationships!$F:$F,A81) | Q81: =IF(AND(O81=0,E81="Custom object"),"No code references","") | R81: ERD - PVL Licenses
A82: Insurer__c | B82: Insurer | C82: Insurers | D82: PVL: Licenses & License Types | E82: Custom object | G82: ReadWrite | H82: =COUNTIF('Field Dictionary'!$A:$A,A82) | I82: =COUNTIFS('Field Dictionary'!$A:$A,A82,'Field Dictionary'!$T:$T,"Custom") | J82: =COUNTIF('Record Types'!$A:$A,A82) | K82: =COUNTIF(Relationships!$A:$A,A82) | L82: 0 | M82: 0 | N82: 0 | O82: =SUM(L82:N82) | P82: =COUNTIF(Relationships!$F:$F,A82) | Q82: =IF(AND(O82=0,E82="Custom object"),"No code references","") | R82: ERD - PVL Licenses
A83: LicenseClassification__c | B83: License Classification | C83: License Classifications | D83: PVL: Licenses & License Types | E83: Custom object | F83: PacPoint-FT070119 - Created for PVL phase 1 | G83: ControlledByParent | H83: =COUNTIF('Field Dictionary'!$A:$A,A83) | I83: =COUNTIFS('Field Dictionary'!$A:$A,A83,'Field Dictionary'!$T:$T,"Custom") | J83: =COUNTIF('Record Types'!$A:$A,A83) | K83: =COUNTIF(Relationships!$A:$A,A83) | L83: 27 | M83: 0 | N83: 10 | O83: =SUM(L83:N83) | P83: =COUNTIF(Relationships!$F:$F,A83) | Q83: =IF(AND(O83=0,E83="Custom object"),"No code references","") | R83: ERD - PVL Licenses
A84: LicenseConditions__c | B84: License Condition | C84: License Conditions | D84: PVL: Licenses & License Types | E84: Custom object | F84: PacPoint-IC080519- Created for PVL phase 1 | G84: ControlledByParent | H84: =COUNTIF('Field Dictionary'!$A:$A,A84) | I84: =COUNTIFS('Field Dictionary'!$A:$A,A84,'Field Dictionary'!$T:$T,"Custom") | J84: =COUNTIF('Record Types'!$A:$A,A84) | K84: =COUNTIF(Relationships!$A:$A,A84) | L84: 8 | M84: 0 | N84: 0 | O84: =SUM(L84:N84) | P84: =COUNTIF(Relationships!$F:$F,A84) | Q84: =IF(AND(O84=0,E84="Custom object"),"No code references","") | R84: ERD - PVL Licenses
A85: LicenseHistory__c | B85: License History | C85: License History | D85: PVL: Licenses & License Types | E85: Custom object | F85: PacPoint-FT041820- Created for PVL phase 1 | G85: ReadWrite | H85: =COUNTIF('Field Dictionary'!$A:$A,A85) | I85: =COUNTIFS('Field Dictionary'!$A:$A,A85,'Field Dictionary'!$T:$T,"Custom") | J85: =COUNTIF('Record Types'!$A:$A,A85) | K85: =COUNTIF(Relationships!$A:$A,A85) | L85: 19 | M85: 0 | N85: 18 | O85: =SUM(L85:N85) | P85: =COUNTIF(Relationships!$F:$F,A85) | Q85: =IF(AND(O85=0,E85="Custom object"),"No code references","") | R85: ERD - PVL Licenses
A86: LicenseName__c | B86: License Name | C86: License Names | D86: PVL: Licenses & License Types | E86: Custom object | F86: PacPoint-FT041820- Created for PVL phase 1 | G86: ReadWrite | H86: =COUNTIF('Field Dictionary'!$A:$A,A86) | I86: =COUNTIFS('Field Dictionary'!$A:$A,A86,'Field Dictionary'!$T:$T,"Custom") | J86: =COUNTIF('Record Types'!$A:$A,A86) | K86: =COUNTIF(Relationships!$A:$A,A86) | L86: 3 | M86: 0 | N86: 5 | O86: =SUM(L86:N86) | P86: =COUNTIF(Relationships!$F:$F,A86) | Q86: =IF(AND(O86=0,E86="Custom object"),"No code references","") | R86: ERD - PVL Licenses
A87: LicenseNumberAssignments__c | B87: License Number Assignments | C87: License Number Assignments | D87: PVL: Licenses & License Types | E87: Custom object | F87: PacPoint-MV093019 - Created for PVL phase 1 | G87: ReadWrite | H87: =COUNTIF('Field Dictionary'!$A:$A,A87) | I87: =COUNTIFS('Field Dictionary'!$A:$A,A87,'Field Dictionary'!$T:$T,"Custom") | J87: =COUNTIF('Record Types'!$A:$A,A87) | K87: =COUNTIF(Relationships!$A:$A,A87) | L87: 3 | M87: 0 | N87: 0 | O87: =SUM(L87:N87) | P87: =COUNTIF(Relationships!$F:$F,A87) | Q87: =IF(AND(O87=0,E87="Custom object"),"No code references","") | R87: ERD - PVL Licenses
A88: LicensePeriod__c | B88: License Period | C88: License Periods | D88: PVL: Licenses & License Types | E88: Custom object | G88: ControlledByParent | H88: =COUNTIF('Field Dictionary'!$A:$A,A88) | I88: =COUNTIFS('Field Dictionary'!$A:$A,A88,'Field Dictionary'!$T:$T,"Custom") | J88: =COUNTIF('Record Types'!$A:$A,A88) | K88: =COUNTIF(Relationships!$A:$A,A88) | L88: 22 | M88: 0 | N88: 22 | O88: =SUM(L88:N88) | P88: =COUNTIF(Relationships!$F:$F,A88) | Q88: =IF(AND(O88=0,E88="Custom object"),"No code references","") | R88: ERD - PVL Licenses
A89: LicenseRequirements__c | B89: License Requirements | C89: LicenseRequirements | D89: PVL: Licenses & License Types | E89: Custom object | F89: PacPoint-IC071619- Created for PVL phase 1 | G89: ReadWrite | H89: =COUNTIF('Field Dictionary'!$A:$A,A89) | I89: =COUNTIFS('Field Dictionary'!$A:$A,A89,'Field Dictionary'!$T:$T,"Custom") | J89: =COUNTIF('Record Types'!$A:$A,A89) | K89: =COUNTIF(Relationships!$A:$A,A89) | L89: 9 | M89: 0 | N89: 1 | O89: =SUM(L89:N89) | P89: =COUNTIF(Relationships!$F:$F,A89) | Q89: =IF(AND(O89=0,E89="Custom object"),"No code references","") | R89: ERD - PVL Licenses
A90: LicenseTypeMapping__c | B90: License Type Mapping | D90: PVL: Licenses & License Types | E90: Custom object | F90: PacPoint: RdG - Case# 8722 - For PVL Phase 1 - License Type Mapping | H90: =COUNTIF('Field Dictionary'!$A:$A,A90) | I90: =COUNTIFS('Field Dictionary'!$A:$A,A90,'Field Dictionary'!$T:$T,"Custom") | J90: =COUNTIF('Record Types'!$A:$A,A90) | K90: =COUNTIF(Relationships!$A:$A,A90) | L90: 0 | M90: 0 | N90: 1 | O90: =SUM(L90:N90) | P90: =COUNTIF(Relationships!$F:$F,A90) | Q90: =IF(AND(O90=0,E90="Custom object"),"No code references","") | R90: ERD - PVL Licenses
A91: LicenseTypeRequirements__c | B91: License Type Requirement | C91: License Type Requirements | D91: PVL: Licenses & License Types | E91: Custom object | F91: PacPoint-FT070119 - Created for PVL phase 1 | G91: ReadWrite | H91: =COUNTIF('Field Dictionary'!$A:$A,A91) | I91: =COUNTIFS('Field Dictionary'!$A:$A,A91,'Field Dictionary'!$T:$T,"Custom") | J91: =COUNTIF('Record Types'!$A:$A,A91) | K91: =COUNTIF(Relationships!$A:$A,A91) | L91: 6 | M91: 0 | N91: 0 | O91: =SUM(L91:N91) | P91: =COUNTIF(Relationships!$F:$F,A91) | Q91: =IF(AND(O91=0,E91="Custom object"),"No code references","") | R91: ERD - PVL Licenses
A92: LicenseType_Required_CE__c | B92: License Type / Education Subjects | C92: License Type / Required CE | D92: PVL: Licenses & License Types | E92: Custom object | F92: PacPoint-KN08122020-Created for PVL CE and INS | G92: ControlledByParent | H92: =COUNTIF('Field Dictionary'!$A:$A,A92) | I92: =COUNTIFS('Field Dictionary'!$A:$A,A92,'Field Dictionary'!$T:$T,"Custom") | J92: =COUNTIF('Record Types'!$A:$A,A92) | K92: =COUNTIF(Relationships!$A:$A,A92) | L92: 1 | M92: 0 | N92: 0 | O92: =SUM(L92:N92) | P92: =COUNTIF(Relationships!$F:$F,A92) | Q92: =IF(AND(O92=0,E92="Custom object"),"No code references","") | R92: ERD - PVL Licenses
A93: LicenseType__c | B93: License Type | C93: License Types | D93: PVL: Licenses & License Types | E93: Custom object | F93: PacPoint-FT070119 - Created for PVL phase 1 | G93: ReadWrite | H93: =COUNTIF('Field Dictionary'!$A:$A,A93) | I93: =COUNTIFS('Field Dictionary'!$A:$A,A93,'Field Dictionary'!$T:$T,"Custom") | J93: =COUNTIF('Record Types'!$A:$A,A93) | K93: =COUNTIF(Relationships!$A:$A,A93) | L93: 77 | M93: 4 | N93: 17 | O93: =SUM(L93:N93) | P93: =COUNTIF(Relationships!$F:$F,A93) | Q93: =IF(AND(O93=0,E93="Custom object"),"No code references","") | R93: ERD - PVL Licenses
A94: License__c | B94: License | C94: Licenses | D94: PVL: Licenses & License Types | E94: Custom object | F94: PacPoint-FT070119 - Created for PVL phase 1 | G94: ReadWrite | H94: =COUNTIF('Field Dictionary'!$A:$A,A94) | I94: =COUNTIFS('Field Dictionary'!$A:$A,A94,'Field Dictionary'!$T:$T,"Custom") | J94: =COUNTIF('Record Types'!$A:$A,A94) | K94: =COUNTIF(Relationships!$A:$A,A94) | L94: 123 | M94: 5 | N94: 66 | O94: =SUM(L94:N94) | P94: =COUNTIF(Relationships!$F:$F,A94) | Q94: =IF(AND(O94=0,E94="Custom object"),"No code references","") | R94: ERD - PVL Licenses
A95: MakeandSupplier__c | B95: Make and Supplier | C95: Makes and Suppliers | D95: PVL: Licenses & License Types | E95: Custom object | F95: Pac Point-DN011520 - Created for PVL Sprint 3 Phase 1 | G95: ReadWrite | H95: =COUNTIF('Field Dictionary'!$A:$A,A95) | I95: =COUNTIFS('Field Dictionary'!$A:$A,A95,'Field Dictionary'!$T:$T,"Custom") | J95: =COUNTIF('Record Types'!$A:$A,A95) | K95: =COUNTIF(Relationships!$A:$A,A95) | L95: 0 | M95: 0 | N95: 0 | O95: =SUM(L95:N95) | P95: =COUNTIF(Relationships!$F:$F,A95) | Q95: =IF(AND(O95=0,E95="Custom object"),"No code references","") | R95: ERD - PVL Licenses
A96: Notification__c | B96: Notification | C96: Notifications | D96: PVL: Licenses & License Types | E96: Custom object | F96: PacPoint: AZ00008158PVL2 | G96: ReadWrite | H96: =COUNTIF('Field Dictionary'!$A:$A,A96) | I96: =COUNTIFS('Field Dictionary'!$A:$A,A96,'Field Dictionary'!$T:$T,"Custom") | J96: =COUNTIF('Record Types'!$A:$A,A96) | K96: =COUNTIF(Relationships!$A:$A,A96) | L96: 35 | M96: 0 | N96: 9 | O96: =SUM(L96:N96) | P96: =COUNTIF(Relationships!$F:$F,A96) | Q96: =IF(AND(O96=0,E96="Custom object"),"No code references","") | R96: ERD - PVL Licenses
A97: PVL_Express_Change_Broker_Form__c | B97: Express Change Broker | C97: Express Change Broker | D97: PVL: Licenses & License Types | E97: Custom object | G97: ReadWrite | H97: =COUNTIF('Field Dictionary'!$A:$A,A97) | I97: =COUNTIFS('Field Dictionary'!$A:$A,A97,'Field Dictionary'!$T:$T,"Custom") | J97: =COUNTIF('Record Types'!$A:$A,A97) | K97: =COUNTIF(Relationships!$A:$A,A97) | L97: 0 | M97: 0 | N97: 3 | O97: =SUM(L97:N97) | P97: =COUNTIF(Relationships!$F:$F,A97) | Q97: =IF(AND(O97=0,E97="Custom object"),"No code references","") | R97: ERD - PVL Licenses
A98: RenewalScanningResults__c | B98: Renewal Scanning Results | C98: Renewal Scanning Results | D98: PVL: Licenses & License Types | E98: Custom object | F98: PacPoint-MV102419 - Created for PVL phase 1 | G98: ReadWrite | H98: =COUNTIF('Field Dictionary'!$A:$A,A98) | I98: =COUNTIFS('Field Dictionary'!$A:$A,A98,'Field Dictionary'!$T:$T,"Custom") | J98: =COUNTIF('Record Types'!$A:$A,A98) | K98: =COUNTIF(Relationships!$A:$A,A98) | L98: 5 | M98: 0 | N98: 0 | O98: =SUM(L98:N98) | P98: =COUNTIF(Relationships!$F:$F,A98) | Q98: =IF(AND(O98=0,E98="Custom object"),"No code references","") | R98: ERD - PVL Licenses
A99: Requirements__c | B99: Requirement | C99: Requirements | D99: PVL: Licenses & License Types | E99: Custom object | F99: PacPoint-IC072419- Created for PVL phase 1 | G99: ReadWrite | H99: =COUNTIF('Field Dictionary'!$A:$A,A99) | I99: =COUNTIFS('Field Dictionary'!$A:$A,A99,'Field Dictionary'!$T:$T,"Custom") | J99: =COUNTIF('Record Types'!$A:$A,A99) | K99: =COUNTIF(Relationships!$A:$A,A99) | L99: 5 | M99: 0 | N99: 0 | O99: =SUM(L99:N99) | P99: =COUNTIF(Relationships!$F:$F,A99) | Q99: =IF(AND(O99=0,E99="Custom object"),"No code references","") | R99: ERD - PVL Licenses
A100: Suspense__c | B100: Suspense | C100: Suspense | D100: PVL: Licenses & License Types | E100: Custom object | G100: ControlledByParent | H100: =COUNTIF('Field Dictionary'!$A:$A,A100) | I100: =COUNTIFS('Field Dictionary'!$A:$A,A100,'Field Dictionary'!$T:$T,"Custom") | J100: =COUNTIF('Record Types'!$A:$A,A100) | K100: =COUNTIF(Relationships!$A:$A,A100) | L100: 12 | M100: 0 | N100: 5 | O100: =SUM(L100:N100) | P100: =COUNTIF(Relationships!$F:$F,A100) | Q100: =IF(AND(O100=0,E100="Custom object"),"No code references","") | R100: ERD - PVL Licenses
A101: ContinuingEducation__c | B101: Continuing Education | C101: Continuing Education | D101: PVL: Exams & Continuing Education | E101: Custom object | F101: PacPoint-FT080719- Created for PVL phase 1 | G101: ReadWrite | H101: =COUNTIF('Field Dictionary'!$A:$A,A101) | I101: =COUNTIFS('Field Dictionary'!$A:$A,A101,'Field Dictionary'!$T:$T,"Custom") | J101: =COUNTIF('Record Types'!$A:$A,A101) | K101: =COUNTIF(Relationships!$A:$A,A101) | L101: 1 | M101: 0 | N101: 1 | O101: =SUM(L101:N101) | P101: =COUNTIF(Relationships!$F:$F,A101) | Q101: =IF(AND(O101=0,E101="Custom object"),"No code references","") | R101: ERD - PVL Exams & CE
...

Sheet Field Dictionary
A1: Field Dictionary
A2: 6,673 fields. Custom objects from source metadata; Account, Contact, Case and pymt__PaymentX__c from a read-only describe of the DCCA sandbox (all standard + custom fields).
A3: ‹ Back to README
A5: Object API Name | B5: Object Label | C5: Domain | D5: Field API Name | E5: Field Label | F5: Data Type | G5: Length / Precision | H5: Required | I5: Unique | J5: External ID | K5: Reference To | L5: Relationship Name | M5: Relationship Type | N5: Picklist Values / Value Set | O5: Formula / Roll-up | P5: Default Value | Q5: Description | R5: Help Text | S5: History Tracked | T5: Standard / Custom | U5: Files Referencing Field | V5: Source
A6: Account | B6: Account | C6: Core: Account · Contact · Case | D6: AccountNumber | E6: Account Number | F6: Text | G6: 40 | T6: Standard | V6: Org describe (DCCA sandbox)
A7: Account | B7: Account | C7: Core: Account · Contact · Case | D7: AccountSource | E7: Account Source | F7: Picklist | G7: 255 | N7: Advertisement; Customer Event; Employee Referral; Google AdWords; Other; Partner; Purchased List; Trade Show; Webinar; Website | T7: Standard | V7: Org describe (DCCA sandbox)
A8: Account | B8: Account | C8: Core: Account · Contact · Case | D8: AnnualRevenue | E8: Annual Revenue | F8: Currency | G8: 18,0 | T8: Standard | V8: Org describe (DCCA sandbox)
A9: Account | B9: Account | C9: Core: Account · Contact · Case | D9: BillingAddress | E9: Billing Address | F9: Address | T9: Standard | V9: Org describe (DCCA sandbox)
A10: Account | B10: Account | C10: Core: Account · Contact · Case | D10: BillingCity | E10: Billing City | F10: Text | G10: 40 | T10: Standard | V10: Org describe (DCCA sandbox)
A11: Account | B11: Account | C11: Core: Account · Contact · Case | D11: BillingCountry | E11: Billing Country | F11: Text | G11: 80 | T11: Standard | V11: Org describe (DCCA sandbox)
A12: Account | B12: Account | C12: Core: Account · Contact · Case | D12: BillingCountryCode | E12: Billing Country Code | F12: Picklist | G12: 10 | N12: AF; AX; AL; DZ; AS; AD; AO; AI; AQ; AG; AR; AM; AW; AU; AT; AZ; BS; BH; BD; BB; BY; BE; BZ; BJ; BM; BT; BO; BQ; BA; BW; BV; BR; IO; BN; BG; BF; BI; KH; CM; CA; CV; KY; CF; TD; CE; CL; CN; TW; CX; CC; CO; KM; CG; CD; CK; CR; CI; HR; CU; CP; CW; CY; CZ; DK; DJ; DM; DO; TP; EC; EG; SV; GQ; ER; EE; ET; FK; FO; FJ; FI; FR; GF; PF; TF; GA; GM; GE; DE; GH; GI; GR; GL; GD; GP; GU; GT; GG; GN; GW; GY; HT; HM; VA; HN; HK; HU; IS; IN; ID; IR; IQ; IE; IG; IM; IL; IT; JR; JM; JP; JE; JO; KZ; KE; KI; KP; KR; KW; KG; LA; LV; LB; LS; LR; LY; LI; LT; LU; MO; MK; MG; MW; MY; MV; ML; MT; MH; MQ; MR; MU; YT; MX; FM; MD; MC; MN; ME; MS; MA; MZ; MM; NA; NR; NP; NL; AN; NC; NZ; NI; NE; NG; NU; NF; NO; OM; PK; PS; PA; PG; PY; PE; PH; PN; PL; PT; PR; QA; RE; RO; RU; RW; BL; SH; KN; LC; MF; PM; VC; WS; SM; ST; SA; SN; RS; SC; SL; SG; SX; SK; SI; SB; SO; ZA; GS; SS; ES; LK; SD; SR; SJ; SZ; SE; CH; SY; TJ; TZ; TH; TL; TG; TK; TO; TT; TN; TR; TM; TC; TV; UG; UA; AE; GB; US; UM; UY; UZ; VU; VE; VN; VG; VI; WF; EH; YE; YU; ZM; ZW | P12: US | T12: Standard | V12: Org describe (DCCA sandbox)
A13: Account | B13: Account | C13: Core: Account · Contact · Case | D13: BillingGeocodeAccuracy | E13: Billing Geocode Accuracy | F13: Picklist | G13: 40 | N13: Address; NearAddress; Block; Street; ExtendedZip; Zip; Neighborhood; City; County; State; Unknown | T13: Standard | V13: Org describe (DCCA sandbox)
A14: Account | B14: Account | C14: Core: Account · Contact · Case | D14: BillingLatitude | E14: Billing Latitude | F14: Number | G14: 18,15 | T14: Standard | V14: Org describe (DCCA sandbox)
A15: Account | B15: Account | C15: Core: Account · Contact · Case | D15: BillingLongitude | E15: Billing Longitude | F15: Number | G15: 18,15 | T15: Standard | V15: Org describe (DCCA sandbox)
A16: Account | B16: Account | C16: Core: Account · Contact · Case | D16: BillingPostalCode | E16: Billing Zip/Postal Code | F16: Text | G16: 20 | T16: Standard | V16: Org describe (DCCA sandbox)
A17: Account | B17: Account | C17: Core: Account · Contact · Case | D17: BillingState | E17: Billing State/Province | F17: Text | G17: 80 | T17: Standard | V17: Org describe (DCCA sandbox)
A18: Account | B18: Account | C18: Core: Account · Contact · Case | D18: BillingStateCode | E18: Billing State/Province Code | F18: Picklist | G18: 10 | N18: AC; AG; AG; AL; AL; AK; AB; AL; AP; AM; AS; AN; AN; AP; 34; AO; AR; AZ; AR; AA; AE; AP; AR; AP; AS; AT; ACT; AV; BA; BC; BS; BA; BT; 11; BL; BN; BG; BI; BR; BO; BZ; BS; BR; BC; CA; CA; CL; CM; CB; CI; CW; CE; CT; CZ; CN; CE; CH; CT; CS; CH; CH; 71; 50; CE; CO; CL; CO; CO; CT; CO; CS; CR; KR; CN; DN; DD; DE; DL; DC; DF; DL; D; DG; EN; ES; DF; FM; FM; FE; FI; FL; FG; FC; FR; 35; G; 62; GE; GA; GA; GO; GO; GR; GU; GT; 44; 45; GR; 52; GJ; 46; HR; HI; 13; 23; 41; HG; HP; 91; 42; 43; ID; IL; IM; IN; IA; IS; JA; JK; JH; 32; 36; 22; KS; KA; KY; KL; KY; KE; KK; AQ; LD; LS; SP; LT; LE; LC; LM; 21; LK; LI; LO; LD; LA; LH; LU; 92; MC; MP; MH; ME; MN; MB; MN; MA; MH; MD; MS; MA; MT; MT; MS; MO; MH; VS; ML; ME; ME; MI; MI; MI; MG; MN; MS; MO; MZ; MO; MN; MT; MB; MO; NL; NA; NA; NE; 15; NV; NB; NL; NH; NJ; NM; NSW; NY; 64; NC; ND; MP; NT; NT; NO; NS; NL; NU; NU; OA; OR; OY; OG; OH; OK; OT; ON; OR; OR; PD; PW; PA; PA; PB; PR; PR; PV; PA; PE; PG; PU; PE; PC; PI; PI; PT; PN; PZ; PO; PE; PY; PB; PR; PB; 63; QC; QLD; QE; QR; RG; RJ; RA; RC; RE; RI; RI; RN; RJ; RN; RS; RM; RO; RR; RN; RO; SA; SL; SC; SP; SK; SS; SV; SE; 61; 37; 31; 14; 51; SI; SK; SI; SO; SO; SO; SA; SC; SD; SR; TB; TM; TN; TA; TAS; TN; TE; TR; TX; 12; TA; TL; TO; TP; TN; TV; TS; TR; TO; UD; UM; VI; UT; UT; UP; VA; VE; VE; VB; VC; VT; VR; VV; VI; VIC; VA; VT; WA; WD; WB; WA; WH; WV; WX; WW; WI; WY; 65; 54; YU; YT; 53; ZA; 33 | T18: Standard | V18: Org describe (DCCA sandbox)
A19: Account | B19: Account | C19: Core: Account · Contact · Case | D19: BillingStreet | E19: Billing Street | F19: TextArea | G19: 255 | T19: Standard | V19: Org describe (DCCA sandbox)
A20: Account | B20: Account | C20: Core: Account · Contact · Case | D20: CreatedById | E20: Created By ID | F20: Lookup | G20: 18 | K20: User | L20: CreatedBy | M20: Lookup | T20: Standard | V20: Org describe (DCCA sandbox)
A21: Account | B21: Account | C21: Core: Account · Contact · Case | D21: CreatedDate | E21: Created Date | F21: DateTime | T21: Standard | V21: Org describe (DCCA sandbox)
A22: Account | B22: Account | C22: Core: Account · Contact · Case | D22: Description | E22: Account Description | F22: TextArea | G22: 32000 | T22: Standard | V22: Org describe (DCCA sandbox)
A23: Account | B23: Account | C23: Core: Account · Contact · Case | D23: Fax | E23: Account Fax | F23: Phone | G23: 40 | T23: Standard | V23: Org describe (DCCA sandbox)
A24: Account | B24: Account | C24: Core: Account · Contact · Case | D24: FirstName | E24: First Name | F24: Text | G24: 40 | T24: Standard | V24: Org describe (DCCA sandbox)
A25: Account | B25: Account | C25: Core: Account · Contact · Case | D25: Id | E25: Account ID | F25: Id | G25: 18 | T25: Standard | V25: Org describe (DCCA sandbox)
A26: Account | B26: Account | C26: Core: Account · Contact · Case | D26: Industry | E26: Industry | F26: Picklist | G26: 255 | N26: Agriculture; Apparel; Banking; Biotechnology; Chemicals; Communications; Construction; Consulting; Education; Electronics; Energy; Engineering; Entertainment; Environmental; Finance; Food & Beverage; Government; Healthcare; Hospitality; Insurance; Machinery; Manufacturing; Media; Not For Profit; Other; Recreation; Retail; Shipping; Technology; Telecommunications; Transportation; Utilities | T26: Standard | V26: Org describe (DCCA sandbox)
A27: Account | B27: Account | C27: Core: Account · Contact · Case | D27: IsCustomerPortal | E27: Customer Portal Account | F27: Checkbox | T27: Standard | V27: Org describe (DCCA sandbox)
A28: Account | B28: Account | C28: Core: Account · Contact · Case | D28: IsDeleted | E28: Deleted | F28: Checkbox | T28: Standard | V28: Org describe (DCCA sandbox)
A29: Account | B29: Account | C29: Core: Account · Contact · Case | D29: IsPersonAccount | E29: Is Person Account | F29: Checkbox | T29: Standard | V29: Org describe (DCCA sandbox)
A30: Account | B30: Account | C30: Core: Account · Contact · Case | D30: IsPriorityRecord | E30: Important | F30: Checkbox | T30: Standard | V30: Org describe (DCCA sandbox)
A31: Account | B31: Account | C31: Core: Account · Contact · Case | D31: Jigsaw | E31: Data.com Key | F31: Text | G31: 20 | T31: Standard | V31: Org describe (DCCA sandbox)
A32: Account | B32: Account | C32: Core: Account · Contact · Case | D32: JigsawCompanyId | E32: Jigsaw Company ID | F32: Text | G32: 20 | L32: JigsawCompany | T32: Standard | V32: Org describe (DCCA sandbox)
A33: Account | B33: Account | C33: Core: Account · Contact · Case | D33: LastActivityDate | E33: Last Activity | F33: Date | T33: Standard | V33: Org describe (DCCA sandbox)
A34: Account | B34: Account | C34: Core: Account · Contact · Case | D34: LastModifiedById | E34: Last Modified By ID | F34: Lookup | G34: 18 | K34: User | L34: LastModifiedBy | M34: Lookup | T34: Standard | V34: Org describe (DCCA sandbox)
A35: Account | B35: Account | C35: Core: Account · Contact · Case | D35: LastModifiedDate | E35: Last Modified Date | F35: DateTime | T35: Standard | V35: Org describe (DCCA sandbox)
A36: Account | B36: Account | C36: Core: Account · Contact · Case | D36: LastName | E36: Last Name | F36: Text | G36: 80 | T36: Standard | V36: Org describe (DCCA sandbox)
A37: Account | B37: Account | C37: Core: Account · Contact · Case | D37: LastReferencedDate | E37: Last Referenced Date | F37: DateTime | T37: Standard | V37: Org describe (DCCA sandbox)
A38: Account | B38: Account | C38: Core: Account · Contact · Case | D38: LastViewedDate | E38: Last Viewed Date | F38: DateTime | T38: Standard | V38: Org describe (DCCA sandbox)
A39: Account | B39: Account | C39: Core: Account · Contact · Case | D39: MasterRecordId | E39: Master Record ID | F39: Lookup | G39: 18 | K39: Account | L39: MasterRecord | M39: Lookup | T39: Standard | V39: Org describe (DCCA sandbox)
A40: Account | B40: Account | C40: Core: Account · Contact · Case | D40: MiddleName | E40: Middle Name | F40: Text | G40: 40 | T40: Standard | V40: Org describe (DCCA sandbox)
A41: Account | B41: Account | C41: Core: Account · Contact · Case | D41: Name | E41: Account Name | F41: Text | G41: 255 | T41: Standard | V41: Org describe (DCCA sandbox)
A42: Account | B42: Account | C42: Core: Account · Contact · Case | D42: NumberOfEmployees | E42: Employees | F42: Number | T42: Standard | V42: Org describe (DCCA sandbox)
A43: Account | B43: Account | C43: Core: Account · Contact · Case | D43: OwnerId | E43: Owner ID | F43: Lookup | G43: 18 | K43: User | L43: Owner | M43: Lookup | T43: Standard | V43: Org describe (DCCA sandbox)
A44: Account | B44: Account | C44: Core: Account · Contact · Case | D44: Ownership | E44: Ownership | F44: Picklist | G44: 255 | N44: Public; Private; Subsidiary; Other | T44: Standard | V44: Org describe (DCCA sandbox)
A45: Account | B45: Account | C45: Core: Account · Contact · Case | D45: ParentId | E45: Parent Account ID | F45: Lookup | G45: 18 | K45: Account | L45: Parent | M45: Lookup | T45: Standard | V45: Org describe (DCCA sandbox)
A46: Account | B46: Account | C46: Core: Account · Contact · Case | D46: PersonBirthdate | E46: Birthdate | F46: Date | T46: Standard | V46: Org describe (DCCA sandbox)
A47: Account | B47: Account | C47: Core: Account · Contact · Case | D47: PersonContactId | E47: Contact ID | F47: Lookup | G47: 18 | K47: Contact | L47: PersonContact | M47: Lookup | T47: Standard | V47: Org describe (DCCA sandbox)
A48: Account | B48: Account | C48: Core: Account · Contact · Case | D48: PersonDepartment | E48: Department | F48: Text | G48: 80 | T48: Standard | V48: Org describe (DCCA sandbox)
A49: Account | B49: Account | C49: Core: Account · Contact · Case | D49: PersonEmail | E49: Email | F49: Email | G49: 80 | T49: Standard | V49: Org describe (DCCA sandbox)
A50: Account | B50: Account | C50: Core: Account · Contact · Case | D50: PersonEmailBouncedDate | E50: Email Bounced Date | F50: DateTime | T50: Standard | V50: Org describe (DCCA sandbox)
A51: Account | B51: Account | C51: Core: Account · Contact · Case | D51: PersonEmailBouncedReason | E51: Email Bounced Reason | F51: Text | G51: 255 | T51: Standard | V51: Org describe (DCCA sandbox)
A52: Account | B52: Account | C52: Core: Account · Contact · Case | D52: PersonGenderIdentity | E52: Gender Identity | F52: Picklist | G52: 255 | N52: Male; Female; Nonbinary; Not Listed | T52: Standard | V52: Org describe (DCCA sandbox)
A53: Account | B53: Account | C53: Core: Account · Contact · Case | D53: PersonIndividualId | E53: Individual ID | F53: Lookup | G53: 18 | K53: Individual | L53: PersonIndividual | M53: Lookup | T53: Standard | V53: Org describe (DCCA sandbox)
A54: Account | B54: Account | C54: Core: Account · Contact · Case | D54: PersonLastCURequestDate | E54: Last Stay-in-Touch Request Date | F54: DateTime | T54: Standard | V54: Org describe (DCCA sandbox)
A55: Account | B55: Account | C55: Core: Account · Contact · Case | D55: PersonLastCUUpdateDate | E55: Last Stay-in-Touch Save Date | F55: DateTime | T55: Standard | V55: Org describe (DCCA sandbox)
A56: Account | B56: Account | C56: Core: Account · Contact · Case | D56: PersonMailingAddress | E56: Address | F56: Address | T56: Standard | V56: Org describe (DCCA sandbox)
A57: Account | B57: Account | C57: Core: Account · Contact · Case | D57: PersonMailingCity | E57: City | F57: Text | G57: 40 | T57: Standard | V57: Org describe (DCCA sandbox)
A58: Account | B58: Account | C58: Core: Account · Contact · Case | D58: PersonMailingCountry | E58: Country | F58: Text | G58: 80 | T58: Standard | V58: Org describe (DCCA sandbox)
A59: Account | B59: Account | C59: Core: Account · Contact · Case | D59: PersonMailingCountryCode | E59: Country Code | F59: Picklist | G59: 10 | N59: AF; AX; AL; DZ; AS; AD; AO; AI; AQ; AG; AR; AM; AW; AU; AT; AZ; BS; BH; BD; BB; BY; BE; BZ; BJ; BM; BT; BO; BQ; BA; BW; BV; BR; IO; BN; BG; BF; BI; KH; CM; CA; CV; KY; CF; TD; CE; CL; CN; TW; CX; CC; CO; KM; CG; CD; CK; CR; CI; HR; CU; CP; CW; CY; CZ; DK; DJ; DM; DO; TP; EC; EG; SV; GQ; ER; EE; ET; FK; FO; FJ; FI; FR; GF; PF; TF; GA; GM; GE; DE; GH; GI; GR; GL; GD; GP; GU; GT; GG; GN; GW; GY; HT; HM; VA; HN; HK; HU; IS; IN; ID; IR; IQ; IE; IG; IM; IL; IT; JR; JM; JP; JE; JO; KZ; KE; KI; KP; KR; KW; KG; LA; LV; LB; LS; LR; LY; LI; LT; LU; MO; MK; MG; MW; MY; MV; ML; MT; MH; MQ; MR; MU; YT; MX; FM; MD; MC; MN; ME; MS; MA; MZ; MM; NA; NR; NP; NL; AN; NC; NZ; NI; NE; NG; NU; NF; NO; OM; PK; PS; PA; PG; PY; PE; PH; PN; PL; PT; PR; QA; RE; RO; RU; RW; BL; SH; KN; LC; MF; PM; VC; WS; SM; ST; SA; SN; RS; SC; SL; SG; SX; SK; SI; SB; SO; ZA; GS; SS; ES; LK; SD; SR; SJ; SZ; SE; CH; SY; TJ; TZ; TH; TL; TG; TK; TO; TT; TN; TR; TM; TC; TV; UG; UA; AE; GB; US; UM; UY; UZ; VU; VE; VN; VG; VI; WF; EH; YE; YU; ZM; ZW | P59: US | T59: Standard | V59: Org describe (DCCA sandbox)
A60: Account | B60: Account | C60: Core: Account · Contact · Case | D60: PersonMailingGeocodeAccuracy | E60: Mailing Geocode Accuracy | F60: Picklist | G60: 40 | N60: Address; NearAddress; Block; Street; ExtendedZip; Zip; Neighborhood; City; County; State; Unknown | T60: Standard | V60: Org describe (DCCA sandbox)
A61: Account | B61: Account | C61: Core: Account · Contact · Case | D61: PersonMailingLatitude | E61: Latitude | F61: Number | G61: 18,15 | T61: Standard | V61: Org describe (DCCA sandbox)
A62: Account | B62: Account | C62: Core: Account · Contact · Case | D62: PersonMailingLongitude | E62: Longitude | F62: Number | G62: 18,15 | T62: Standard | V62: Org describe (DCCA sandbox)
A63: Account | B63: Account | C63: Core: Account · Contact · Case | D63: PersonMailingPostalCode | E63: Zip/Postal Code | F63: Text | G63: 20 | T63: Standard | V63: Org describe (DCCA sandbox)
A64: Account | B64: Account | C64: Core: Account · Contact · Case | D64: PersonMailingState | E64: State/Province | F64: Text | G64: 80 | T64: Standard | V64: Org describe (DCCA sandbox)
A65: Account | B65: Account | C65: Core: Account · Contact · Case | D65: PersonMailingStateCode | E65: State/Province Code | F65: Picklist | G65: 10 | N65: AC; AG; AG; AL; AL; AK; AB; AL; AP; AM; AS; AN; AN; AP; 34; AO; AR; AZ; AR; AA; AE; AP; AR; AP; AS; AT; ACT; AV; BA; BC; BS; BA; BT; 11; BL; BN; BG; BI; BR; BO; BZ; BS; BR; BC; CA; CA; CL; CM; CB; CI; CW; CE; CT; CZ; CN; CE; CH; CT; CS; CH; CH; 71; 50; CE; CO; CL; CO; CO; CT; CO; CS; CR; KR; CN; DN; DD; DE; DL; DC; DF; DL; D; DG; EN; ES; DF; FM; FM; FE; FI; FL; FG; FC; FR; 35; G; 62; GE; GA; GA; GO; GO; GR; GU; GT; 44; 45; GR; 52; GJ; 46; HR; HI; 13; 23; 41; HG; HP; 91; 42; 43; ID; IL; IM; IN; IA; IS; JA; JK; JH; 32; 36; 22; KS; KA; KY; KL; KY; KE; KK; AQ; LD; LS; SP; LT; LE; LC; LM; 21; LK; LI; LO; LD; LA; LH; LU; 92; MC; MP; MH; ME; MN; MB; MN; MA; MH; MD; MS; MA; MT; MT; MS; MO; MH; VS; ML; ME; ME; MI; MI; MI; MG; MN; MS; MO; MZ; MO; MN; MT; MB; MO; NL; NA; NA; NE; 15; NV; NB; NL; NH; NJ; NM; NSW; NY; 64; NC; ND; MP; NT; NT; NO; NS; NL; NU; NU; OA; OR; OY; OG; OH; OK; OT; ON; OR; OR; PD; PW; PA; PA; PB; PR; PR; PV; PA; PE; PG; PU; PE; PC; PI; PI; PT; PN; PZ; PO; PE; PY; PB; PR; PB; 63; QC; QLD; QE; QR; RG; RJ; RA; RC; RE; RI; RI; RN; RJ; RN; RS; RM; RO; RR; RN; RO; SA; SL; SC; SP; SK; SS; SV; SE; 61; 37; 31; 14; 51; SI; SK; SI; SO; SO; SO; SA; SC; SD; SR; TB; TM; TN; TA; TAS; TN; TE; TR; TX; 12; TA; TL; TO; TP; TN; TV; TS; TR; TO; UD; UM; VI; UT; UT; UP; VA; VE; VE; VB; VC; VT; VR; VV; VI; VIC; VA; VT; WA; WD; WB; WA; WH; WV; WX; WW; WI; WY; 65; 54; YU; YT; 53; ZA; 33 | T65: Standard | V65: Org describe (DCCA sandbox)
A66: Account | B66: Account | C66: Core: Account · Contact · Case | D66: PersonMailingStreet | E66: Street | F66: TextArea | G66: 255 | T66: Standard | V66: Org describe (DCCA sandbox)
A67: Account | B67: Account | C67: Core: Account · Contact · Case | D67: PersonMobilePhone | E67: Mobile | F67: Phone | G67: 40 | T67: Standard | V67: Org describe (DCCA sandbox)
A68: Account | B68: Account | C68: Core: Account · Contact · Case | D68: PersonOtherAddress | E68: Other Address | F68: Address | T68: Standard | V68: Org describe (DCCA sandbox)
A69: Account | B69: Account | C69: Core: Account · Contact · Case | D69: PersonOtherCity | E69: Other City | F69: Text | G69: 40 | T69: Standard | V69: Org describe (DCCA sandbox)
A70: Account | B70: Account | C70: Core: Account · Contact · Case | D70: PersonOtherCountry | E70: Other Country | F70: Text | G70: 80 | T70: Standard | V70: Org describe (DCCA sandbox)
A71: Account | B71: Account | C71: Core: Account · Contact · Case | D71: PersonOtherCountryCode | E71: Other Country Code | F71: Picklist | G71: 10 | N71: AF; AX; AL; DZ; AS; AD; AO; AI; AQ; AG; AR; AM; AW; AU; AT; AZ; BS; BH; BD; BB; BY; BE; BZ; BJ; BM; BT; BO; BQ; BA; BW; BV; BR; IO; BN; BG; BF; BI; KH; CM; CA; CV; KY; CF; TD; CE; CL; CN; TW; CX; CC; CO; KM; CG; CD; CK; CR; CI; HR; CU; CP; CW; CY; CZ; DK; DJ; DM; DO; TP; EC; EG; SV; GQ; ER; EE; ET; FK; FO; FJ; FI; FR; GF; PF; TF; GA; GM; GE; DE; GH; GI; GR; GL; GD; GP; GU; GT; GG; GN; GW; GY; HT; HM; VA; HN; HK; HU; IS; IN; ID; IR; IQ; IE; IG; IM; IL; IT; JR; JM; JP; JE; JO; KZ; KE; KI; KP; KR; KW; KG; LA; LV; LB; LS; LR; LY; LI; LT; LU; MO; MK; MG; MW; MY; MV; ML; MT; MH; MQ; MR; MU; YT; MX; FM; MD; MC; MN; ME; MS; MA; MZ; MM; NA; NR; NP; NL; AN; NC; NZ; NI; NE; NG; NU; NF; NO; OM; PK; PS; PA; PG; PY; PE; PH; PN; PL; PT; PR; QA; RE; RO; RU; RW; BL; SH; KN; LC; MF; PM; VC; WS; SM; ST; SA; SN; RS; SC; SL; SG; SX; SK; SI; SB; SO; ZA; GS; SS; ES; LK; SD; SR; SJ; SZ; SE; CH; SY; TJ; TZ; TH; TL; TG; TK; TO; TT; TN; TR; TM; TC; TV; UG; UA; AE; GB; US; UM; UY; UZ; VU; VE; VN; VG; VI; WF; EH; YE; YU; ZM; ZW | P71: US | T71: Standard | V71: Org describe (DCCA sandbox)
A72: Account | B72: Account | C72: Core: Account · Contact · Case | D72: PersonOtherGeocodeAccuracy | E72: Other Geocode Accuracy | F72: Picklist | G72: 40 | N72: Address; NearAddress; Block; Street; ExtendedZip; Zip; Neighborhood; City; County; State; Unknown | T72: Standard | V72: Org describe (DCCA sandbox)
A73: Account | B73: Account | C73: Core: Account · Contact · Case | D73: PersonOtherLatitude | E73: Other Latitude | F73: Number | G73: 18,15 | T73: Standard | V73: Org describe (DCCA sandbox)
A74: Account | B74: Account | C74: Core: Account · Contact · Case | D74: PersonOtherLongitude | E74: Other Longitude | F74: Number | G74: 18,15 | T74: Standard | V74: Org describe (DCCA sandbox)
A75: Account | B75: Account | C75: Core: Account · Contact · Case | D75: PersonOtherPhone | E75: Other Phone | F75: Phone | G75: 40 | T75: Standard | V75: Org describe (DCCA sandbox)
A76: Account | B76: Account | C76: Core: Account · Contact · Case | D76: PersonOtherPostalCode | E76: Other Zip/Postal Code | F76: Text | G76: 20 | T76: Standard | V76: Org describe (DCCA sandbox)
A77: Account | B77: Account | C77: Core: Account · Contact · Case | D77: PersonOtherState | E77: Other State/Province | F77: Text | G77: 80 | T77: Standard | V77: Org describe (DCCA sandbox)
A78: Account | B78: Account | C78: Core: Account · Contact · Case | D78: PersonOtherStateCode | E78: Other State/Province Code | F78: Picklist | G78: 10 | N78: AC; AG; AG; AL; AL; AK; AB; AL; AP; AM; AS; AN; AN; AP; 34; AO; AR; AZ; AR; AA; AE; AP; AR; AP; AS; AT; ACT; AV; BA; BC; BS; BA; BT; 11; BL; BN; BG; BI; BR; BO; BZ; BS; BR; BC; CA; CA; CL; CM; CB; CI; CW; CE; CT; CZ; CN; CE; CH; CT; CS; CH; CH; 71; 50; CE; CO; CL; CO; CO; CT; CO; CS; CR; KR; CN; DN; DD; DE; DL; DC; DF; DL; D; DG; EN; ES; DF; FM; FM; FE; FI; FL; FG; FC; FR; 35; G; 62; GE; GA; GA; GO; GO; GR; GU; GT; 44; 45; GR; 52; GJ; 46; HR; HI; 13; 23; 41; HG; HP; 91; 42; 43; ID; IL; IM; IN; IA; IS; JA; JK; JH; 32; 36; 22; KS; KA; KY; KL; KY; KE; KK; AQ; LD; LS; SP; LT; LE; LC; LM; 21; LK; LI; LO; LD; LA; LH; LU; 92; MC; MP; MH; ME; MN; MB; MN; MA; MH; MD; MS; MA; MT; MT; MS; MO; MH; VS; ML; ME; ME; MI; MI; MI; MG; MN; MS; MO; MZ; MO; MN; MT; MB; MO; NL; NA; NA; NE; 15; NV; NB; NL; NH; NJ; NM; NSW; NY; 64; NC; ND; MP; NT; NT; NO; NS; NL; NU; NU; OA; OR; OY; OG; OH; OK; OT; ON; OR; OR; PD; PW; PA; PA; PB; PR; PR; PV; PA; PE; PG; PU; PE; PC; PI; PI; PT; PN; PZ; PO; PE; PY; PB; PR; PB; 63; QC; QLD; QE; QR; RG; RJ; RA; RC; RE; RI; RI; RN; RJ; RN; RS; RM; RO; RR; RN; RO; SA; SL; SC; SP; SK; SS; SV; SE; 61; 37; 31; 14; 51; SI; SK; SI; SO; SO; SO; SA; SC; SD; SR; TB; TM; TN; TA; TAS; TN; TE; TR; TX; 12; TA; TL; TO; TP; TN; TV; TS; TR; TO; UD; UM; VI; UT; UT; UP; VA; VE; VE; VB; VC; VT; VR; VV; VI; VIC; VA; VT; WA; WD; WB; WA; WH; WV; WX; WW; WI; WY; 65; 54; YU; YT; 53; ZA; 33 | T78: Standard | V78: Org describe (DCCA sandbox)
A79: Account | B79: Account | C79: Core: Account · Contact · Case | D79: PersonOtherStreet | E79: Other Street | F79: TextArea | G79: 255 | T79: Standard | V79: Org describe (DCCA sandbox)
A80: Account | B80: Account | C80: Core: Account · Contact · Case | D80: PersonReportsToId | E80: Reports To ID | F80: Lookup | G80: 18 | K80: Contact | L80: PersonReportsTo | M80: Lookup | T80: Standard | V80: Org describe (DCCA sandbox)
A81: Account | B81: Account | C81: Core: Account · Contact · Case | D81: PersonTitle | E81: Title | F81: Text | G81: 80 | T81: Standard | V81: Org describe (DCCA sandbox)
A82: Account | B82: Account | C82: Core: Account · Contact · Case | D82: Phone | E82: Account Phone | F82: Phone | G82: 40 | T82: Standard | V82: Org describe (DCCA sandbox)
A83: Account | B83: Account | C83: Core: Account · Contact · Case | D83: PhotoUrl | E83: Photo URL | F83: Url | G83: 255 | T83: Standard | V83: Org describe (DCCA sandbox)
A84: Account | B84: Account | C84: Core: Account · Contact · Case | D84: Rating | E84: Account Rating | F84: Picklist | G84: 255 | N84: Hot; Warm; Cold | T84: Standard | V84: Org describe (DCCA sandbox)
A85: Account | B85: Account | C85: Core: Account · Contact · Case | D85: RecordTypeId | E85: Record Type ID | F85: Lookup | G85: 18 | K85: RecordType | L85: RecordType | M85: Lookup | T85: Standard | V85: Org describe (DCCA sandbox)
A86: Account | B86: Account | C86: Core: Account · Contact · Case | D86: Salutation | E86: Salutation | F86: Picklist | G86: 40 | N86: Mr.; Ms.; Mrs.; Dr.; Prof. | T86: Standard | V86: Org describe (DCCA sandbox)
A87: Account | B87: Account | C87: Core: Account · Contact · Case | D87: ShippingAddress | E87: Shipping Address | F87: Address | T87: Standard | V87: Org describe (DCCA sandbox)
A88: Account | B88: Account | C88: Core: Account · Contact · Case | D88: ShippingCity | E88: Shipping City | F88: Text | G88: 40 | T88: Standard | V88: Org describe (DCCA sandbox)
A89: Account | B89: Account | C89: Core: Account · Contact · Case | D89: ShippingCountry | E89: Shipping Country | F89: Text | G89: 80 | T89: Standard | V89: Org describe (DCCA sandbox)
A90: Account | B90: Account | C90: Core: Account · Contact · Case | D90: ShippingCountryCode | E90: Shipping Country Code | F90: Picklist | G90: 10 | N90: AF; AX; AL; DZ; AS; AD; AO; AI; AQ; AG; AR; AM; AW; AU; AT; AZ; BS; BH; BD; BB; BY; BE; BZ; BJ; BM; BT; BO; BQ; BA; BW; BV; BR; IO; BN; BG; BF; BI; KH; CM; CA; CV; KY; CF; TD; CE; CL; CN; TW; CX; CC; CO; KM; CG; CD; CK; CR; CI; HR; CU; CP; CW; CY; CZ; DK; DJ; DM; DO; TP; EC; EG; SV; GQ; ER; EE; ET; FK; FO; FJ; FI; FR; GF; PF; TF; GA; GM; GE; DE; GH; GI; GR; GL; GD; GP; GU; GT; GG; GN; GW; GY; HT; HM; VA; HN; HK; HU; IS; IN; ID; IR; IQ; IE; IG; IM; IL; IT; JR; JM; JP; JE; JO; KZ; KE; KI; KP; KR; KW; KG; LA; LV; LB; LS; LR; LY; LI; LT; LU; MO; MK; MG; MW; MY; MV; ML; MT; MH; MQ; MR; MU; YT; MX; FM; MD; MC; MN; ME; MS; MA; MZ; MM; NA; NR; NP; NL; AN; NC; NZ; NI; NE; NG; NU; NF; NO; OM; PK; PS; PA; PG; PY; PE; PH; PN; PL; PT; PR; QA; RE; RO; RU; RW; BL; SH; KN; LC; MF; PM; VC; WS; SM; ST; SA; SN; RS; SC; SL; SG; SX; SK; SI; SB; SO; ZA; GS; SS; ES; LK; SD; SR; SJ; SZ; SE; CH; SY; TJ; TZ; TH; TL; TG; TK; TO; TT; TN; TR; TM; TC; TV; UG; UA; AE; GB; US; UM; UY; UZ; VU; VE; VN; VG; VI; WF; EH; YE; YU; ZM; ZW | P90: US | T90: Standard | V90: Org describe (DCCA sandbox)
A91: Account | B91: Account | C91: Core: Account · Contact · Case | D91: ShippingGeocodeAccuracy | E91: Shipping Geocode Accuracy | F91: Picklist | G91: 40 | N91: Address; NearAddress; Block; Street; ExtendedZip; Zip; Neighborhood; City; County; State; Unknown | T91: Standard | V91: Org describe (DCCA sandbox)
A92: Account | B92: Account | C92: Core: Account · Contact · Case | D92: ShippingLatitude | E92: Shipping Latitude | F92: Number | G92: 18,15 | T92: Standard | V92: Org describe (DCCA sandbox)
A93: Account | B93: Account | C93: Core: Account · Contact · Case | D93: ShippingLongitude | E93: Shipping Longitude | F93: Number | G93: 18,15 | T93: Standard | V93: Org describe (DCCA sandbox)
A94: Account | B94: Account | C94: Core: Account · Contact · Case | D94: ShippingPostalCode | E94: Shipping Zip/Postal Code | F94: Text | G94: 20 | T94: Standard | V94: Org describe (DCCA sandbox)
A95: Account | B95: Account | C95: Core: Account · Contact · Case | D95: ShippingState | E95: Shipping State/Province | F95: Text | G95: 80 | T95: Standard | V95: Org describe (DCCA sandbox)
A96: Account | B96: Account | C96: Core: Account · Contact · Case | D96: ShippingStateCode | E96: Shipping State/Province Code | F96: Picklist | G96: 10 | N96: AC; AG; AG; AL; AL; AK; AB; AL; AP; AM; AS; AN; AN; AP; 34; AO; AR; AZ; AR; AA; AE; AP; AR; AP; AS; AT; ACT; AV; BA; BC; BS; BA; BT; 11; BL; BN; BG; BI; BR; BO; BZ; BS; BR; BC; CA; CA; CL; CM; CB; CI; CW; CE; CT; CZ; CN; CE; CH; CT; CS; CH; CH; 71; 50; CE; CO; CL; CO; CO; CT; CO; CS; CR; KR; CN; DN; DD; DE; DL; DC; DF; DL; D; DG; EN; ES; DF; FM; FM; FE; FI; FL; FG; FC; FR; 35; G; 62; GE; GA; GA; GO; GO; GR; GU; GT; 44; 45; GR; 52; GJ; 46; HR; HI; 13; 23; 41; HG; HP; 91; 42; 43; ID; IL; IM; IN; IA; IS; JA; JK; JH; 32; 36; 22; KS; KA; KY; KL; KY; KE; KK; AQ; LD; LS; SP; LT; LE; LC; LM; 21; LK; LI; LO; LD; LA; LH; LU; 92; MC; MP; MH; ME; MN; MB; MN; MA; MH; MD; MS; MA; MT; MT; MS; MO; MH; VS; ML; ME; ME; MI; MI; MI; MG; MN; MS; MO; MZ; MO; MN; MT; MB; MO; NL; NA; NA; NE; 15; NV; NB; NL; NH; NJ; NM; NSW; NY; 64; NC; ND; MP; NT; NT; NO; NS; NL; NU; NU; OA; OR; OY; OG; OH; OK; OT; ON; OR; OR; PD; PW; PA; PA; PB; PR; PR; PV; PA; PE; PG; PU; PE; PC; PI; PI; PT; PN; PZ; PO; PE; PY; PB; PR; PB; 63; QC; QLD; QE; QR; RG; RJ; RA; RC; RE; RI; RI; RN; RJ; RN; RS; RM; RO; RR; RN; RO; SA; SL; SC; SP; SK; SS; SV; SE; 61; 37; 31; 14; 51; SI; SK; SI; SO; SO; SO; SA; SC; SD; SR; TB; TM; TN; TA; TAS; TN; TE; TR; TX; 12; TA; TL; TO; TP; TN; TV; TS; TR; TO; UD; UM; VI; UT; UT; UP; VA; VE; VE; VB; VC; VT; VR; VV; VI; VIC; VA; VT; WA; WD; WB; WA; WH; WV; WX; WW; WI; WY; 65; 54; YU; YT; 53; ZA; 33 | T96: Standard | V96: Org describe (DCCA sandbox)
A97: Account | B97: Account | C97: Core: Account · Contact · Case | D97: ShippingStreet | E97: Shipping Street | F97: TextArea | G97: 255 | T97: Standard | V97: Org describe (DCCA sandbox)
A98: Account | B98: Account | C98: Core: Account · Contact · Case | D98: Sic | E98: SIC Code | F98: Text | G98: 20 | T98: Standard | V98: Org describe (DCCA sandbox)
A99: Account | B99: Account | C99: Core: Account · Contact · Case | D99: SicDesc | E99: SIC Description | F99: Text | G99: 80 | T99: Standard | V99: Org describe (DCCA sandbox)
A100: Account | B100: Account | C100: Core: Account · Contact · Case | D100: Site | E100: Account Site | F100: Text | G100: 80 | T100: Standard | V100: Org describe (DCCA sandbox)
A101: Account | B101: Account | C101: Core: Account · Contact · Case | D101: SourceSystemIdentifier | E101: Source System ID | F101: Text | G101: 85 | T101: Standard | V101: Org describe (DCCA sandbox)
...

Sheet Relationships
A1: Relationships
A2: Every lookup / master-detail / hierarchy field. Domains are looked up live from the Object Catalogue.
A3: ‹ Back to README
A5: Child Object | B5: Child Domain | C5: Field API Name | D5: Field Label | E5: Relationship Type | F5: Parent Object | G5: Parent Domain | H5: Child Relationship Name | I5: Required | J5: Crosses Domain | K5: Shown in ERD | L5: Source
A6: Account | B6: =IFERROR(INDEX('Object Catalogue'!$D:$D,MATCH(A6,'Object Catalogue'!$A:$A,0)),"Platform / managed") | C6: Contact__c | D6: Paying Contact | E6: Lookup | F6: Contact | G6: =IFERROR(INDEX('Object Catalogue'!$D:$D,MATCH(F6,'Object Catalogue'!$A:$A,0)),"Platform / managed") | H6: Contact__r | J6: =IF(B6=G6,"No","Yes") | K6: Yes | L6: Org describe (DCCA sandbox)
A7: Account | B7: =IFERROR(INDEX('Object Catalogue'!$D:$D,MATCH(A7,'Object Catalogue'!$A:$A,0)),"Platform / managed") | C7: MasterRecordId | D7: Master Record ID | E7: Lookup | F7: Account | G7: =IFERROR(INDEX('Object Catalogue'!$D:$D,MATCH(F7,'Object Catalogue'!$A:$A,0)),"Platform / managed") | H7: MasterRecord | J7: =IF(B7=G7,"No","Yes") | K7: Yes | L7: Org describe (DCCA sandbox)
A8: Account | B8: =IFERROR(INDEX('Object Catalogue'!$D:$D,MATCH(A8,'Object Catalogue'!$A:$A,0)),"Platform / managed") | C8: OwnerId | D8: Owner ID | E8: Lookup | F8: User | G8: =IFERROR(INDEX('Object Catalogue'!$D:$D,MATCH(F8,'Object Catalogue'!$A:$A,0)),"Platform / managed") | H8: Owner | J8: =IF(B8=G8,"No","Yes") | K8: No (User/system lookup) | L8: Org describe (DCCA sandbox)
A9: Account | B9: =IFERROR(INDEX('Object Catalogue'!$D:$D,MATCH(A9,'Object Catalogue'!$A:$A,0)),"Platform / managed") | C9: ParentId | D9: Parent Account ID | E9: Lookup | F9: Account | G9: =IFERROR(INDEX('Object Catalogue'!$D:$D,MATCH(F9,'Object Catalogue'!$A:$A,0)),"Platform / managed") | H9: Parent | J9: =IF(B9=G9,"No","Yes") | K9: Yes | L9: Org describe (DCCA sandbox)
A10: Account | B10: =IFERROR(INDEX('Object Catalogue'!$D:$D,MATCH(A10,'Object Catalogue'!$A:$A,0)),"Platform / managed") | C10: PersonContactId | D10: Contact ID | E10: Lookup | F10: Contact | G10: =IFERROR(INDEX('Object Catalogue'!$D:$D,MATCH(F10,'Object Catalogue'!$A:$A,0)),"Platform / managed") | H10: PersonContact | J10: =IF(B10=G10,"No","Yes") | K10: Yes | L10: Org describe (DCCA sandbox)
A11: Account | B11: =IFERROR(INDEX('Object Catalogue'!$D:$D,MATCH(A11,'Object Catalogue'!$A:$A,0)),"Platform / managed") | C11: PersonIndividualId | D11: Individual ID | E11: Lookup | F11: Individual | G11: =IFERROR(INDEX('Object Catalogue'!$D:$D,MATCH(F11,'Object Catalogue'!$A:$A,0)),"Platform / managed") | H11: PersonIndividual | J11: =IF(B11=G11,"No","Yes") | K11: Yes | L11: Org describe (DCCA sandbox)
A12: Account | B12: =IFERROR(INDEX('Object Catalogue'!$D:$D,MATCH(A12,'Object Catalogue'!$A:$A,0)),"Platform / managed") | C12: PersonReportsToId | D12: Reports To ID | E12: Lookup | F12: Contact | G12: =IFERROR(INDEX('Object Catalogue'!$D:$D,MATCH(F12,'Object Catalogue'!$A:$A,0)),"Platform / managed") | H12: PersonReportsTo | J12: =IF(B12=G12,"No","Yes") | K12: Yes | L12: Org describe (DCCA sandbox)
A13: Account | B13: =IFERROR(INDEX('Object Catalogue'!$D:$D,MATCH(A13,'Object Catalogue'!$A:$A,0)),"Platform / managed") | C13: RecordTypeId | D13: Record Type ID | E13: Lookup | F13: RecordType | G13: =IFERROR(INDEX('Object Catalogue'!$D:$D,MATCH(F13,'Object Catalogue'!$A:$A,0)),"Platform / managed") | H13: RecordType | J13: =IF(B13=G13,"No","Yes") | K13: No (User/system lookup) | L13: Org describe (DCCA sandbox)
A14: Account | B14: =IFERROR(INDEX('Object Catalogue'!$D:$D,MATCH(A14,'Object Catalogue'!$A:$A,0)),"Platform / managed") | C14: breg_Account_Affiliation__pc | D14: Account Affiliation | E14: Lookup | F14: breg_Account_Affiliation__c | G14: =IFERROR(INDEX('Object Catalogue'!$D:$D,MATCH(F14,'Object Catalogue'!$A:$A,0)),"Platform / managed") | H14: breg_Account_Affiliation__pr | J14: =IF(B14=G14,"No","Yes") | K14: Yes | L14: Org describe (DCCA sandbox)
A15: Account | B15: =IFERROR(INDEX('Object Catalogue'!$D:$D,MATCH(A15,'Object Catalogue'!$A:$A,0)),"Platform / managed") | C15: breg_Certified_Register_Agent__c | D15: Current Active Agent | E15: Lookup | F15: breg_Account_Affiliation__c | G15: =IFERROR(INDEX('Object Catalogue'!$D:$D,MATCH(F15,'Object Catalogue'!$A:$A,0)),"Platform / managed") | H15: breg_Certified_Register_Agent__r | J15: =IF(B15=G15,"No","Yes") | K15: Yes | L15: Org describe (DCCA sandbox)
A16: Account | B16: =IFERROR(INDEX('Object Catalogue'!$D:$D,MATCH(A16,'Object Catalogue'!$A:$A,0)),"Platform / managed") | C16: breg_Creator__c | D16: Creator | E16: Lookup | F16: User | G16: =IFERROR(INDEX('Object Catalogue'!$D:$D,MATCH(F16,'Object Catalogue'!$A:$A,0)),"Platform / managed") | H16: breg_Creator__r | J16: =IF(B16=G16,"No","Yes") | K16: No (User/system lookup) | L16: Org describe (DCCA sandbox)
A17: Account | B17: =IFERROR(INDEX('Object Catalogue'!$D:$D,MATCH(A17,'Object Catalogue'!$A:$A,0)),"Platform / managed") | C17: breg_Pending_Transaction__c | D17: Pending Transaction | E17: Lookup | F17: breg_Transaction__c | G17: =IFERROR(INDEX('Object Catalogue'!$D:$D,MATCH(F17,'Object Catalogue'!$A:$A,0)),"Platform / managed") | H17: breg_Pending_Transaction__r | J17: =IF(B17=G17,"No","Yes") | K17: Yes | L17: Org describe (DCCA sandbox)
... A26: AdditionalDependentAppsLicenses__c | B26: =IFERROR(INDEX('Object Catalogue'!$D:$D,MATCH(A26,'Object Catalogue'!$A:$A,0)),"Platform / managed") | C26: DependentLicense__c | D26: Dependent License | E26: Lookup | F26: License__c | G26: =IFERROR(INDEX('Object Catalogue'!$D:$D,MATCH(F26,'Object Catalogue'!$A:$A,0)),"Platform / managed") | H26: AdditionalDependentAppsLicenses | J26: =IF(B26=G26,"No","Yes") | K26: Yes | L26: Source metadata
A27: AllegationViolation__c | B27: =IFERROR(INDEX('Object Catalogue'!$D:$D,MATCH(A27,'Object Catalogue'!$A:$A,0)),"Platform / managed") | C27: Allegation__c | D27: Allegation | E27: Master-detail | F27: Allegation__c | G27: =IFERROR(INDEX('Object Catalogue'!$D:$D,MATCH(F27,'Object Catalogue'!$A:$A,0)),"Platform / managed") | H27: AllegationViolation | I27: Yes | J27: =IF(B27=G27,"No","Yes") | K27: Yes | L27: Source metadata
A28: AllegationViolation__c | B28: =IFERROR(INDEX('Object Catalogue'!$D:$D,MATCH(A28,'Object Catalogue'!$A:$A,0)),"Platform / managed") | C28: Violation__c | D28: Violation | E28: Master-detail | F28: Violation__c | G28: =IFERROR(INDEX('Object Catalogue'!$D:$D,MATCH(F28,'Object Catalogue'!$A:$A,0)),"Platform / managed") | H28: AllegationViolation | I28: Yes | J28: =IF(B28=G28,"No","Yes") | K28: Yes | L28: Source metadata
A29: Allegation__c | B29: =IFERROR(INDEX('Object Catalogue'!$D:$D,MATCH(A29,'Object Catalogue'!$A:$A,0)),"Platform / managed") | C29: SEBCaseContact__c | D29: SEB Case Contact | E29: Lookup | F29: SEBCaseContact__c | G29: =IFERROR(INDEX('Object Catalogue'!$D:$D,MATCH(F29,'Object Catalogue'!$A:$A,0)),"Platform / managed") | H29: Allegations | J29: =IF(B29=G29,"No","Yes") | K29: Yes | L29: Source metadata
A30: Allegation__c | B30: =IFERROR(INDEX('Object Catalogue'!$D:$D,MATCH(A30,'Object Catalogue'!$A:$A,0)),"Platform / managed") | C30: SEBCaseID__c | D30: SEB Case ID | E30: Master-detail | F30: SEBCase__c | G30: =IFERROR(INDEX('Object Catalogue'!$D:$D,MATCH(F30,'Object Catalogue'!$A:$A,0)),"Platform / managed") | H30: Allegations | I30: Yes | J30: =IF(B30=G30,"No","Yes") | K30: Yes | L30: Source metadata
A31: ApplicationClassifications__c | B31: =IFERROR(INDEX('Object Catalogue'!$D:$D,MATCH(A31,'Object Catalogue'!$A:$A,0)),"Platform / managed") | C31: Application__c | D31: Application | E31: Master-detail | F31: Application__c | G31: =IFERROR(INDEX('Object Catalogue'!$D:$D,MATCH(F31,'Object Catalogue'!$A:$A,0)),"Platform / managed") | H31: Application_Classifications | I31: Yes | J31: =IF(B31=G31,"No","Yes") | K31: Yes | L31: Source metadata
A32: ApplicationClassifications__c | B32: =IFERROR(INDEX('Object Catalogue'!$D:$D,MATCH(A32,'Object Catalogue'!$A:$A,0)),"Platform / managed") | C32: Classification__c | D32: Classification | E32: Master-detail | F32: Classification__c | G32: =IFERROR(INDEX('Object Catalogue'!$D:$D,MATCH(F32,'Object Catalogue'!$A:$A,0)),"Platform / managed") | H32: Application_Classifications | I32: Yes | J32: =IF(B32=G32,"No","Yes") | K32: Yes | L32: Source metadata
A33: ApplicationClassifications__c | B33: =IFERROR(INDEX('Object Catalogue'!$D:$D,MATCH(A33,'Object Catalogue'!$A:$A,0)),"Platform / managed") | C33: LicenseType__c | D33: License Type | E33: Lookup | F33: LicenseType__c | G33: =IFERROR(INDEX('Object Catalogue'!$D:$D,MATCH(F33,'Object Catalogue'!$A:$A,0)),"Platform / managed") | H33: Application_Classifications | J33: =IF(B33=G33,"No","Yes") | K33: Yes | L33: Source metadata
A34: ApplicationRequirement__c | B34: =IFERROR(INDEX('Object Catalogue'!$D:$D,MATCH(A34,'Object Catalogue'!$A:$A,0)),"Platform / managed") | C34: Application__c | D34: Application | E34: Master-detail | F34: Application__c | G34: =IFERROR(INDEX('Object Catalogue'!$D:$D,MATCH(F34,'Object Catalogue'!$A:$A,0)),"Platform / managed") | H34: Application_Deficiencies | I34: Yes | J34: =IF(B34=G34,"No","Yes") | K34: Yes | L34: Source metadata
A35: ApplicationRequirement__c | B35: =IFERROR(INDEX('Object Catalogue'!$D:$D,MATCH(A35,'Object Catalogue'!$A:$A,0)),"Platform / managed") | C35: ParentApplicationRequirement__c | D35: Parent Application Requirement | E35: Lookup | F35: ApplicationRequirement__c | G35: =IFERROR(INDEX('Object Catalogue'!$D:$D,MATCH(F35,'Object Catalogue'!$A:$A,0)),"Platform / managed") | H35: ApplicationRequirements | J35: =IF(B35=G35,"No","Yes") | K35: Yes | L35: Source metadata
A36: ApplicationRequirement__c | B36: =IFERROR(INDEX('Object Catalogue'!$D:$D,MATCH(A36,'Object Catalogue'!$A:$A,0)),"Platform / managed") | C36: Requirement__c | D36: Requirement | E36: Lookup | F36: Requirements__c | G36: =IFERROR(INDEX('Object Catalogue'!$D:$D,MATCH(F36,'Object Catalogue'!$A:$A,0)),"Platform / managed") | H36: Application_Requirements | J36: =IF(B36=G36,"No","Yes") | K36: Yes | L36: Source metadata
A37: Application_Cache__c | B37: =IFERROR(INDEX('Object Catalogue'!$D:$D,MATCH(A37,'Object Catalogue'!$A:$A,0)),"Platform / managed") | C37: Application_Meta_Data__c | D37: Application Meta Data | E37: Lookup | F37: Application_Meta_Data__c | G37: =IFERROR(INDEX('Object Catalogue'!$D:$D,MATCH(F37,'Object Catalogue'!$A:$A,0)),"Platform / managed") | H37: Application_Cache | J37: =IF(B37=G37,"No","Yes") | K37: Yes | L37: Source metadata
A38: Application_Cache__c | B38: =IFERROR(INDEX('Object Catalogue'!$D:$D,MATCH(A38,'Object Catalogue'!$A:$A,0)),"Platform / managed") | C38: Duties_Reassessment_Application__c | D38: Reassessment Application | E38: Lookup | F38: Application__c | G38: =IFERROR(INDEX('Object Catalogue'!$D:$D,MATCH(F38,'Object Catalogue'!$A:$A,0)),"Platform / managed") | H38: Draft_Applications | J38: =IF(B38=G38,"No","Yes") | K38: Yes | L38: Source metadata
A39: Application_Cache__c | B39: =IFERROR(INDEX('Object Catalogue'!$D:$D,MATCH(A39,'Object Catalogue'!$A:$A,0)),"Platform / managed") | C39: PVLPortalUser__c | D39: PVL Portal User | E39: Lookup | F39: PVL_Portal_User__c | G39: =IFERROR(INDEX('Object Catalogue'!$D:$D,MATCH(F39,'Object Catalogue'!$A:$A,0)),"Platform / managed") | H39: Draft_Applications | J39: =IF(B39=G39,"No","Yes") | K39: Yes | L39: Source metadata
A40: Application_Cache__c | B40: =IFERROR(INDEX('Object Catalogue'!$D:$D,MATCH(A40,'Object Catalogue'!$A:$A,0)),"Platform / managed") | C40: Previous_Owner__c | D40: Previous Owner | E40: Lookup | F40: User | G40: =IFERROR(INDEX('Object Catalogue'!$D:$D,MATCH(F40,'Object Catalogue'!$A:$A,0)),"Platform / managed") | H40: PreviousOwnerDraftApplications | J40: =IF(B40=G40,"No","Yes") | K40: No (User/system lookup) | L40: Source metadata
A41: Application__c | B41: =IFERROR(INDEX('Object Catalogue'!$D:$D,MATCH(A41,'Object Catalogue'!$A:$A,0)),"Platform / managed") | C41: Applicant__c | D41: Applicant | E41: Lookup | F41: Account | G41: =IFERROR(INDEX('Object Catalogue'!$D:$D,MATCH(F41,'Object Catalogue'!$A:$A,0)),"Platform / managed") | H41: Applications | J41: =IF(B41=G41,"No","Yes") | K41: Yes | L41: Source metadata
A42: Application__c | B42: =IFERROR(INDEX('Object Catalogue'!$D:$D,MATCH(A42,'Object Catalogue'!$A:$A,0)),"Platform / managed") | C42: Consultant__c | D42: Consultant | E42: Lookup | F42: Account | G42: =IFERROR(INDEX('Object Catalogue'!$D:$D,MATCH(F42,'Object Catalogue'!$A:$A,0)),"Platform / managed") | H42: Applications2 | J42: =IF(B42=G42,"No","Yes") | K42: Yes | L42: Source metadata
A43: Application__c | B43: =IFERROR(INDEX('Object Catalogue'!$D:$D,MATCH(A43,'Object Catalogue'!$A:$A,0)),"Platform / managed") | C43: CurrentLicense__c | D43: Current License | E43: Lookup | F43: License__c | G43: =IFERROR(INDEX('Object Catalogue'!$D:$D,MATCH(F43,'Object Catalogue'!$A:$A,0)),"Platform / managed") | H43: Applications1 | J43: =IF(B43=G43,"No","Yes") | K43: Yes | L43: Source metadata
A44: Application__c | B44: =IFERROR(INDEX('Object Catalogue'!$D:$D,MATCH(A44,'Object Catalogue'!$A:$A,0)),"Platform / managed") | C44: DependentApplication__c | D44: Dependent Application | E44: Lookup | F44: Application__c | G44: =IFERROR(INDEX('Object Catalogue'!$D:$D,MATCH(F44,'Object Catalogue'!$A:$A,0)),"Platform / managed") | H44: Dependent_Applications | J44: =IF(B44=G44,"No","Yes") | K44: Yes | L44: Source metadata
A45: Application__c | B45: =IFERROR(INDEX('Object Catalogue'!$D:$D,MATCH(A45,'Object Catalogue'!$A:$A,0)),"Platform / managed") | C45: DependentLicense2__c | D45: Dependent License 2 | E45: Lookup | F45: License__c | G45: =IFERROR(INDEX('Object Catalogue'!$D:$D,MATCH(F45,'Object Catalogue'!$A:$A,0)),"Platform / managed") | H45: Applications2 | J45: =IF(B45=G45,"No","Yes") | K45: Yes | L45: Source metadata
A46: Application__c | B46: =IFERROR(INDEX('Object Catalogue'!$D:$D,MATCH(A46,'Object Catalogue'!$A:$A,0)),"Platform / managed") | C46: DependentLicense__c | D46: Dependent License | E46: Lookup | F46: License__c | G46: =IFERROR(INDEX('Object Catalogue'!$D:$D,MATCH(F46,'Object Catalogue'!$A:$A,0)),"Platform / managed") | H46: Applications | J46: =IF(B46=G46,"No","Yes") | K46: Yes | L46: Source metadata
... A51: AssociatedLicense__c | B51: =IFERROR(INDEX('Object Catalogue'!$D:$D,MATCH(A51,'Object Catalogue'!$A:$A,0)),"Platform / managed") | C51: EmployeeLicense__c | D51: Employee License | E51: Lookup | F51: License__c | G51: =IFERROR(INDEX('Object Catalogue'!$D:$D,MATCH(F51,'Object Catalogue'!$A:$A,0)),"Platform / managed") | H51: AssociatedEntities | J51: =IF(B51=G51,"No","Yes") | K51: Yes | L51: Source metadata
A52: AssociatedLicense__c | B52: =IFERROR(INDEX('Object Catalogue'!$D:$D,MATCH(A52,'Object Catalogue'!$A:$A,0)),"Platform / managed") | C52: EntityLicense__c | D52: Entity License | E52: Master-detail | F52: License__c | G52: =IFERROR(INDEX('Object Catalogue'!$D:$D,MATCH(F52,'Object Catalogue'!$A:$A,0)),"Platform / managed") | H52: AssociatedEmployee | I52: Yes | J52: =IF(B52=G52,"No","Yes") | K52: Yes | L52: Source metadata
A53: Associated_Account__c | B53: =IFERROR(INDEX('Object Catalogue'!$D:$D,MATCH(A53,'Object Catalogue'!$A:$A,0)),"Platform / managed") | C53: Account__c | D53: Account | E53: Lookup | F53: Account | G53: =IFERROR(INDEX('Object Catalogue'!$D:$D,MATCH(F53,'Object Catalogue'!$A:$A,0)),"Platform / managed") | H53: Associated_Accounts | J53: =IF(B53=G53,"No","Yes") | K53: Yes | L53: Source metadata
A54: Associated_Account__c | B54: =IFERROR(INDEX('Object Catalogue'!$D:$D,MATCH(A54,'Object Catalogue'!$A:$A,0)),"Platform / managed") | C54: License__c | D54: License | E54: Lookup | F54: License__c | G54: =IFERROR(INDEX('Object Catalogue'!$D:$D,MATCH(F54,'Object Catalogue'!$A:$A,0)),"Platform / managed") | H54: Associated_Accounts | J54: =IF(B54=G54,"No","Yes") | K54: Yes | L54: Source metadata
A55: Card_Cache__c | B55: =IFERROR(INDEX('Object Catalogue'!$D:$D,MATCH(A55,'Object Catalogue'!$A:$A,0)),"Platform / managed") | C55: Application_Cache__c | D55: Application Cache | E55: Master-detail | F55: Application_Cache__c | G55: =IFERROR(INDEX('Object Catalogue'!$D:$D,MATCH(F55,'Object Catalogue'!$A:$A,0)),"Platform / managed") | H55: Card_Cache | I55: Yes | J55: =IF(B55=G55,"No","Yes") | K55: Yes | L55: Source metadata
A56: Card_Cache__c | B56: =IFERROR(INDEX('Object Catalogue'!$D:$D,MATCH(A56,'Object Catalogue'!$A:$A,0)),"Platform / managed") | C56: Card_Meta_Data__c | D56: Card Meta Data | E56: Lookup | F56: Card_Meta_Data__c | G56: =IFERROR(INDEX('Object Catalogue'!$D:$D,MATCH(F56,'Object Catalogue'!$A:$A,0)),"Platform / managed") | H56: Card_Cache | J56: =IF(B56=G56,"No","Yes") | K56: Yes | L56: Source metadata
A57: Card_Meta_Data__c | B57: =IFERROR(INDEX('Object Catalogue'!$D:$D,MATCH(A57,'Object Catalogue'!$A:$A,0)),"Platform / managed") | C57: Application_Meta_Data__c | D57: Application Meta Data | E57: Lookup | F57: Application_Meta_Data__c | G57: =IFERROR(INDEX('Object Catalogue'!$D:$D,MATCH(F57,'Object Catalogue'!$A:$A,0)),"Platform / managed") | H57: Card_Meta_Data1 | J57: =IF(B57=G57,"No","Yes") | K57: Yes | L57: Source metadata
A58: Case | B58: =IFERROR(INDEX('Object Catalogue'!$D:$D,MATCH(A58,'Object Catalogue'!$A:$A,0)),"Platform / managed") | C58: AccountId | D58: Account ID | E58: Lookup | F58: Account | G58: =IFERROR(INDEX('Object Catalogue'!$D:$D,MATCH(F58,'Object Catalogue'!$A:$A,0)),"Platform / managed") | H58: Account | J58: =IF(B58=G58,"No","Yes") | K58: Yes | L58: Org describe (DCCA sandbox)
A59: Case | B59: =IFERROR(INDEX('Object Catalogue'!$D:$D,MATCH(A59,'Object Catalogue'!$A:$A,0)),"Platform / managed") | C59: AssetId | D59: Asset ID | E59: Lookup | F59: Asset | G59: =IFERROR(INDEX('Object Catalogue'!$D:$D,MATCH(F59,'Object Catalogue'!$A:$A,0)),"Platform / managed") | H59: Asset | J59: =IF(B59=G59,"No","Yes") | K59: Yes | L59: Org describe (DCCA sandbox)
A60: Case | B60: =IFERROR(INDEX('Object Catalogue'!$D:$D,MATCH(A60,'Object Catalogue'!$A:$A,0)),"Platform / managed") | C60: Assigned_To__c | D60: Assigned To | E60: Lookup | F60: User | G60: =IFERROR(INDEX('Object Catalogue'!$D:$D,MATCH(F60,'Object Catalogue'!$A:$A,0)),"Platform / managed") | H60: Assigned_To__r | J60: =IF(B60=G60,"No","Yes") | K60: No (User/system lookup) | L60: Org describe (DCCA sandbox)
A61: Case | B61: =IFERROR(INDEX('Object Catalogue'!$D:$D,MATCH(A61,'Object Catalogue'!$A:$A,0)),"Platform / managed") | C61: BusinessHoursId | D61: Business Hours ID | E61: Lookup | F61: BusinessHours | G61: =IFERROR(INDEX('Object Catalogue'!$D:$D,MATCH(F61,'Object Catalogue'!$A:$A,0)),"Platform / managed") | H61: BusinessHours | I61: Yes | J61: =IF(B61=G61,"No","Yes") | K61: No (User/system lookup) | L61: Org describe (DCCA sandbox)
A62: Case | B62: =IFERROR(INDEX('Object Catalogue'!$D:$D,MATCH(A62,'Object Catalogue'!$A:$A,0)),"Platform / managed") | C62: ContactId | D62: Contact ID | E62: Lookup | F62: Contact | G62: =IFERROR(INDEX('Object Catalogue'!$D:$D,MATCH(F62,'Object Catalogue'!$A:$A,0)),"Platform / managed") | H62: Contact | J62: =IF(B62=G62,"No","Yes") | K62: Yes | L62: Org describe (DCCA sandbox)
A63: Case | B63: =IFERROR(INDEX('Object Catalogue'!$D:$D,MATCH(A63,'Object Catalogue'!$A:$A,0)),"Platform / managed") | C63: MasterRecordId | D63: Master Record ID | E63: Lookup | F63: Case | G63: =IFERROR(INDEX('Object Catalogue'!$D:$D,MATCH(F63,'Object Catalogue'!$A:$A,0)),"Platform / managed") | H63: MasterRecord | J63: =IF(B63=G63,"No","Yes") | K63: Yes | L63: Org describe (DCCA sandbox)
A64: Case | B64: =IFERROR(INDEX('Object Catalogue'!$D:$D,MATCH(A64,'Object Catalogue'!$A:$A,0)),"Platform / managed") | C64: OwnerId | D64: Owner ID | E64: Lookup | F64: Group, User | G64: =IFERROR(INDEX('Object Catalogue'!$D:$D,MATCH(F64,'Object Catalogue'!$A:$A,0)),"Platform / managed") | H64: Owner | J64: =IF(B64=G64,"No","Yes") | K64: No (User/system lookup) | L64: Org describe (DCCA sandbox)
A65: Case | B65: =IFERROR(INDEX('Object Catalogue'!$D:$D,MATCH(A65,'Object Catalogue'!$A:$A,0)),"Platform / managed") | C65: ParentId | D65: Parent Case ID | E65: Lookup | F65: Case | G65: =IFERROR(INDEX('Object Catalogue'!$D:$D,MATCH(F65,'Object Catalogue'!$A:$A,0)),"Platform / managed") | H65: Parent | J65: =IF(B65=G65,"No","Yes") | K65: Yes | L65: Org describe (DCCA sandbox)
A66: Case | B66: =IFERROR(INDEX('Object Catalogue'!$D:$D,MATCH(A66,'Object Catalogue'!$A:$A,0)),"Platform / managed") | C66: RecordTypeId | D66: Record Type ID | E66: Lookup | F66: RecordType | G66: =IFERROR(INDEX('Object Catalogue'!$D:$D,MATCH(F66,'Object Catalogue'!$A:$A,0)),"Platform / managed") | H66: RecordType | J66: =IF(B66=G66,"No","Yes") | K66: No (User/system lookup) | L66: Org describe (DCCA sandbox)
A67: Case | B67: =IFERROR(INDEX('Object Catalogue'!$D:$D,MATCH(A67,'Object Catalogue'!$A:$A,0)),"Platform / managed") | C67: SourceId | D67: Case Source ID | E67: Lookup | F67: BusinessMilestone, EmailMessage, MessagingSession, PersonLifeEvent, PublicComplaint, SocialPost | G67: =IFERROR(INDEX('Object Catalogue'!$D:$D,MATCH(F67,'Object Catalogue'!$A:$A,0)),"Platform / managed") | H67: Source | J67: =IF(B67=G67,"No","Yes") | K67: No (User/system lookup) | L67: Org describe (DCCA sandbox)
A68: Case | B68: =IFERROR(INDEX('Object Catalogue'!$D:$D,MATCH(A68,'Object Catalogue'!$A:$A,0)),"Platform / managed") | C68: breg_Annual__c | D68: Annual | E68: Lookup | F68: breg_Annual__c | G68: =IFERROR(INDEX('Object Catalogue'!$D:$D,MATCH(F68,'Object Catalogue'!$A:$A,0)),"Platform / managed") | H68: breg_Annual__r | J68: =IF(B68=G68,"No","Yes") | K68: Yes | L68: Org describe (DCCA sandbox)
A69: Case | B69: =IFERROR(INDEX('Object Catalogue'!$D:$D,MATCH(A69,'Object Catalogue'!$A:$A,0)),"Platform / managed") | C69: breg_Document__c | D69: Document | E69: Lookup | F69: breg_Document__c | G69: =IFERROR(INDEX('Object Catalogue'!$D:$D,MATCH(F69,'Object Catalogue'!$A:$A,0)),"Platform / managed") | H69: breg_Document__r | J69: =IF(B69=G69,"No","Yes") | K69: Yes | L69: Org describe (DCCA sandbox)
A70: Case | B70: =IFERROR(INDEX('Object Catalogue'!$D:$D,MATCH(A70,'Object Catalogue'!$A:$A,0)),"Platform / managed") | C70: breg_Entity__c | D70: Entity | E70: Lookup | F70: Account | G70: =IFERROR(INDEX('Object Catalogue'!$D:$D,MATCH(F70,'Object Catalogue'!$A:$A,0)),"Platform / managed") | H70: breg_Entity__r | J70: =IF(B70=G70,"No","Yes") | K70: Yes | L70: Org describe (DCCA sandbox)
A71: Case | B71: =IFERROR(INDEX('Object Catalogue'!$D:$D,MATCH(A71,'Object Catalogue'!$A:$A,0)),"Platform / managed") | C71: breg_Form_Configuration__c | D71: Form Configuration | E71: Lookup | F71: breg_Form_Configuration__c | G71: =IFERROR(INDEX('Object Catalogue'!$D:$D,MATCH(F71,'Object Catalogue'!$A:$A,0)),"Platform / managed") | H71: breg_Form_Configuration__r | J71: =IF(B71=G71,"No","Yes") | K71: Yes | L71: Org describe (DCCA sandbox)
A72: Case | B72: =IFERROR(INDEX('Object Catalogue'!$D:$D,MATCH(A72,'Object Catalogue'!$A:$A,0)),"Platform / managed") | C72: breg_GP_Case__c | D72: GP Case | E72: Lookup | F72: Case | G72: =IFERROR(INDEX('Object Catalogue'!$D:$D,MATCH(F72,'Object Catalogue'!$A:$A,0)),"Platform / managed") | H72: breg_GP_Case__r | J72: =IF(B72=G72,"No","Yes") | K72: Yes | L72: Org describe (DCCA sandbox)
A73: Case | B73: =IFERROR(INDEX('Object Catalogue'!$D:$D,MATCH(A73,'Object Catalogue'!$A:$A,0)),"Platform / managed") | C73: breg_GP_Entity__c | D73: GP Entity | E73: Lookup | F73: Account | G73: =IFERROR(INDEX('Object Catalogue'!$D:$D,MATCH(F73,'Object Catalogue'!$A:$A,0)),"Platform / managed") | H73: breg_GP_Entity__r | J73: =IF(B73=G73,"No","Yes") | K73: Yes | L73: Org describe (DCCA sandbox)
... A78: Case | B78: =IFERROR(INDEX('Object Catalogue'!$D:$D,MATCH(A78,'Object Catalogue'!$A:$A,0)),"Platform / managed") | C78: breg_TN_TM_SM__c | D78: TN/TM/SM | E78: Lookup | F78: breg_TN_TM_SM__c | G78: =IFERROR(INDEX('Object Catalogue'!$D:$D,MATCH(F78,'Object Catalogue'!$A:$A,0)),"Platform / managed") | H78: breg_TN_TM_SM__r | J78: =IF(B78=G78,"No","Yes") | K78: Yes | L78: Org describe (DCCA sandbox)
A79: CaseTeamAssignment__c | B79: =IFERROR(INDEX('Object Catalogue'!$D:$D,MATCH(A79,'Object Catalogue'!$A:$A,0)),"Platform / managed") | C79: Case__c | D79: Case | E79: Master-detail | F79: Case | G79: =IFERROR(INDEX('Object Catalogue'!$D:$D,MATCH(F79,'Object Catalogue'!$A:$A,0)),"Platform / managed") | H79: CaseTeamAssignments | I79: Yes | J79: =IF(B79=G79,"No","Yes") | K79: Yes | L79: Source metadata
A80: CaseTeamAssignment__c | B80: =IFERROR(INDEX('Object Catalogue'!$D:$D,MATCH(A80,'Object Catalogue'!$A:$A,0)),"Platform / managed") | C80: User__c | D80: User | E80: Lookup | F80: User | G80: =IFERROR(INDEX('Object Catalogue'!$D:$D,MATCH(F80,'Object Catalogue'!$A:$A,0)),"Platform / managed") | H80: CaseTeamAssignments | J80: =IF(B80=G80,"No","Yes") | K80: No (User/system lookup) | L80: Source metadata
A81: CaseTeamMember__c | B81: =IFERROR(INDEX('Object Catalogue'!$D:$D,MATCH(A81,'Object Catalogue'!$A:$A,0)),"Platform / managed") | C81: CaseTeam__c | D81: Case Team | E81: Master-detail | F81: CaseTeam__c | G81: =IFERROR(INDEX('Object Catalogue'!$D:$D,MATCH(F81,'Object Catalogue'!$A:$A,0)),"Platform / managed") | H81: CaseTeamMembers | I81: Yes | J81: =IF(B81=G81,"No","Yes") | K81: Yes | L81: Source metadata
A82: CaseTeamMember__c | B82: =IFERROR(INDEX('Object Catalogue'!$D:$D,MATCH(A82,'Object Catalogue'!$A:$A,0)),"Platform / managed") | C82: User__c | D82: User | E82: Lookup | F82: User | G82: =IFERROR(INDEX('Object Catalogue'!$D:$D,MATCH(F82,'Object Catalogue'!$A:$A,0)),"Platform / managed") | H82: CaseTeamMembers | J82: =IF(B82=G82,"No","Yes") | K82: No (User/system lookup) | L82: Source metadata
A83: CashierCode__c | B83: =IFERROR(INDEX('Object Catalogue'!$D:$D,MATCH(A83,'Object Catalogue'!$A:$A,0)),"Platform / managed") | C83: BoardProgram__c | D83: Board/Program | E83: Lookup | F83: BoardProgram__c | G83: =IFERROR(INDEX('Object Catalogue'!$D:$D,MATCH(F83,'Object Catalogue'!$A:$A,0)),"Platform / managed") | H83: CashierCodes | J83: =IF(B83=G83,"No","Yes") | K83: Yes | L83: Source metadata
A84: CertificateRequest__c | B84: =IFERROR(INDEX('Object Catalogue'!$D:$D,MATCH(A84,'Object Catalogue'!$A:$A,0)),"Platform / managed") | C84: License__c | D84: License | E84: Lookup | F84: License__c | G84: =IFERROR(INDEX('Object Catalogue'!$D:$D,MATCH(F84,'Object Catalogue'!$A:$A,0)),"Platform / managed") | H84: Certificate_Requests | J84: =IF(B84=G84,"No","Yes") | K84: Yes | L84: Source metadata
A85: Checklist__c | B85: =IFERROR(INDEX('Object Catalogue'!$D:$D,MATCH(A85,'Object Catalogue'!$A:$A,0)),"Platform / managed") | C85: Investigation__c | D85: Investigation | E85: Lookup | F85: Investigation__c | G85: =IFERROR(INDEX('Object Catalogue'!$D:$D,MATCH(F85,'Object Catalogue'!$A:$A,0)),"Platform / managed") | H85: Checklists | J85: =IF(B85=G85,"No","Yes") | K85: Yes | L85: Source metadata
A86: Classification__c | B86: =IFERROR(INDEX('Object Catalogue'!$D:$D,MATCH(A86,'Object Catalogue'!$A:$A,0)),"Platform / managed") | C86: LicenseType__c | D86: License Type | E86: Master-detail | F86: LicenseType__c | G86: =IFERROR(INDEX('Object Catalogue'!$D:$D,MATCH(F86,'Object Catalogue'!$A:$A,0)),"Platform / managed") | H86: Classifications | I86: Yes | J86: =IF(B86=G86,"No","Yes") | K86: Yes | L86: Source metadata
A87: CollectionsAllocation__c | B87: =IFERROR(INDEX('Object Catalogue'!$D:$D,MATCH(A87,'Object Catalogue'!$A:$A,0)),"Platform / managed") | C87: Deposit__c | D87: Deposit | E87: Lookup | F87: Deposits__c | G87: =IFERROR(INDEX('Object Catalogue'!$D:$D,MATCH(F87,'Object Catalogue'!$A:$A,0)),"Platform / managed") | H87: Collections_Allocations | J87: =IF(B87=G87,"No","Yes") | K87: Yes | L87: Source metadata
A88: CollectionsAllocation__c | B88: =IFERROR(INDEX('Object Catalogue'!$D:$D,MATCH(A88,'Object Catalogue'!$A:$A,0)),"Platform / managed") | C88: Payment__c | D88: Payment | E88: Master-detail | F88: pymt__PaymentX__c | G88: =IFERROR(INDEX('Object Catalogue'!$D:$D,MATCH(F88,'Object Catalogue'!$A:$A,0)),"Platform / managed") | H88: Collections_Allocations | I88: Yes | J88: =IF(B88=G88,"No","Yes") | K88: Yes | L88: Source metadata
A89: CollectionsAllocation__c | B89: =IFERROR(INDEX('Object Catalogue'!$D:$D,MATCH(A89,'Object Catalogue'!$A:$A,0)),"Platform / managed") | C89: Reconciliation_Batch__c | D89: Reconciliation Batch | E89: Lookup | F89: Reconciliation_Batch__c | G89: =IFERROR(INDEX('Object Catalogue'!$D:$D,MATCH(F89,'Object Catalogue'!$A:$A,0)),"Platform / managed") | H89: Collections_Allocations | J89: =IF(B89=G89,"No","Yes") | K89: Yes | L89: Source metadata
A90: CollectionsAllocation__c | B90: =IFERROR(INDEX('Object Catalogue'!$D:$D,MATCH(A90,'Object Catalogue'!$A:$A,0)),"Platform / managed") | C90: TransactionLine__c | D90: Transaction Line | E90: Master-detail | F90: TransactionLine__c | G90: =IFERROR(INDEX('Object Catalogue'!$D:$D,MATCH(F90,'Object Catalogue'!$A:$A,0)),"Platform / managed") | H90: Collections_Allocations | I90: Yes | J90: =IF(B90=G90,"No","Yes") | K90: Yes | L90: Source metadata
A91: CollectionsAllocation__c | B91: =IFERROR(INDEX('Object Catalogue'!$D:$D,MATCH(A91,'Object Catalogue'!$A:$A,0)),"Platform / managed") | C91: Transaction__c | D91: Transaction | E91: Lookup | F91: Transaction__c | G91: =IFERROR(INDEX('Object Catalogue'!$D:$D,MATCH(F91,'Object Catalogue'!$A:$A,0)),"Platform / managed") | H91: Collections_Allocations | J91: =IF(B91=G91,"No","Yes") | K91: Yes | L91: Source metadata
A92: Contact | B92: =IFERROR(INDEX('Object Catalogue'!$D:$D,MATCH(A92,'Object Catalogue'!$A:$A,0)),"Platform / managed") | C92: AccountId | D92: Account ID | E92: Lookup | F92: Account | G92: =IFERROR(INDEX('Object Catalogue'!$D:$D,MATCH(F92,'Object Catalogue'!$A:$A,0)),"Platform / managed") | H92: Account | J92: =IF(B92=G92,"No","Yes") | K92: Yes | L92: Org describe (DCCA sandbox)
A93: Contact | B93: =IFERROR(INDEX('Object Catalogue'!$D:$D,MATCH(A93,'Object Catalogue'!$A:$A,0)),"Platform / managed") | C93: IndividualId | D93: Individual ID | E93: Lookup | F93: Individual | G93: =IFERROR(INDEX('Object Catalogue'!$D:$D,MATCH(F93,'Object Catalogue'!$A:$A,0)),"Platform / managed") | H93: Individual | J93: =IF(B93=G93,"No","Yes") | K93: Yes | L93: Org describe (DCCA sandbox)
A94: Contact | B94: =IFERROR(INDEX('Object Catalogue'!$D:$D,MATCH(A94,'Object Catalogue'!$A:$A,0)),"Platform / managed") | C94: MasterRecordId | D94: Master Record ID | E94: Lookup | F94: Contact | G94: =IFERROR(INDEX('Object Catalogue'!$D:$D,MATCH(F94,'Object Catalogue'!$A:$A,0)),"Platform / managed") | H94: MasterRecord | J94: =IF(B94=G94,"No","Yes") | K94: Yes | L94: Org describe (DCCA sandbox)
A95: Contact | B95: =IFERROR(INDEX('Object Catalogue'!$D:$D,MATCH(A95,'Object Catalogue'!$A:$A,0)),"Platform / managed") | C95: OwnerId | D95: Owner ID | E95: Lookup | F95: User | G95: =IFERROR(INDEX('Object Catalogue'!$D:$D,MATCH(F95,'Object Catalogue'!$A:$A,0)),"Platform / managed") | H95: Owner | J95: =IF(B95=G95,"No","Yes") | K95: No (User/system lookup) | L95: Org describe (DCCA sandbox)
A96: Contact | B96: =IFERROR(INDEX('Object Catalogue'!$D:$D,MATCH(A96,'Object Catalogue'!$A:$A,0)),"Platform / managed") | C96: RecordTypeId | D96: Record Type ID | E96: Lookup | F96: RecordType | G96: =IFERROR(INDEX('Object Catalogue'!$D:$D,MATCH(F96,'Object Catalogue'!$A:$A,0)),"Platform / managed") | H96: RecordType | J96: =IF(B96=G96,"No","Yes") | K96: No (User/system lookup) | L96: Org describe (DCCA sandbox)
A97: Contact | B97: =IFERROR(INDEX('Object Catalogue'!$D:$D,MATCH(A97,'Object Catalogue'!$A:$A,0)),"Platform / managed") | C97: ReportsToId | D97: Reports To ID | E97: Lookup | F97: Contact | G97: =IFERROR(INDEX('Object Catalogue'!$D:$D,MATCH(F97,'Object Catalogue'!$A:$A,0)),"Platform / managed") | H97: ReportsTo | J97: =IF(B97=G97,"No","Yes") | K97: Yes | L97: Org describe (DCCA sandbox)
A98: Contact | B98: =IFERROR(INDEX('Object Catalogue'!$D:$D,MATCH(A98,'Object Catalogue'!$A:$A,0)),"Platform / managed") | C98: breg_Account_Affiliation__c | D98: Account Affiliation | E98: Lookup | F98: breg_Account_Affiliation__c | G98: =IFERROR(INDEX('Object Catalogue'!$D:$D,MATCH(F98,'Object Catalogue'!$A:$A,0)),"Platform / managed") | H98: breg_Account_Affiliation__r | J98: =IF(B98=G98,"No","Yes") | K98: Yes | L98: Org describe (DCCA sandbox)
A99: Contact | B99: =IFERROR(INDEX('Object Catalogue'!$D:$D,MATCH(A99,'Object Catalogue'!$A:$A,0)),"Platform / managed") | C99: breg_Pending_Transaction__c | D99: Pending Transaction | E99: Lookup | F99: breg_Transaction__c | G99: =IFERROR(INDEX('Object Catalogue'!$D:$D,MATCH(F99,'Object Catalogue'!$A:$A,0)),"Platform / managed") | H99: breg_Pending_Transaction__r | J99: =IF(B99=G99,"No","Yes") | K99: Yes | L99: Org describe (DCCA sandbox)
A100: Contact | B100: =IFERROR(INDEX('Object Catalogue'!$D:$D,MATCH(A100,'Object Catalogue'!$A:$A,0)),"Platform / managed") | C100: breg_Transaction__c | D100: Transaction | E100: Lookup | F100: breg_Transaction__c | G100: =IFERROR(INDEX('Object Catalogue'!$D:$D,MATCH(F100,'Object Catalogue'!$A:$A,0)),"Platform / managed") | H100: breg_Transaction__r | J100: =IF(B100=G100,"No","Yes") | K100: Yes | L100: Org describe (DCCA sandbox)
A101: ContinuingEducation__c | B101: =IFERROR(INDEX('Object Catalogue'!$D:$D,MATCH(A101,'Object Catalogue'!$A:$A,0)),"Platform / managed") | C101: License__c | D101: License | E101: Lookup | F101: License__c | G101: =IFERROR(INDEX('Object Catalogue'!$D:$D,MATCH(F101,'Object Catalogue'!$A:$A,0)),"Platform / managed") | H101: Continuing_Education1 | J101: =IF(B101=G101,"No","Yes") | K101: Yes | L101: Source metadata
A102: Course__c | B102: =IFERROR(INDEX('Object Catalogue'!$D:$D,MATCH(A102,'Object Catalogue'!$A:$A,0)),"Platform / managed") | C102: Account__c | D102: Account | E102: Lookup | F102: Account | G102: =IFERROR(INDEX('Object Catalogue'!$D:$D,MATCH(F102,'Object Catalogue'!$A:$A,0)),"Platform / managed") | H102: Courses | J102: =IF(B102=G102,"No","Yes") | K102: Yes | L102: Source metadata
... A106: Course__c | B106: =IFERROR(INDEX('Object Catalogue'!$D:$D,MATCH(A106,'Object Catalogue'!$A:$A,0)),"Platform / managed") | C106: Subject__c | D106: Subject | E106: Lookup | F106: Subject__c | G106: =IFERROR(INDEX('Object Catalogue'!$D:$D,MATCH(F106,'Object Catalogue'!$A:$A,0)),"Platform / managed") | H106: Courses | J106: =IF(B106=G106,"No","Yes") | K106: Yes | L106: Source metadata
A107: DocGeneratorDataSource__c | B107: =IFERROR(INDEX('Object Catalogue'!$D:$D,MATCH(A107,'Object Catalogue'!$A:$A,0)),"Platform / managed") | C107: DocGeneratorSettings__c | D107: Doc Generator Settings | E107: Lookup | F107: DocGeneratorSettings__c | G107: =IFERROR(INDEX('Object Catalogue'!$D:$D,MATCH(F107,'Object Catalogue'!$A:$A,0)),"Platform / managed") | H107: Doc_Generator_Data_Sources | I107: Yes | J107: =IF(B107=G107,"No","Yes") | K107: Yes | L107: Source metadata
A108: Earned_Continuing_Education__c | B108: =IFERROR(INDEX('Object Catalogue'!$D:$D,MATCH(A108,'Object Catalogue'!$A:$A,0)),"Platform / managed") | C108: ContinuingEducation__c | D108: Course Enrollment | E108: Lookup | F108: PrelicenseCEEnrollment__c | G108: =IFERROR(INDEX('Object Catalogue'!$D:$D,MATCH(F108,'Object Catalogue'!$A:$A,0)),"Platform / managed") | H108: Earned_Continuing_Education | J108: =IF(B108=G108,"No","Yes") | K108: Yes | L108: Source metadata
A109: Earned_Continuing_Education__c | B109: =IFERROR(INDEX('Object Catalogue'!$D:$D,MATCH(A109,'Object Catalogue'!$A:$A,0)),"Platform / managed") | C109: Course__c | D109: Course | E109: Lookup | F109: Course__c | G109: =IFERROR(INDEX('Object Catalogue'!$D:$D,MATCH(F109,'Object Catalogue'!$A:$A,0)),"Platform / managed") | H109: Earned_Continuing_Education | J109: =IF(B109=G109,"No","Yes") | K109: Yes | L109: Source metadata
A110: Earned_Continuing_Education__c | B110: =IFERROR(INDEX('Object Catalogue'!$D:$D,MATCH(A110,'Object Catalogue'!$A:$A,0)),"Platform / managed") | C110: License__c | D110: License | E110: Master-detail | F110: License__c | G110: =IFERROR(INDEX('Object Catalogue'!$D:$D,MATCH(F110,'Object Catalogue'!$A:$A,0)),"Platform / managed") | H110: Earned_Continuing_Education | I110: Yes | J110: =IF(B110=G110,"No","Yes") | K110: Yes | L110: Source metadata
A111: Earned_Prelicense__c | B111: =IFERROR(INDEX('Object Catalogue'!$D:$D,MATCH(A111,'Object Catalogue'!$A:$A,0)),"Platform / managed") | C111: Applicant__c | D111: Applicant | E111: Master-detail | F111: Account | G111: =IFERROR(INDEX('Object Catalogue'!$D:$D,MATCH(F111,'Object Catalogue'!$A:$A,0)),"Platform / managed") | H111: Earned_Prelicense | I111: Yes | J111: =IF(B111=G111,"No","Yes") | K111: Yes | L111: Source metadata
A112: Earned_Prelicense__c | B112: =IFERROR(INDEX('Object Catalogue'!$D:$D,MATCH(A112,'Object Catalogue'!$A:$A,0)),"Platform / managed") | C112: Application__c | D112: Application | E112: Lookup | F112: Application__c | G112: =IFERROR(INDEX('Object Catalogue'!$D:$D,MATCH(F112,'Object Catalogue'!$A:$A,0)),"Platform / managed") | H112: Earned_Prelicense | J112: =IF(B112=G112,"No","Yes") | K112: Yes | L112: Source metadata
A113: Earned_Prelicense__c | B113: =IFERROR(INDEX('Object Catalogue'!$D:$D,MATCH(A113,'Object Catalogue'!$A:$A,0)),"Platform / managed") | C113: PrelicenseContinuingEducation__c | D113: Prelicense & Continuing Education | E113: Lookup | F113: PrelicenseCEEnrollment__c | G113: =IFERROR(INDEX('Object Catalogue'!$D:$D,MATCH(F113,'Object Catalogue'!$A:$A,0)),"Platform / managed") | H113: Earned_Prelicense | J113: =IF(B113=G113,"No","Yes") | K113: Yes | L113: Source metadata
A114: Education__c | B114: =IFERROR(INDEX('Object Catalogue'!$D:$D,MATCH(A114,'Object Catalogue'!$A:$A,0)),"Platform / managed") | C114: Application__c | D114: Application | E114: Master-detail | F114: Application__c | G114: =IFERROR(INDEX('Object Catalogue'!$D:$D,MATCH(F114,'Object Catalogue'!$A:$A,0)),"Platform / managed") | H114: Education | I114: Yes | J114: =IF(B114=G114,"No","Yes") | K114: Yes | L114: Source metadata
A115: EmailAlertTrigger__c | B115: =IFERROR(INDEX('Object Catalogue'!$D:$D,MATCH(A115,'Object Catalogue'!$A:$A,0)),"Platform / managed") | C115: Case__c | D115: Case | E115: Lookup | F115: Case | G115: =IFERROR(INDEX('Object Catalogue'!$D:$D,MATCH(F115,'Object Catalogue'!$A:$A,0)),"Platform / managed") | H115: EmailAlertTriggers | J115: =IF(B115=G115,"No","Yes") | K115: Yes | L115: Source metadata
A116: EmailAlertTrigger__c | B116: =IFERROR(INDEX('Object Catalogue'!$D:$D,MATCH(A116,'Object Catalogue'!$A:$A,0)),"Platform / managed") | C116: Contact__c | D116: Contact | E116: Lookup | F116: Contact | G116: =IFERROR(INDEX('Object Catalogue'!$D:$D,MATCH(F116,'Object Catalogue'!$A:$A,0)),"Platform / managed") | H116: EmailAlertTriggers | J116: =IF(B116=G116,"No","Yes") | K116: Yes | L116: Source metadata
A117: EmailAlertTrigger__c | B117: =IFERROR(INDEX('Object Catalogue'!$D:$D,MATCH(A117,'Object Catalogue'!$A:$A,0)),"Platform / managed") | C117: Filing__c | D117: Filing | E117: Lookup | F117: Filing__c | G117: =IFERROR(INDEX('Object Catalogue'!$D:$D,MATCH(F117,'Object Catalogue'!$A:$A,0)),"Platform / managed") | H117: EmailAlertTriggers | J117: =IF(B117=G117,"No","Yes") | K117: Yes | L117: Source metadata
A118: EmailAlertTrigger__c | B118: =IFERROR(INDEX('Object Catalogue'!$D:$D,MATCH(A118,'Object Catalogue'!$A:$A,0)),"Platform / managed") | C118: User__c | D118: User | E118: Lookup | F118: User | G118: =IFERROR(INDEX('Object Catalogue'!$D:$D,MATCH(F118,'Object Catalogue'!$A:$A,0)),"Platform / managed") | H118: Email_Alert_Triggers | J118: =IF(B118=G118,"No","Yes") | K118: No (User/system lookup) | L118: Source metadata
A119: EnforcementActionDocument__c | B119: =IFERROR(INDEX('Object Catalogue'!$D:$D,MATCH(A119,'Object Catalogue'!$A:$A,0)),"Platform / managed") | C119: SEBCaseContact__c | D119: SEB Case Contact | E119: Master-detail | F119: SEBCaseContact__c | G119: =IFERROR(INDEX('Object Catalogue'!$D:$D,MATCH(F119,'Object Catalogue'!$A:$A,0)),"Platform / managed") | H119: EnforcementActionDocuments | I119: Yes | J119: =IF(B119=G119,"No","Yes") | K119: Yes | L119: Source metadata
A120: ExamDeficiency__c | B120: =IFERROR(INDEX('Object Catalogue'!$D:$D,MATCH(A120,'Object Catalogue'!$A:$A,0)),"Platform / managed") | C120: Deficiency__c | D120: Deficiency | E120: Master-detail | F120: Deficiency__c | G120: =IFERROR(INDEX('Object Catalogue'!$D:$D,MATCH(F120,'Object Catalogue'!$A:$A,0)),"Platform / managed") | H120: ExamDeficiencies | I120: Yes | J120: =IF(B120=G120,"No","Yes") | K120: Yes | L120: Source metadata
...

Sheet Core Object References
A1: Account, Contact & Case: Inbound References
A2: Every object that looks up to Account, Contact or Case, and the lookups those three objects hold.
A3: ‹ Back to README
A5: Core Object | B5: Direction | C5: Related Object | D5: Related Object Domain | E5: Field API Name | F5: Field Label | G5: Relationship Type
A6: Account | B6: Inbound (child → core) | C6: breg_Account_Affiliation__c | D6: BREG: Business Registration | E6: breg_Account__c | F6: Account | G6: Lookup
A7: Account | B7: Inbound (child → core) | C7: breg_Account_Affiliation__c | D7: BREG: Business Registration | E7: breg_Entity__c | F7: Entity | G7: Lookup
A8: Account | B8: Inbound (child → core) | C8: breg_Acquisition_Transaction__c | D8: BREG: Business Registration | E8: breg_Merged_Entity__c | F8: Merged Entity | G8: Lookup
A9: Account | B9: Inbound (child → core) | C9: breg_Annual__c | D9: BREG: Business Registration | E9: breg_Account__c | F9: Account | G9: Lookup
A10: Account | B10: Inbound (child → core) | C10: breg_Certificate__c | D10: BREG: Business Registration | E10: breg_Account__c | F10: Account | G10: Lookup
A11: Account | B11: Inbound (child → core) | C11: breg_Document__c | D11: BREG: Business Registration | E11: breg_Account__c | F11: Account | G11: Lookup
A12: Account | B12: Inbound (child → core) | C12: breg_Log__c | D12: BREG: Business Registration | E12: breg_Account__c | F12: Account | G12: Lookup
A13: Account | B13: Inbound (child → core) | C13: breg_Notification__c | D13: BREG: Business Registration | E13: breg_Account__c | F13: Account | G13: Lookup
A14: Account | B14: Inbound (child → core) | C14: breg_Stock__c | D14: BREG: Business Registration | E14: breg_Account__c | F14: Account | G14: Lookup
A15: Account | B15: Inbound (child → core) | C15: breg_TN_TM_SM__c | D15: BREG: Business Registration | E15: breg_Account__c | F15: Account | G15: Lookup
A16: Account | B16: Inbound (child → core) | C16: breg_Test_Annual__c | D16: BREG: Business Registration | E16: breg_Account__c | F16: Account | G16: Lookup
... A137: Contact | B137: Outbound (core → parent) | C137: breg_Transaction__c | D137: BREG: Business Registration | E137: breg_Transaction__c | F137: Transaction | G137: Lookup

Sheet Record Types
A1: Record Types
A2: 343 record types across all objects.
A3: ‹ Back to README
A5: Object API Name | B5: Domain | C5: Record Type API Name | D5: Record Type Label | E5: Active | F5: Description | G5: Source
A6: Account | B6: Core: Account · Contact · Case | C6: BREG_Account | D6: BREG Account | E6: Yes | G6: Org describe (DCCA sandbox)
A7: Account | B7: Core: Account · Contact · Case | C7: BREG_Member_Account | D7: BREG Member Account | E7: Yes | G7: Org describe (DCCA sandbox)
A8: Account | B8: Core: Account · Contact · Case | C8: BusinessAccount | D8: Business Account | E8: Yes | G8: Org describe (DCCA sandbox)
A9: Account | B9: Core: Account · Contact · Case | C9: PVL | D9: Call Center | E9: Yes | G9: Org describe (DCCA sandbox)
A10: Account | B10: Core: Account · Contact · Case | C10: Complainant | D10: Complainant | E10: Yes | G10: Org describe (DCCA sandbox)
A11: Account | B11: Core: Account · Contact · Case | C11: DCCA_CATV | D11: DCCA CATV | E11: Yes | G11: Org describe (DCCA sandbox)
A12: Account | B12: Core: Account · Contact · Case | C12: PVLAttendee | D12: PVL - Attendee | E12: Yes | G12: Org describe (DCCA sandbox)
A13: Account | B13: Core: Account · Contact · Case | C13: PVLCEProvidersSchools | D13: PVL - CE Providers & Schools | E13: Yes | G13: Org describe (DCCA sandbox)
A14: Account | B14: Core: Account · Contact · Case | C14: PersonAccount | D14: Person Account | E14: Yes | G14: Org describe (DCCA sandbox)
A15: Application__c | B15: PVL: Applications & Portal | C15: PVLACU | D15: PVL - ACU | E15: Yes | F15: PacPoint-DN04062020 - Created for PVL Sprint 4 Phase 1 | G15: Source metadata
A16: Application__c | B16: PVL: Applications & Portal | C16: PVLACUI | D16: PVL - ACUI | E16: Yes | F16: PacPoint-DN05212020 - Created for PVL Sprint 4 Phase 1 | G16: Source metadata
A17: Application__c | B17: PVL: Applications & Portal | C17: PVLAD | D17: PVL - AD | E17: Yes | F17: PacPoint-DN04062020 - Created for PVL Sprint 4 Phase 1 | G17: Source metadata
A18: Application__c | B18: PVL: Applications & Portal | C18: PVLADBCOLBCOLXB | D18: PVL - ADB/COLB/COLXB | E18: Yes | F18: PacPoint-DN05202020 - Created for PVL Sprint 4 Phase 1 | G18: Source metadata
A19: Application__c | B19: PVL: Applications & Portal | C19: PVLADDC | D19: PVL - ADDC | E19: Yes | F19: PacPoint-DN03102020 - Created for PVL Sprint 3 Phase 1 | G19: Source metadata
A20: Application__c | B20: PVL: Applications & Portal | C20: PVLADDP | D20: PVL - ADDP | E20: Yes | F20: PacPoint-DN03102020 - Created for PVL Sprint 3 Phase 1 | G20: Source metadata
A21: Application__c | B21: PVL: Applications & Portal | C21: PVLAMC | D21: PVL - AMC | E21: Yes | F21: Pac Point-DN010220 - Created for PVL Sprint 3 Phase 1 | G21: Source metadata
A22: Application__c | B22: PVL: Applications & Portal | C22: PVLAMD | D22: PVL - AMD | E22: Yes | F22: PacPoint-KN110819-Created for PVL Sprint 2 Phase 1 | G22: Source metadata
A23: Application__c | B23: PVL: Applications & Portal | C23: PVL_AOUO | D23: PVL - AOUO | E23: Yes | F23: PacPoint-KN07312020-Created for PVL Phase 1 Sprint 6 | G23: Source metadata
A24: Application__c | B24: PVL: Applications & Portal | C24: PVLAPRN | D24: PVL - APRN | E24: Yes | F24: PacPoint-KN091219-Created for PVL Sprint 1 Phase 1 | G24: Source metadata
A25: Application__c | B25: PVL: Applications & Portal | C25: PVLAT | D25: PVL - AT | E25: Yes | F25: PacPoint-KN123119-Created for PVL Sprint 3 Phase 1 | G25: Source metadata
A26: Application__c | B26: PVL: Applications & Portal | C26: PVLAUC | D26: PVL - AUC | E26: Yes | F26: Pac Point-DN010220 - Created for PVL Sprint 3 Phase 1 | G26: Source metadata
... A94: Application__c | B94: PVL: Applications & Portal | C94: PVLOTOTA | D94: PVL - OT/OTA | E94: Yes | F94: PacPoint-KN111119-Created for PVL Sprint 2 Phase 1 | G94: Source metadata
A95: Application__c | B95: PVL: Applications & Portal | C95: PVLOnlineRenewalRestore | D95: PVL - Online Renewal/Restore | E95: Yes | G95: Source metadata
A96: Application__c | B96: PVL: Applications & Portal | C96: PVLPA | D96: PVL - PA | E96: Yes | F96: PacPoint-DN04072020 - Created for PVL Sprint 4 Phase 1 | G96: Source metadata
A97: Application__c | B97: PVL: Applications & Portal | C97: PVLPCFR | D97: PVL - PCFR | E97: Yes | F97: PacPoint-KN091219-Created for PVL Sprint 1 Phase 1 | G97: Source metadata
A98: Application__c | B98: PVL: Applications & Portal | C98: PVLPCOEntity | D98: PVL - PCO - Entity | E98: Yes | F98: PacPoint-KN091219-Created for PVL Sprint 1 Phase 1 | G98: Source metadata
A99: Application__c | B99: PVL: Applications & Portal | C99: PVLPCORME | D99: PVL - PCO - RME | E99: Yes | F99: PacPoint-KN100119-Created for PVL Sprint 1 Phase 1 | G99: Source metadata
A100: Application__c | B100: PVL: Applications & Portal | C100: PVLPCOSoleProp | D100: PVL - PCO - Sole Prop | E100: Yes | F100: PacPoint-KN100119-Created for PVL Sprint 1 Phase 1 | G100: Source metadata
A101: Application__c | B101: PVL: Applications & Portal | C101: PVLPDGDSoleProp | D101: PVL - PD/GD - Sole Prop | E101: Yes | F101: PacPoint-KN102319-Created for PVL Sprint 2 Phase 1 | G101: Source metadata
A102: Application__c | B102: PVL: Applications & Portal | C102: PVL_PDREL | D102: PVL - PDREL | E102: Yes | F102: PacPoint-KN091219-Created for PVL Phase 1 Sprint 4 | G102: Source metadata
A103: Application__c | B103: PVL: Applications & Portal | C103: PVLPE | D103: PVL - PE | E103: Yes | F103: Pac Point-DN121619 - Created for PVL Sprint 2 Phase 1 | G103: Source metadata
A104: Application__c | B104: PVL: Applications & Portal | C104: PVLPH | D104: PVL - PH | E104: Yes | F104: PacPoint-KN123119-Created for PVL Sprint 3 Phase 1 | G104: Source metadata
A105: Application__c | B105: PVL: Applications & Portal | C105: PVL_PHT | D105: PVL - PHT | E105: Yes | F105: Created by MTX For JIRA Case VPVL-189 | G105: Source metadata
A106: Application__c | B106: PVL: Applications & Portal | C106: PVLPHY | D106: PVL - PHY | E106: Yes | F106: PacPoint-KN123119-Created for PVL Sprint 3 Phase 1 | G106: Source metadata
A107: Application__c | B107: PVL: Applications & Portal | C107: PVLPMP | D107: PVL - PMP | E107: Yes | F107: PacPoint-DN04342020 - Created for PVL Sprint 3 Phase 1 | G107: Source metadata
... A127: Application__c | B127: PVL: Applications & Portal | C127: PVLRNLPN | D127: PVL - RN/LPN | E127: Yes | F127: PacPoint-KN091219-Created for PVL Sprint 1 Phase 1 | G127: Source metadata
A128: Application__c | B128: PVL: Applications & Portal | C128: PVL_RN_LPNTEMP | D128: PVL - RN/LPNTEMP | E128: Yes | G128: Source metadata
A129: Application__c | B129: PVL: Applications & Portal | C129: PVLRNEW | D129: PVL - RNEW | E129: Yes | F129: PacPoint-KN102319-Created for PVL Sprint 2 Phase 1 | G129: Source metadata
A130: Application__c | B130: PVL: Applications & Portal | C130: PVLRS | D130: PVL - RS | E130: Yes | F130: PacPoint-DN04072020 - Created for PVL Sprint 4 Phase 1 | G130: Source metadata
A131: Application__c | B131: PVL: Applications & Portal | C131: PVLRT | D131: PVL - RT | E131: Yes | F131: Pac Point-DN010220 - Created for PVL Sprint 3 Phase 1 | G131: Source metadata
A132: Application__c | B132: PVL: Applications & Portal | C132: PVLResident | D132: PVL - Resident | E132: Yes | F132: PacPoint-KN112619-Created for PVL Sprint 2 Phase 1 | G132: Source metadata
A133: Application__c | B133: PVL: Applications & Portal | C133: PVLS | D133: PVL - S | E133: Yes | F133: PacPoint-DN06022020 - Created for PVL Sprint 4 Phase 1 | G133: Source metadata
A134: Application__c | B134: PVL: Applications & Portal | C134: PVLSPAUD | D134: PVL - SP/AUD | E134: Yes | F134: PacPoint-KN110419-Created for PVL Sprint 2 Phase 1 | G134: Source metadata
A135: Application__c | B135: PVL: Applications & Portal | C135: PVLSPP | D135: PVL - SPP | E135: Yes | F135: Pacific Point - JF08152022 - CASE 23448 | G135: Source metadata
A136: Application__c | B136: PVL: Applications & Portal | C136: PVLTAR | D136: PVL - TAR | E136: Yes | F136: PacPoint-KN111119-Created for PVL Sprint 2 Phase 1 | G136: Source metadata
A137: Application__c | B137: PVL: Applications & Portal | C137: PVLTB | D137: PVL - TB | E137: Yes | F137: PacPoint-DN06022020-Created for PVL Sprint 4 Phase 1 | G137: Source metadata
A138: Application__c | B138: PVL: Applications & Portal | C138: PVLTD | D138: PVL - TD | E138: Yes | F138: PacPoint-DN05012020 - Created for PVL Sprint 3 Phase 1 | G138: Source metadata
A139: Application__c | B139: PVL: Applications & Portal | C139: PVLTSATLPTSM | D139: PVL - TSA/TLP/TSM | E139: Yes | F139: Pac Point-DN010220 - Created for PVL Sprint 3 Phase 1 | G139: Source metadata
A140: Application__c | B140: PVL: Applications & Portal | C140: PVLUAA | D140: PVL - UAA | E140: Yes | F140: Pac Point-DN010220 - Created for PVL Sprint 3 Phase 1 | G140: Source metadata
A141: Application__c | B141: PVL: Applications & Portal | C141: PVLVE | D141: PVL - VE | E141: Yes | F141: Pac Point-DN010220 - Created for PVL Sprint 3 Phase 1 | G141: Source metadata
A142: Application__c | B142: PVL: Applications & Portal | C142: PVL_VEC | D142: PVL - VEC | E142: No | G142: Source metadata
A143: Application__c | B143: PVL: Applications & Portal | C143: PVL_VECR | D143: PVL - VECR | E143: Yes | G143: Source metadata
A144: Application__c | B144: PVL: Applications & Portal | C144: PVLVT | D144: PVL - VT | E144: Yes | F144: Pac Point-DN010220 - Created for PVL Sprint 3 Phase 1 | G144: Source metadata
A145: Application__c | B145: PVL: Applications & Portal | C145: PVLWBOND | D145: PVL - WBOND | E145: Yes | F145: PacPoint-DN03102020 - Created for PVL Sprint 3 Phase 1 | G145: Source metadata
A146: Application__c | B146: PVL: Applications & Portal | C146: PVL_WEDEC | D146: PVL - WEDEC | E146: Yes | F146: PacPoint-KN06032020-Created for PVL Phase 1 Sprint 4 | G146: Source metadata
A147: Application__c | B147: PVL: Applications & Portal | C147: PVL_WEDUC | D147: PVL - WEDUC | E147: Yes | F147: PacPoint-KN06032020-Created for PVL Phase 1 Sprint 4 | G147: Source metadata
A148: Application__c | B148: PVL: Applications & Portal | C148: PVLWUSEM | D148: PVL - WUSEM | E148: Yes | F148: PacPoint-KN07102020-Created for PVL Phase 1 Sprint 6 | G148: Source metadata
A149: Application__c | B149: PVL: Applications & Portal | C149: System | D149: System | E149: Yes | F149: System Use Only | G149: Source metadata
A150: Case | B150: Core: Account · Contact · Case | C150: BREG_Case | D150: BREG Case | E150: Yes | G150: Org describe (DCCA sandbox)
A151: Case | B151: Core: Account · Contact · Case | C151: BREG_Complaint | D151: BREG Complaint | E151: Yes | G151: Org describe (DCCA sandbox)
A152: Case | B152: Core: Account · Contact · Case | C152: BREG_Refund_Request_Case | D152: BREG Refund Request Case | E152: Yes | G152: Org describe (DCCA sandbox)
A153: Case | B153: Core: Account · Contact · Case | C153: CATV_Complaint | D153: CATV Complaint | E153: Yes | G153: Org describe (DCCA sandbox)
A154: Case | B154: Core: Account · Contact · Case | C154: PVL | D154: Call Center | E154: Yes | G154: Org describe (DCCA sandbox)
A155: Case | B155: Core: Account · Contact · Case | C155: DCA_Complaint | D155: DCA Complaint | E155: Yes | G155: Org describe (DCCA sandbox)
A156: Case | B156: Core: Account · Contact · Case | C156: DFI_Complaint | D156: DFI Complaint | E156: Yes | G156: Org describe (DCCA sandbox)
A157: Case | B157: Core: Account · Contact · Case | C157: DO_Referral | D157: DO Referral | E157: Yes | G157: Org describe (DCCA sandbox)
A158: Case | B158: Core: Account · Contact · Case | C158: Email_Support | D158: Email Support | E158: Yes | G158: Org describe (DCCA sandbox)
A159: Case | B159: Core: Account · Contact · Case | C159: General_Complaint | D159: General Complaint | E159: Yes | G159: Org describe (DCCA sandbox)
A160: Case | B160: Core: Account · Contact · Case | C160: INS_Complaint | D160: INS Complaint | E160: Yes | G160: Org describe (DCCA sandbox)
A161: Case | B161: Core: Account · Contact · Case | C161: OCP_Complaint | D161: OCP Complaint | E161: Yes | G161: Org describe (DCCA sandbox)
... A166: Contact | B166: Core: Account · Contact · Case | C166: DCCA_CATV | D166: DCCA CATV | E166: Yes | G166: Org describe (DCCA sandbox)
A167: Deficiency__c | B167: Securities: Filings & Exams | C167: Exam | D167: Exam | E167: Yes | F167: PacPoint-IC0100518 - Created for BREG phase 1 | G167: Source metadata
A168: Deficiency__c | B168: Securities: Filings & Exams | C168: Filing | D168: Filing | E168: Yes | F168: PacPoint-IC0100518 - Created for BREG phase 1 | G168: Source metadata
A169: FileDetails__c | B169: Securities: Filings & Exams | C169: SEB | D169: SEB | E169: Yes | F169: PacPoint-MV010819 - Created for BREG phase 1 | G169: Source metadata
A170: FileDetails__c | B170: Securities: Filings & Exams | C170: SEC | D170: SEC | E170: Yes | F170: PacPoint-MV010819 - Created for BREG phase 1 | G170: Source metadata
A171: Filing__c | B171: Securities: Filings & Exams | C171: BrokerDealer | D171: Broker-Dealer | E171: Yes | G171: Source metadata
A172: Filing__c | B172: Securities: Filings & Exams | C172: BrokerdealerAgent | D172: Broker-dealer Agent | E172: Yes | G172: Source metadata
A173: Filing__c | B173: Securities: Filings & Exams | C173: ByQualification | D173: By Qualification | E173: Yes | G173: Source metadata
A174: Filing__c | B174: Securities: Filings & Exams | C174: Franchise | D174: Franchise | E174: Yes | G174: Source metadata
A175: Filing__c | B175: Securities: Filings & Exams | C175: InvestmentAdviser | D175: Investment Adviser | E175: Yes | G175: Source metadata
A176: Filing__c | B176: Securities: Filings & Exams | C176: InvestmentAdviserRepresentative | D176: Investment Adviser Representative | E176: Yes | G176: Source metadata
A177: Filing__c | B177: Securities: Filings & Exams | C177: IssuerDealer | D177: Issuer Dealer | E177: Yes | G177: Source metadata
A178: Filing__c | B178: Securities: Filings & Exams | C178: IssuerDealerAgent | D178: Issuer Dealer Agent | E178: Yes | G178: Source metadata
A179: Filing__c | B179: Securities: Filings & Exams | C179: ModelAccreditedInvestor | D179: Model Accredited Investor | E179: Yes | G179: Source metadata
A180: Filing__c | B180: Securities: Filings & Exams | C180: MutualFund | D180: Mutual Fund | E180: Yes | G180: Source metadata
A181: Filing__c | B181: Securities: Filings & Exams | C181: RegulationA | D181: Regulation A | E181: Yes | G181: Source metadata
A182: Filing__c | B182: Securities: Filings & Exams | C182: RegulationD | D182: Regulation D | E182: Yes | G182: Source metadata
... A184: Filing__c | B184: Securities: Filings & Exams | C184: UnitInvestmentTrust | D184: Unit Investment Trust | E184: Yes | G184: Source metadata
A185: FiscalForm__c | B185: Payments & Finance | C185: DepositSlip | D185: Deposit Slip | E185: Yes | F185: PacPoint-AC081120 - Case# 10552 - Created for DCCA - Fiscal Forms CR - Creating to capture the Fiscal Form records. | G185: Source metadata
A186: FiscalForm__c | B186: Payments & Finance | C186: JV | D186: JV | E186: Yes | F186: PacPoint-AC081120 - Case# 10552 - Created for DCCA - Fiscal Forms CR - Creating to capture the Fiscal Form records. | G186: Source metadata
A187: FiscalForm__c | B187: Payments & Finance | C187: RECWKST | D187: RECWKST | E187: Yes | F187: PacPoint-AC081120 - Case# 10552 - Created for DCCA - Fiscal Forms CR - Creating to capture the Fiscal Form records. | G187: Source metadata
A188: FiscalForm__c | B188: Payments & Finance | C188: TDR | D188: TDR | E188: Yes | F188: PacPoint-AC081120 - Case# 10552 - Created for DCCA - Fiscal Forms CR - Creating to capture the Fiscal Form records. | G188: Source metadata
A189: INET_Request__c | B189: CATV / INET | C189: INET_Request | D189: INET Request | E189: Yes | G189: Source metadata
A190: Investigation__c | B190: Enforcement: SEB & RICO | C190: Investigation | D190: Investigation | E190: Yes | G190: Source metadata
A191: Investigation__c | B191: Enforcement: SEB & RICO | C191: Legal | D191: Legal | E191: Yes | G191: Source metadata
A192: Knowledge__kav | B192: Service & Work Management | C192: Articles | D192: Articles | E192: Yes | F192: Used on PVL Knowledge | G192: Source metadata
...

Sheet Picklist Values
A1: Picklist Values
A2: Field-specific picklist values, active values from the org describe for Account/Contact/Case/Payment, and all Global Value Sets (Object = "(Global Value Set)").
A3: ‹ Back to README
A5: Object API Name | B5: Field API Name | C5: Value Set | D5: API Value | E5: Label | F5: Default | G5: Restricted
A6: Account | B6: AccountSource | C6: (org describe) | D6: Advertisement | E6: Advertisement
A7: Account | B7: AccountSource | C7: (org describe) | D7: Customer Event | E7: Customer Event
A8: Account | B8: AccountSource | C8: (org describe) | D8: Employee Referral | E8: Employee Referral
A9: Account | B9: AccountSource | C9: (org describe) | D9: Google AdWords | E9: Google AdWords
A10: Account | B10: AccountSource | C10: (org describe) | D10: Other | E10: Other
A11: Account | B11: AccountSource | C11: (org describe) | D11: Partner | E11: Partner
A12: Account | B12: AccountSource | C12: (org describe) | D12: Purchased List | E12: Purchased List
A13: Account | B13: AccountSource | C13: (org describe) | D13: Trade Show | E13: Trade Show
A14: Account | B14: AccountSource | C14: (org describe) | D14: Webinar | E14: Webinar
A15: Account | B15: AccountSource | C15: (org describe) | D15: Website | E15: Website
A16: Account | B16: BillingCountryCode | C16: (org describe) | D16: AF | E16: Afghanistan | G16: Yes
A17: Account | B17: BillingCountryCode | C17: (org describe) | D17: AX | E17: Aland Islands | G17: Yes
A18: Account | B18: BillingCountryCode | C18: (org describe) | D18: AL | E18: Albania | G18: Yes
A19: Account | B19: BillingCountryCode | C19: (org describe) | D19: DZ | E19: Algeria | G19: Yes
A20: Account | B20: BillingCountryCode | C20: (org describe) | D20: AS | E20: American Samoa | G20: Yes
A21: Account | B21: BillingCountryCode | C21: (org describe) | D21: AD | E21: Andorra | G21: Yes
A22: Account | B22: BillingCountryCode | C22: (org describe) | D22: AO | E22: Angola | G22: Yes
A23: Account | B23: BillingCountryCode | C23: (org describe) | D23: AI | E23: Anguilla | G23: Yes
A24: Account | B24: BillingCountryCode | C24: (org describe) | D24: AQ | E24: Antarctica | G24: Yes
A25: Account | B25: BillingCountryCode | C25: (org describe) | D25: AG | E25: Antigua and Barbuda | G25: Yes
A26: Account | B26: BillingCountryCode | C26: (org describe) | D26: AR | E26: Argentina | G26: Yes
A27: Account | B27: BillingCountryCode | C27: (org describe) | D27: AM | E27: Armenia | G27: Yes
... A254: Account | B254: BillingCountryCode | C254: (org describe) | D254: GB | E254: United Kingdom | G254: Yes
A255: Account | B255: BillingCountryCode | C255: (org describe) | D255: US | E255: United States | F255: Yes | G255: Yes
A256: Account | B256: BillingCountryCode | C256: (org describe) | D256: UM | E256: United States Minor Outlying Islands | G256: Yes
A257: Account | B257: BillingCountryCode | C257: (org describe) | D257: UY | E257: Uruguay | G257: Yes
A258: Account | B258: BillingCountryCode | C258: (org describe) | D258: UZ | E258: Uzbekistan | G258: Yes
A259: Account | B259: BillingCountryCode | C259: (org describe) | D259: VU | E259: Vanuatu | G259: Yes
A260: Account | B260: BillingCountryCode | C260: (org describe) | D260: VE | E260: Venezuela, Bolivarian Republic of | G260: Yes
A261: Account | B261: BillingCountryCode | C261: (org describe) | D261: VN | E261: Viet Nam | G261: Yes
A262: Account | B262: BillingCountryCode | C262: (org describe) | D262: VG | E262: Virgin Islands, British | G262: Yes
A263: Account | B263: BillingCountryCode | C263: (org describe) | D263: VI | E263: Virgin Islands, U.S. | G263: Yes
A264: Account | B264: BillingCountryCode | C264: (org describe) | D264: WF | E264: Wallis and Futuna | G264: Yes
A265: Account | B265: BillingCountryCode | C265: (org describe) | D265: EH | E265: Western Sahara | G265: Yes
A266: Account | B266: BillingCountryCode | C266: (org describe) | D266: YE | E266: Yemen | G266: Yes
A267: Account | B267: BillingCountryCode | C267: (org describe) | D267: YU | E267: Yugoslavia | G267: Yes
... A894: Account | B894: Hi_Status__pc | C894: (org describe) | D894: WITHDRAWN | E894: WITHDRAWN | G894: Yes
A895: Account | B895: Industry | C895: (org describe) | D895: Agriculture | E895: Agriculture
A896: Account | B896: Industry | C896: (org describe) | D896: Apparel | E896: Apparel
A897: Account | B897: Industry | C897: (org describe) | D897: Banking | E897: Banking
A898: Account | B898: Industry | C898: (org describe) | D898: Biotechnology | E898: Biotechnology
A899: Account | B899: Industry | C899: (org describe) | D899: Chemicals | E899: Chemicals
A900: Account | B900: Industry | C900: (org describe) | D900: Communications | E900: Communications
A901: Account | B901: Industry | C901: (org describe) | D901: Construction | E901: Construction
A902: Account | B902: Industry | C902: (org describe) | D902: Consulting | E902: Consulting
A903: Account | B903: Industry | C903: (org describe) | D903: Education | E903: Education
A904: Account | B904: Industry | C904: (org describe) | D904: Electronics | E904: Electronics
A905: Account | B905: Industry | C905: (org describe) | D905: Energy | E905: Energy
A906: Account | B906: Industry | C906: (org describe) | D906: Engineering | E906: Engineering
... A926: Account | B926: Industry | C926: (org describe) | D926: Utilities | E926: Utilities
A927: Account | B927: Island__c | C927: (org describe) | D927: Hawaii | E927: Hawaii | G927: Yes
A928: Account | B928: Island__c | C928: (org describe) | D928: Kauai | E928: Kauai | G928: Yes
A929: Account | B929: Island__c | C929: (org describe) | D929: Lanai | E929: Lanai | G929: Yes
A930: Account | B930: Island__c | C930: (org describe) | D930: Maui | E930: Maui | G930: Yes
A931: Account | B931: Island__c | C931: (org describe) | D931: Molokai | E931: Molokai | G931: Yes
A932: Account | B932: Island__c | C932: (org describe) | D932: Oahu | E932: Oahu | G932: Yes
A933: Account | B933: Ownership | C933: (org describe) | D933: Public | E933: Public
A934: Account | B934: Ownership | C934: (org describe) | D934: Private | E934: Private
A935: Account | B935: Ownership | C935: (org describe) | D935: Subsidiary | E935: Subsidiary
A936: Account | B936: Ownership | C936: (org describe) | D936: Other | E936: Other
A937: Account | B937: PersonGenderIdentity | C937: (org describe) | D937: Male | E937: Male | G937: Yes
A938: Account | B938: PersonGenderIdentity | C938: (org describe) | D938: Female | E938: Female | G938: Yes
A939: Account | B939: PersonGenderIdentity | C939: (org describe) | D939: Nonbinary | E939: Nonbinary | G939: Yes
A940: Account | B940: PersonGenderIdentity | C940: (org describe) | D940: Not Listed | E940: Not Listed | G940: Yes
A941: Account | B941: PersonMailingCountryCode | C941: (org describe) | D941: AF | E941: Afghanistan | G941: Yes
A942: Account | B942: PersonMailingCountryCode | C942: (org describe) | D942: AX | E942: Aland Islands | G942: Yes
A943: Account | B943: PersonMailingCountryCode | C943: (org describe) | D943: AL | E943: Albania | G943: Yes
A944: Account | B944: PersonMailingCountryCode | C944: (org describe) | D944: DZ | E944: Algeria | G944: Yes
A945: Account | B945: PersonMailingCountryCode | C945: (org describe) | D945: AS | E945: American Samoa | G945: Yes
A946: Account | B946: PersonMailingCountryCode | C946: (org describe) | D946: AD | E946: Andorra | G946: Yes
A947: Account | B947: PersonMailingCountryCode | C947: (org describe) | D947: AO | E947: Angola | G947: Yes
A948: Account | B948: PersonMailingCountryCode | C948: (org describe) | D948: AI | E948: Anguilla | G948: Yes
... A1179: Account | B1179: PersonMailingCountryCode | C1179: (org describe) | D1179: GB | E1179: United Kingdom | G1179: Yes
A1180: Account | B1180: PersonMailingCountryCode | C1180: (org describe) | D1180: US | E1180: United States | F1180: Yes | G1180: Yes
A1181: Account | B1181: PersonMailingCountryCode | C1181: (org describe) | D1181: UM | E1181: United States Minor Outlying Islands | G1181: Yes
A1182: Account | B1182: PersonMailingCountryCode | C1182: (org describe) | D1182: UY | E1182: Uruguay | G1182: Yes
A1183: Account | B1183: PersonMailingCountryCode | C1183: (org describe) | D1183: UZ | E1183: Uzbekistan | G1183: Yes
A1184: Account | B1184: PersonMailingCountryCode | C1184: (org describe) | D1184: VU | E1184: Vanuatu | G1184: Yes
A1185: Account | B1185: PersonMailingCountryCode | C1185: (org describe) | D1185: VE | E1185: Venezuela, Bolivarian Republic of | G1185: Yes
A1186: Account | B1186: PersonMailingCountryCode | C1186: (org describe) | D1186: VN | E1186: Viet Nam | G1186: Yes
A1187: Account | B1187: PersonMailingCountryCode | C1187: (org describe) | D1187: VG | E1187: Virgin Islands, British | G1187: Yes
A1188: Account | B1188: PersonMailingCountryCode | C1188: (org describe) | D1188: VI | E1188: Virgin Islands, U.S. | G1188: Yes
A1189: Account | B1189: PersonMailingCountryCode | C1189: (org describe) | D1189: WF | E1189: Wallis and Futuna | G1189: Yes
A1190: Account | B1190: PersonMailingCountryCode | C1190: (org describe) | D1190: EH | E1190: Western Sahara | G1190: Yes
A1191: Account | B1191: PersonMailingCountryCode | C1191: (org describe) | D1191: YE | E1191: Yemen | G1191: Yes
A1192: Account | B1192: PersonMailingCountryCode | C1192: (org describe) | D1192: YU | E1192: Yugoslavia | G1192: Yes
... A1792: Account | B1792: PersonOtherCountryCode | C1792: (org describe) | D1792: GB | E1792: United Kingdom | G1792: Yes
A1793: Account | B1793: PersonOtherCountryCode | C1793: (org describe) | D1793: US | E1793: United States | F1793: Yes | G1793: Yes
A1794: Account | B1794: PersonOtherCountryCode | C1794: (org describe) | D1794: UM | E1794: United States Minor Outlying Islands | G1794: Yes
A1795: Account | B1795: PersonOtherCountryCode | C1795: (org describe) | D1795: UY | E1795: Uruguay | G1795: Yes
A1796: Account | B1796: PersonOtherCountryCode | C1796: (org describe) | D1796: UZ | E1796: Uzbekistan | G1796: Yes
A1797: Account | B1797: PersonOtherCountryCode | C1797: (org describe) | D1797: VU | E1797: Vanuatu | G1797: Yes
A1798: Account | B1798: PersonOtherCountryCode | C1798: (org describe) | D1798: VE | E1798: Venezuela, Bolivarian Republic of | G1798: Yes
A1799: Account | B1799: PersonOtherCountryCode | C1799: (org describe) | D1799: VN | E1799: Viet Nam | G1799: Yes
A1800: Account | B1800: PersonOtherCountryCode | C1800: (org describe) | D1800: VG | E1800: Virgin Islands, British | G1800: Yes
A1801: Account | B1801: PersonOtherCountryCode | C1801: (org describe) | D1801: VI | E1801: Virgin Islands, U.S. | G1801: Yes
...

Sheet ERD - Overview
A1: ERD: Domain Overview
A2: Account, Contact and Case at the centre; lines show relationship fields crossing between domains (number and thickness = count; purple = to/from Core).
A3: ‹ Back to README
A4: Use View ▸ Zoom to enlarge; the image is stored at 2× resolution so it stays sharp when zoomed in.

Sheet ERD - Core Acct-Contact-Case
A1: ERD: Core: Account · Contact · Case
A2: Shared CRM backbone used by every division.
A3: ‹ Back to README
A4: Legend: solid line = master-detail (child owned by parent) · dashed line = lookup · crow's foot = "many" side · boxes with attribute rows = objects in this domain (Label, Fields, CodeRefs) · plain boxes = objects from other domains or managed packages. Lookups to User are omitted.
A60: Objects in this domain (3) | F60: Shown with 7 related objects from other domains.
A61: Object API Name | B61: Label | C61: Fields | D61: Relationship Fields | E61: Code References
A62: Account | B62: =IFERROR(INDEX('Object Catalogue'!$B:$B,MATCH(A62,'Object Catalogue'!$A:$A,0)),"") | C62: =IFERROR(INDEX('Object Catalogue'!$H:$H,MATCH(A62,'Object Catalogue'!$A:$A,0)),"") | D62: =IFERROR(INDEX('Object Catalogue'!$K:$K,MATCH(A62,'Object Catalogue'!$A:$A,0)),"") | E62: =IFERROR(INDEX('Object Catalogue'!$O:$O,MATCH(A62,'Object Catalogue'!$A:$A,0)),"")
A63: Case | B63: =IFERROR(INDEX('Object Catalogue'!$B:$B,MATCH(A63,'Object Catalogue'!$A:$A,0)),"") | C63: =IFERROR(INDEX('Object Catalogue'!$H:$H,MATCH(A63,'Object Catalogue'!$A:$A,0)),"") | D63: =IFERROR(INDEX('Object Catalogue'!$K:$K,MATCH(A63,'Object Catalogue'!$A:$A,0)),"") | E63: =IFERROR(INDEX('Object Catalogue'!$O:$O,MATCH(A63,'Object Catalogue'!$A:$A,0)),"")
A64: Contact | B64: =IFERROR(INDEX('Object Catalogue'!$B:$B,MATCH(A64,'Object Catalogue'!$A:$A,0)),"") | C64: =IFERROR(INDEX('Object Catalogue'!$H:$H,MATCH(A64,'Object Catalogue'!$A:$A,0)),"") | D64: =IFERROR(INDEX('Object Catalogue'!$K:$K,MATCH(A64,'Object Catalogue'!$A:$A,0)),"") | E64: =IFERROR(INDEX('Object Catalogue'!$O:$O,MATCH(A64,'Object Catalogue'!$A:$A,0)),"")

Sheet ERD - BREG Registration
A1: ERD: BREG: Business Registration
A2: Entities, filings, transactions, annuals, certificates and documents for the Business Registration Division.
A3: ‹ Back to README
A4: Legend: solid line = master-detail (child owned by parent) · dashed line = lookup · crow's foot = "many" side · boxes with attribute rows = objects in this domain (Label, Fields, CodeRefs) · plain boxes = objects from other domains or managed packages. Lookups to User are omitted.
A82: Objects in this domain (31) | F82: Shown with 6 related objects from other domains.
A83: Object API Name | B83: Label | C83: Fields | D83: Relationship Fields | E83: Code References
A84: BREG_ADDRESS_PROTECTION__c | B84: =IFERROR(INDEX('Object Catalogue'!$B:$B,MATCH(A84,'Object Catalogue'!$A:$A,0)),"") | C84: =IFERROR(INDEX('Object Catalogue'!$H:$H,MATCH(A84,'Object Catalogue'!$A:$A,0)),"") | D84: =IFERROR(INDEX('Object Catalogue'!$K:$K,MATCH(A84,'Object Catalogue'!$A:$A,0)),"") | E84: =IFERROR(INDEX('Object Catalogue'!$O:$O,MATCH(A84,'Object Catalogue'!$A:$A,0)),"")
A85: BREG_File_Number_Sequence__c | B85: =IFERROR(INDEX('Object Catalogue'!$B:$B,MATCH(A85,'Object Catalogue'!$A:$A,0)),"") | C85: =IFERROR(INDEX('Object Catalogue'!$H:$H,MATCH(A85,'Object Catalogue'!$A:$A,0)),"") | D85: =IFERROR(INDEX('Object Catalogue'!$K:$K,MATCH(A85,'Object Catalogue'!$A:$A,0)),"") | E85: =IFERROR(INDEX('Object Catalogue'!$O:$O,MATCH(A85,'Object Catalogue'!$A:$A,0)),"")
A86: breg_Account_Affiliation__c | B86: =IFERROR(INDEX('Object Catalogue'!$B:$B,MATCH(A86,'Object Catalogue'!$A:$A,0)),"") | C86: =IFERROR(INDEX('Object Catalogue'!$H:$H,MATCH(A86,'Object Catalogue'!$A:$A,0)),"") | D86: =IFERROR(INDEX('Object Catalogue'!$K:$K,MATCH(A86,'Object Catalogue'!$A:$A,0)),"") | E86: =IFERROR(INDEX('Object Catalogue'!$O:$O,MATCH(A86,'Object Catalogue'!$A:$A,0)),"")
A87: breg_Acquisition_Transaction__c | B87: =IFERROR(INDEX('Object Catalogue'!$B:$B,MATCH(A87,'Object Catalogue'!$A:$A,0)),"") | C87: =IFERROR(INDEX('Object Catalogue'!$H:$H,MATCH(A87,'Object Catalogue'!$A:$A,0)),"") | D87: =IFERROR(INDEX('Object Catalogue'!$K:$K,MATCH(A87,'Object Catalogue'!$A:$A,0)),"") | E87: =IFERROR(INDEX('Object Catalogue'!$O:$O,MATCH(A87,'Object Catalogue'!$A:$A,0)),"")
A88: breg_Agent_Search_List__c | B88: =IFERROR(INDEX('Object Catalogue'!$B:$B,MATCH(A88,'Object Catalogue'!$A:$A,0)),"") | C88: =IFERROR(INDEX('Object Catalogue'!$H:$H,MATCH(A88,'Object Catalogue'!$A:$A,0)),"") | D88: =IFERROR(INDEX('Object Catalogue'!$K:$K,MATCH(A88,'Object Catalogue'!$A:$A,0)),"") | E88: =IFERROR(INDEX('Object Catalogue'!$O:$O,MATCH(A88,'Object Catalogue'!$A:$A,0)),"")
A89: breg_Agent_Search_Result__c | B89: =IFERROR(INDEX('Object Catalogue'!$B:$B,MATCH(A89,'Object Catalogue'!$A:$A,0)),"") | C89: =IFERROR(INDEX('Object Catalogue'!$H:$H,MATCH(A89,'Object Catalogue'!$A:$A,0)),"") | D89: =IFERROR(INDEX('Object Catalogue'!$K:$K,MATCH(A89,'Object Catalogue'!$A:$A,0)),"") | E89: =IFERROR(INDEX('Object Catalogue'!$O:$O,MATCH(A89,'Object Catalogue'!$A:$A,0)),"")
A90: breg_Annual__c | B90: =IFERROR(INDEX('Object Catalogue'!$B:$B,MATCH(A90,'Object Catalogue'!$A:$A,0)),"") | C90: =IFERROR(INDEX('Object Catalogue'!$H:$H,MATCH(A90,'Object Catalogue'!$A:$A,0)),"") | D90: =IFERROR(INDEX('Object Catalogue'!$K:$K,MATCH(A90,'Object Catalogue'!$A:$A,0)),"") | E90: =IFERROR(INDEX('Object Catalogue'!$O:$O,MATCH(A90,'Object Catalogue'!$A:$A,0)),"")
A91: breg_BRIM_Transaction_Event__b | B91: =IFERROR(INDEX('Object Catalogue'!$B:$B,MATCH(A91,'Object Catalogue'!$A:$A,0)),"") | C91: =IFERROR(INDEX('Object Catalogue'!$H:$H,MATCH(A91,'Object Catalogue'!$A:$A,0)),"") | D91: =IFERROR(INDEX('Object Catalogue'!$K:$K,MATCH(A91,'Object Catalogue'!$A:$A,0)),"") | E91: =IFERROR(INDEX('Object Catalogue'!$O:$O,MATCH(A91,'Object Catalogue'!$A:$A,0)),"")
A92: breg_Batch_Job_Execution__c | B92: =IFERROR(INDEX('Object Catalogue'!$B:$B,MATCH(A92,'Object Catalogue'!$A:$A,0)),"") | C92: =IFERROR(INDEX('Object Catalogue'!$H:$H,MATCH(A92,'Object Catalogue'!$A:$A,0)),"") | D92: =IFERROR(INDEX('Object Catalogue'!$K:$K,MATCH(A92,'Object Catalogue'!$A:$A,0)),"") | E92: =IFERROR(INDEX('Object Catalogue'!$O:$O,MATCH(A92,'Object Catalogue'!$A:$A,0)),"")
A93: breg_Case_Staging__c | B93: =IFERROR(INDEX('Object Catalogue'!$B:$B,MATCH(A93,'Object Catalogue'!$A:$A,0)),"") | C93: =IFERROR(INDEX('Object Catalogue'!$H:$H,MATCH(A93,'Object Catalogue'!$A:$A,0)),"") | D93: =IFERROR(INDEX('Object Catalogue'!$K:$K,MATCH(A93,'Object Catalogue'!$A:$A,0)),"") | E93: =IFERROR(INDEX('Object Catalogue'!$O:$O,MATCH(A93,'Object Catalogue'!$A:$A,0)),"")
A94: breg_Certificate__c | B94: =IFERROR(INDEX('Object Catalogue'!$B:$B,MATCH(A94,'Object Catalogue'!$A:$A,0)),"") | C94: =IFERROR(INDEX('Object Catalogue'!$H:$H,MATCH(A94,'Object Catalogue'!$A:$A,0)),"") | D94: =IFERROR(INDEX('Object Catalogue'!$K:$K,MATCH(A94,'Object Catalogue'!$A:$A,0)),"") | E94: =IFERROR(INDEX('Object Catalogue'!$O:$O,MATCH(A94,'Object Catalogue'!$A:$A,0)),"")
A95: breg_DBEDT_Report__c | B95: =IFERROR(INDEX('Object Catalogue'!$B:$B,MATCH(A95,'Object Catalogue'!$A:$A,0)),"") | C95: =IFERROR(INDEX('Object Catalogue'!$H:$H,MATCH(A95,'Object Catalogue'!$A:$A,0)),"") | D95: =IFERROR(INDEX('Object Catalogue'!$K:$K,MATCH(A95,'Object Catalogue'!$A:$A,0)),"") | E95: =IFERROR(INDEX('Object Catalogue'!$O:$O,MATCH(A95,'Object Catalogue'!$A:$A,0)),"")
... A114: breg_Transaction__c | B114: =IFERROR(INDEX('Object Catalogue'!$B:$B,MATCH(A114,'Object Catalogue'!$A:$A,0)),"") | C114: =IFERROR(INDEX('Object Catalogue'!$H:$H,MATCH(A114,'Object Catalogue'!$A:$A,0)),"") | D114: =IFERROR(INDEX('Object Catalogue'!$K:$K,MATCH(A114,'Object Catalogue'!$A:$A,0)),"") | E114: =IFERROR(INDEX('Object Catalogue'!$O:$O,MATCH(A114,'Object Catalogue'!$A:$A,0)),"")

Sheet ERD - BREG Web Staging
A1: ERD: BREG: Legacy Web Filing Staging
A2: Staging tables that receive legacy RDPMS web filings before they are mapped onto a Case.
A3: ‹ Back to README
A4: Legend: solid line = master-detail (child owned by parent) · dashed line = lookup · crow's foot = "many" side · boxes with attribute rows = objects in this domain (Label, Fields, CodeRefs) · plain boxes = objects from other domains or managed packages. Lookups to User are omitted.
A35: Objects in this domain (8) | F35: Shown with 2 related objects from other domains.
A36: Object API Name | B36: Label | C36: Fields | D36: Relationship Fields | E36: Code References
A37: breg_WEB_WEB_ADDRESSES__c | B37: =IFERROR(INDEX('Object Catalogue'!$B:$B,MATCH(A37,'Object Catalogue'!$A:$A,0)),"") | C37: =IFERROR(INDEX('Object Catalogue'!$H:$H,MATCH(A37,'Object Catalogue'!$A:$A,0)),"") | D37: =IFERROR(INDEX('Object Catalogue'!$K:$K,MATCH(A37,'Object Catalogue'!$A:$A,0)),"") | E37: =IFERROR(INDEX('Object Catalogue'!$O:$O,MATCH(A37,'Object Catalogue'!$A:$A,0)),"")
A38: breg_WEB_WEB_BUSINESS_INFO__c | B38: =IFERROR(INDEX('Object Catalogue'!$B:$B,MATCH(A38,'Object Catalogue'!$A:$A,0)),"") | C38: =IFERROR(INDEX('Object Catalogue'!$H:$H,MATCH(A38,'Object Catalogue'!$A:$A,0)),"") | D38: =IFERROR(INDEX('Object Catalogue'!$K:$K,MATCH(A38,'Object Catalogue'!$A:$A,0)),"") | E38: =IFERROR(INDEX('Object Catalogue'!$O:$O,MATCH(A38,'Object Catalogue'!$A:$A,0)),"")
A39: breg_WEB_WEB_FILING_INFO__c | B39: =IFERROR(INDEX('Object Catalogue'!$B:$B,MATCH(A39,'Object Catalogue'!$A:$A,0)),"") | C39: =IFERROR(INDEX('Object Catalogue'!$H:$H,MATCH(A39,'Object Catalogue'!$A:$A,0)),"") | D39: =IFERROR(INDEX('Object Catalogue'!$K:$K,MATCH(A39,'Object Catalogue'!$A:$A,0)),"") | E39: =IFERROR(INDEX('Object Catalogue'!$O:$O,MATCH(A39,'Object Catalogue'!$A:$A,0)),"")
A40: breg_WEB_WEB_FILING_YEARS__c | B40: =IFERROR(INDEX('Object Catalogue'!$B:$B,MATCH(A40,'Object Catalogue'!$A:$A,0)),"") | C40: =IFERROR(INDEX('Object Catalogue'!$H:$H,MATCH(A40,'Object Catalogue'!$A:$A,0)),"") | D40: =IFERROR(INDEX('Object Catalogue'!$K:$K,MATCH(A40,'Object Catalogue'!$A:$A,0)),"") | E40: =IFERROR(INDEX('Object Catalogue'!$O:$O,MATCH(A40,'Object Catalogue'!$A:$A,0)),"")
A41: breg_WEB_WEB_PERSONS__c | B41: =IFERROR(INDEX('Object Catalogue'!$B:$B,MATCH(A41,'Object Catalogue'!$A:$A,0)),"") | C41: =IFERROR(INDEX('Object Catalogue'!$H:$H,MATCH(A41,'Object Catalogue'!$A:$A,0)),"") | D41: =IFERROR(INDEX('Object Catalogue'!$K:$K,MATCH(A41,'Object Catalogue'!$A:$A,0)),"") | E41: =IFERROR(INDEX('Object Catalogue'!$O:$O,MATCH(A41,'Object Catalogue'!$A:$A,0)),"")
A42: breg_WEB_WEB_RESUB__c | B42: =IFERROR(INDEX('Object Catalogue'!$B:$B,MATCH(A42,'Object Catalogue'!$A:$A,0)),"") | C42: =IFERROR(INDEX('Object Catalogue'!$H:$H,MATCH(A42,'Object Catalogue'!$A:$A,0)),"") | D42: =IFERROR(INDEX('Object Catalogue'!$K:$K,MATCH(A42,'Object Catalogue'!$A:$A,0)),"") | E42: =IFERROR(INDEX('Object Catalogue'!$O:$O,MATCH(A42,'Object Catalogue'!$A:$A,0)),"")
A43: breg_WEB_WEB_STOCKS__c | B43: =IFERROR(INDEX('Object Catalogue'!$B:$B,MATCH(A43,'Object Catalogue'!$A:$A,0)),"") | C43: =IFERROR(INDEX('Object Catalogue'!$H:$H,MATCH(A43,'Object Catalogue'!$A:$A,0)),"") | D43: =IFERROR(INDEX('Object Catalogue'!$K:$K,MATCH(A43,'Object Catalogue'!$A:$A,0)),"") | E43: =IFERROR(INDEX('Object Catalogue'!$O:$O,MATCH(A43,'Object Catalogue'!$A:$A,0)),"")
A44: breg_WEB_WEB_TRADE_MARKS__c | B44: =IFERROR(INDEX('Object Catalogue'!$B:$B,MATCH(A44,'Object Catalogue'!$A:$A,0)),"") | C44: =IFERROR(INDEX('Object Catalogue'!$H:$H,MATCH(A44,'Object Catalogue'!$A:$A,0)),"") | D44: =IFERROR(INDEX('Object Catalogue'!$K:$K,MATCH(A44,'Object Catalogue'!$A:$A,0)),"") | E44: =IFERROR(INDEX('Object Catalogue'!$O:$O,MATCH(A44,'Object Catalogue'!$A:$A,0)),"")

Sheet ERD - PVL Applications
A1: ERD: PVL: Applications & Portal
A2: Professional & Vocational Licensing applications, draft/metadata-driven online forms and portal users.
A3: ‹ Back to README
A4: Legend: solid line = master-detail (child owned by parent) · dashed line = lookup · crow's foot = "many" side · boxes with attribute rows = objects in this domain (Label, Fields, CodeRefs) · plain boxes = objects from other domains or managed packages. Lookups to User are omitted.
A81: Objects in this domain (21) | F81: Shown with 6 related objects from other domains.
A82: Object API Name | B82: Label | C82: Fields | D82: Relationship Fields | E82: Code References
A83: AdditionalDependentAppsLicenses__c | B83: =IFERROR(INDEX('Object Catalogue'!$B:$B,MATCH(A83,'Object Catalogue'!$A:$A,0)),"") | C83: =IFERROR(INDEX('Object Catalogue'!$H:$H,MATCH(A83,'Object Catalogue'!$A:$A,0)),"") | D83: =IFERROR(INDEX('Object Catalogue'!$K:$K,MATCH(A83,'Object Catalogue'!$A:$A,0)),"") | E83: =IFERROR(INDEX('Object Catalogue'!$O:$O,MATCH(A83,'Object Catalogue'!$A:$A,0)),"")
A84: ApplicationClassifications__c | B84: =IFERROR(INDEX('Object Catalogue'!$B:$B,MATCH(A84,'Object Catalogue'!$A:$A,0)),"") | C84: =IFERROR(INDEX('Object Catalogue'!$H:$H,MATCH(A84,'Object Catalogue'!$A:$A,0)),"") | D84: =IFERROR(INDEX('Object Catalogue'!$K:$K,MATCH(A84,'Object Catalogue'!$A:$A,0)),"") | E84: =IFERROR(INDEX('Object Catalogue'!$O:$O,MATCH(A84,'Object Catalogue'!$A:$A,0)),"")
A85: ApplicationRequirement__c | B85: =IFERROR(INDEX('Object Catalogue'!$B:$B,MATCH(A85,'Object Catalogue'!$A:$A,0)),"") | C85: =IFERROR(INDEX('Object Catalogue'!$H:$H,MATCH(A85,'Object Catalogue'!$A:$A,0)),"") | D85: =IFERROR(INDEX('Object Catalogue'!$K:$K,MATCH(A85,'Object Catalogue'!$A:$A,0)),"") | E85: =IFERROR(INDEX('Object Catalogue'!$O:$O,MATCH(A85,'Object Catalogue'!$A:$A,0)),"")
A86: Application_Cache__c | B86: =IFERROR(INDEX('Object Catalogue'!$B:$B,MATCH(A86,'Object Catalogue'!$A:$A,0)),"") | C86: =IFERROR(INDEX('Object Catalogue'!$H:$H,MATCH(A86,'Object Catalogue'!$A:$A,0)),"") | D86: =IFERROR(INDEX('Object Catalogue'!$K:$K,MATCH(A86,'Object Catalogue'!$A:$A,0)),"") | E86: =IFERROR(INDEX('Object Catalogue'!$O:$O,MATCH(A86,'Object Catalogue'!$A:$A,0)),"")
A87: Application_Log__c | B87: =IFERROR(INDEX('Object Catalogue'!$B:$B,MATCH(A87,'Object Catalogue'!$A:$A,0)),"") | C87: =IFERROR(INDEX('Object Catalogue'!$H:$H,MATCH(A87,'Object Catalogue'!$A:$A,0)),"") | D87: =IFERROR(INDEX('Object Catalogue'!$K:$K,MATCH(A87,'Object Catalogue'!$A:$A,0)),"") | E87: =IFERROR(INDEX('Object Catalogue'!$O:$O,MATCH(A87,'Object Catalogue'!$A:$A,0)),"")
A88: Application_Meta_Data__c | B88: =IFERROR(INDEX('Object Catalogue'!$B:$B,MATCH(A88,'Object Catalogue'!$A:$A,0)),"") | C88: =IFERROR(INDEX('Object Catalogue'!$H:$H,MATCH(A88,'Object Catalogue'!$A:$A,0)),"") | D88: =IFERROR(INDEX('Object Catalogue'!$K:$K,MATCH(A88,'Object Catalogue'!$A:$A,0)),"") | E88: =IFERROR(INDEX('Object Catalogue'!$O:$O,MATCH(A88,'Object Catalogue'!$A:$A,0)),"")
A89: Application__c | B89: =IFERROR(INDEX('Object Catalogue'!$B:$B,MATCH(A89,'Object Catalogue'!$A:$A,0)),"") | C89: =IFERROR(INDEX('Object Catalogue'!$H:$H,MATCH(A89,'Object Catalogue'!$A:$A,0)),"") | D89: =IFERROR(INDEX('Object Catalogue'!$K:$K,MATCH(A89,'Object Catalogue'!$A:$A,0)),"") | E89: =IFERROR(INDEX('Object Catalogue'!$O:$O,MATCH(A89,'Object Catalogue'!$A:$A,0)),"")
A90: ApprenticeApplicationCounter__c | B90: =IFERROR(INDEX('Object Catalogue'!$B:$B,MATCH(A90,'Object Catalogue'!$A:$A,0)),"") | C90: =IFERROR(INDEX('Object Catalogue'!$H:$H,MATCH(A90,'Object Catalogue'!$A:$A,0)),"") | D90: =IFERROR(INDEX('Object Catalogue'!$K:$K,MATCH(A90,'Object Catalogue'!$A:$A,0)),"") | E90: =IFERROR(INDEX('Object Catalogue'!$O:$O,MATCH(A90,'Object Catalogue'!$A:$A,0)),"")
A91: Card_Cache__c | B91: =IFERROR(INDEX('Object Catalogue'!$B:$B,MATCH(A91,'Object Catalogue'!$A:$A,0)),"") | C91: =IFERROR(INDEX('Object Catalogue'!$H:$H,MATCH(A91,'Object Catalogue'!$A:$A,0)),"") | D91: =IFERROR(INDEX('Object Catalogue'!$K:$K,MATCH(A91,'Object Catalogue'!$A:$A,0)),"") | E91: =IFERROR(INDEX('Object Catalogue'!$O:$O,MATCH(A91,'Object Catalogue'!$A:$A,0)),"")
A92: Card_Meta_Data__c | B92: =IFERROR(INDEX('Object Catalogue'!$B:$B,MATCH(A92,'Object Catalogue'!$A:$A,0)),"") | C92: =IFERROR(INDEX('Object Catalogue'!$H:$H,MATCH(A92,'Object Catalogue'!$A:$A,0)),"") | D92: =IFERROR(INDEX('Object Catalogue'!$K:$K,MATCH(A92,'Object Catalogue'!$A:$A,0)),"") | E92: =IFERROR(INDEX('Object Catalogue'!$O:$O,MATCH(A92,'Object Catalogue'!$A:$A,0)),"")
A93: Education__c | B93: =IFERROR(INDEX('Object Catalogue'!$B:$B,MATCH(A93,'Object Catalogue'!$A:$A,0)),"") | C93: =IFERROR(INDEX('Object Catalogue'!$H:$H,MATCH(A93,'Object Catalogue'!$A:$A,0)),"") | D93: =IFERROR(INDEX('Object Catalogue'!$K:$K,MATCH(A93,'Object Catalogue'!$A:$A,0)),"") | E93: =IFERROR(INDEX('Object Catalogue'!$O:$O,MATCH(A93,'Object Catalogue'!$A:$A,0)),"")
A94: Field_Filter__c | B94: =IFERROR(INDEX('Object Catalogue'!$B:$B,MATCH(A94,'Object Catalogue'!$A:$A,0)),"") | C94: =IFERROR(INDEX('Object Catalogue'!$H:$H,MATCH(A94,'Object Catalogue'!$A:$A,0)),"") | D94: =IFERROR(INDEX('Object Catalogue'!$K:$K,MATCH(A94,'Object Catalogue'!$A:$A,0)),"") | E94: =IFERROR(INDEX('Object Catalogue'!$O:$O,MATCH(A94,'Object Catalogue'!$A:$A,0)),"")
... A103: Requisition__c | B103: =IFERROR(INDEX('Object Catalogue'!$B:$B,MATCH(A103,'Object Catalogue'!$A:$A,0)),"") | C103: =IFERROR(INDEX('Object Catalogue'!$H:$H,MATCH(A103,'Object Catalogue'!$A:$A,0)),"") | D103: =IFERROR(INDEX('Object Catalogue'!$K:$K,MATCH(A103,'Object Catalogue'!$A:$A,0)),"") | E103: =IFERROR(INDEX('Object Catalogue'!$O:$O,MATCH(A103,'Object Catalogue'!$A:$A,0)),"")

Sheet ERD - PVL Licenses
A1: ERD: PVL: Licenses & License Types
A2: Issued licenses, license-type configuration, requirements, insurance/bonds and notifications.
A3: ‹ Back to README
A4: Legend: solid line = master-detail (child owned by parent) · dashed line = lookup · crow's foot = "many" side · boxes with attribute rows = objects in this domain (Label, Fields, CodeRefs) · plain boxes = objects from other domains or managed packages. Lookups to User are omitted.
A70: Objects in this domain (32) | F70: Shown with 5 related objects from other domains.
A71: Object API Name | B71: Label | C71: Fields | D71: Relationship Fields | E71: Code References
A72: AccountName__c | B72: =IFERROR(INDEX('Object Catalogue'!$B:$B,MATCH(A72,'Object Catalogue'!$A:$A,0)),"") | C72: =IFERROR(INDEX('Object Catalogue'!$H:$H,MATCH(A72,'Object Catalogue'!$A:$A,0)),"") | D72: =IFERROR(INDEX('Object Catalogue'!$K:$K,MATCH(A72,'Object Catalogue'!$A:$A,0)),"") | E72: =IFERROR(INDEX('Object Catalogue'!$O:$O,MATCH(A72,'Object Catalogue'!$A:$A,0)),"")
A73: AssociatedLicense__c | B73: =IFERROR(INDEX('Object Catalogue'!$B:$B,MATCH(A73,'Object Catalogue'!$A:$A,0)),"") | C73: =IFERROR(INDEX('Object Catalogue'!$H:$H,MATCH(A73,'Object Catalogue'!$A:$A,0)),"") | D73: =IFERROR(INDEX('Object Catalogue'!$K:$K,MATCH(A73,'Object Catalogue'!$A:$A,0)),"") | E73: =IFERROR(INDEX('Object Catalogue'!$O:$O,MATCH(A73,'Object Catalogue'!$A:$A,0)),"")
A74: Associated_Account__c | B74: =IFERROR(INDEX('Object Catalogue'!$B:$B,MATCH(A74,'Object Catalogue'!$A:$A,0)),"") | C74: =IFERROR(INDEX('Object Catalogue'!$H:$H,MATCH(A74,'Object Catalogue'!$A:$A,0)),"") | D74: =IFERROR(INDEX('Object Catalogue'!$K:$K,MATCH(A74,'Object Catalogue'!$A:$A,0)),"") | E74: =IFERROR(INDEX('Object Catalogue'!$O:$O,MATCH(A74,'Object Catalogue'!$A:$A,0)),"")
A75: BoardProgram__c | B75: =IFERROR(INDEX('Object Catalogue'!$B:$B,MATCH(A75,'Object Catalogue'!$A:$A,0)),"") | C75: =IFERROR(INDEX('Object Catalogue'!$H:$H,MATCH(A75,'Object Catalogue'!$A:$A,0)),"") | D75: =IFERROR(INDEX('Object Catalogue'!$K:$K,MATCH(A75,'Object Catalogue'!$A:$A,0)),"") | E75: =IFERROR(INDEX('Object Catalogue'!$O:$O,MATCH(A75,'Object Catalogue'!$A:$A,0)),"")
A76: BusinessAccountCounter__c | B76: =IFERROR(INDEX('Object Catalogue'!$B:$B,MATCH(A76,'Object Catalogue'!$A:$A,0)),"") | C76: =IFERROR(INDEX('Object Catalogue'!$H:$H,MATCH(A76,'Object Catalogue'!$A:$A,0)),"") | D76: =IFERROR(INDEX('Object Catalogue'!$K:$K,MATCH(A76,'Object Catalogue'!$A:$A,0)),"") | E76: =IFERROR(INDEX('Object Catalogue'!$O:$O,MATCH(A76,'Object Catalogue'!$A:$A,0)),"")
A77: CertificateRequest__c | B77: =IFERROR(INDEX('Object Catalogue'!$B:$B,MATCH(A77,'Object Catalogue'!$A:$A,0)),"") | C77: =IFERROR(INDEX('Object Catalogue'!$H:$H,MATCH(A77,'Object Catalogue'!$A:$A,0)),"") | D77: =IFERROR(INDEX('Object Catalogue'!$K:$K,MATCH(A77,'Object Catalogue'!$A:$A,0)),"") | E77: =IFERROR(INDEX('Object Catalogue'!$O:$O,MATCH(A77,'Object Catalogue'!$A:$A,0)),"")
A78: Classification__c | B78: =IFERROR(INDEX('Object Catalogue'!$B:$B,MATCH(A78,'Object Catalogue'!$A:$A,0)),"") | C78: =IFERROR(INDEX('Object Catalogue'!$H:$H,MATCH(A78,'Object Catalogue'!$A:$A,0)),"") | D78: =IFERROR(INDEX('Object Catalogue'!$K:$K,MATCH(A78,'Object Catalogue'!$A:$A,0)),"") | E78: =IFERROR(INDEX('Object Catalogue'!$O:$O,MATCH(A78,'Object Catalogue'!$A:$A,0)),"")
A79: DocGeneratorDataSource__c | B79: =IFERROR(INDEX('Object Catalogue'!$B:$B,MATCH(A79,'Object Catalogue'!$A:$A,0)),"") | C79: =IFERROR(INDEX('Object Catalogue'!$H:$H,MATCH(A79,'Object Catalogue'!$A:$A,0)),"") | D79: =IFERROR(INDEX('Object Catalogue'!$K:$K,MATCH(A79,'Object Catalogue'!$A:$A,0)),"") | E79: =IFERROR(INDEX('Object Catalogue'!$O:$O,MATCH(A79,'Object Catalogue'!$A:$A,0)),"")
A80: DocGeneratorSettings__c | B80: =IFERROR(INDEX('Object Catalogue'!$B:$B,MATCH(A80,'Object Catalogue'!$A:$A,0)),"") | C80: =IFERROR(INDEX('Object Catalogue'!$H:$H,MATCH(A80,'Object Catalogue'!$A:$A,0)),"") | D80: =IFERROR(INDEX('Object Catalogue'!$K:$K,MATCH(A80,'Object Catalogue'!$A:$A,0)),"") | E80: =IFERROR(INDEX('Object Catalogue'!$O:$O,MATCH(A80,'Object Catalogue'!$A:$A,0)),"")
A81: Express_Change_Broker_History__c | B81: =IFERROR(INDEX('Object Catalogue'!$B:$B,MATCH(A81,'Object Catalogue'!$A:$A,0)),"") | C81: =IFERROR(INDEX('Object Catalogue'!$H:$H,MATCH(A81,'Object Catalogue'!$A:$A,0)),"") | D81: =IFERROR(INDEX('Object Catalogue'!$K:$K,MATCH(A81,'Object Catalogue'!$A:$A,0)),"") | E81: =IFERROR(INDEX('Object Catalogue'!$O:$O,MATCH(A81,'Object Catalogue'!$A:$A,0)),"")
A82: Inspections__c | B82: =IFERROR(INDEX('Object Catalogue'!$B:$B,MATCH(A82,'Object Catalogue'!$A:$A,0)),"") | C82: =IFERROR(INDEX('Object Catalogue'!$H:$H,MATCH(A82,'Object Catalogue'!$A:$A,0)),"") | D82: =IFERROR(INDEX('Object Catalogue'!$K:$K,MATCH(A82,'Object Catalogue'!$A:$A,0)),"") | E82: =IFERROR(INDEX('Object Catalogue'!$O:$O,MATCH(A82,'Object Catalogue'!$A:$A,0)),"")
A83: InsuranceBond__c | B83: =IFERROR(INDEX('Object Catalogue'!$B:$B,MATCH(A83,'Object Catalogue'!$A:$A,0)),"") | C83: =IFERROR(INDEX('Object Catalogue'!$H:$H,MATCH(A83,'Object Catalogue'!$A:$A,0)),"") | D83: =IFERROR(INDEX('Object Catalogue'!$K:$K,MATCH(A83,'Object Catalogue'!$A:$A,0)),"") | E83: =IFERROR(INDEX('Object Catalogue'!$O:$O,MATCH(A83,'Object Catalogue'!$A:$A,0)),"")
... A103: Suspense__c | B103: =IFERROR(INDEX('Object Catalogue'!$B:$B,MATCH(A103,'Object Catalogue'!$A:$A,0)),"") | C103: =IFERROR(INDEX('Object Catalogue'!$H:$H,MATCH(A103,'Object Catalogue'!$A:$A,0)),"") | D103: =IFERROR(INDEX('Object Catalogue'!$K:$K,MATCH(A103,'Object Catalogue'!$A:$A,0)),"") | E103: =IFERROR(INDEX('Object Catalogue'!$O:$O,MATCH(A103,'Object Catalogue'!$A:$A,0)),"")

Sheet ERD - PVL Exams & CE
A1: ERD: PVL: Exams & Continuing Education
A2: Licensing exam requirements, courses, schools, instructors and earned CE / pre-licence credit.
A3: ‹ Back to README
A4: Legend: solid line = master-detail (child owned by parent) · dashed line = lookup · crow's foot = "many" side · boxes with attribute rows = objects in this domain (Label, Fields, CodeRefs) · plain boxes = objects from other domains or managed packages. Lookups to User are omitted.
A112: Objects in this domain (16) | F112: Shown with 7 related objects from other domains.
A113: Object API Name | B113: Label | C113: Fields | D113: Relationship Fields | E113: Code References
A114: ContinuingEducation__c | B114: =IFERROR(INDEX('Object Catalogue'!$B:$B,MATCH(A114,'Object Catalogue'!$A:$A,0)),"") | C114: =IFERROR(INDEX('Object Catalogue'!$H:$H,MATCH(A114,'Object Catalogue'!$A:$A,0)),"") | D114: =IFERROR(INDEX('Object Catalogue'!$K:$K,MATCH(A114,'Object Catalogue'!$A:$A,0)),"") | E114: =IFERROR(INDEX('Object Catalogue'!$O:$O,MATCH(A114,'Object Catalogue'!$A:$A,0)),"")
A115: Course__c | B115: =IFERROR(INDEX('Object Catalogue'!$B:$B,MATCH(A115,'Object Catalogue'!$A:$A,0)),"") | C115: =IFERROR(INDEX('Object Catalogue'!$H:$H,MATCH(A115,'Object Catalogue'!$A:$A,0)),"") | D115: =IFERROR(INDEX('Object Catalogue'!$K:$K,MATCH(A115,'Object Catalogue'!$A:$A,0)),"") | E115: =IFERROR(INDEX('Object Catalogue'!$O:$O,MATCH(A115,'Object Catalogue'!$A:$A,0)),"")
A116: Earned_Continuing_Education__c | B116: =IFERROR(INDEX('Object Catalogue'!$B:$B,MATCH(A116,'Object Catalogue'!$A:$A,0)),"") | C116: =IFERROR(INDEX('Object Catalogue'!$H:$H,MATCH(A116,'Object Catalogue'!$A:$A,0)),"") | D116: =IFERROR(INDEX('Object Catalogue'!$K:$K,MATCH(A116,'Object Catalogue'!$A:$A,0)),"") | E116: =IFERROR(INDEX('Object Catalogue'!$O:$O,MATCH(A116,'Object Catalogue'!$A:$A,0)),"")
A117: Earned_Prelicense__c | B117: =IFERROR(INDEX('Object Catalogue'!$B:$B,MATCH(A117,'Object Catalogue'!$A:$A,0)),"") | C117: =IFERROR(INDEX('Object Catalogue'!$H:$H,MATCH(A117,'Object Catalogue'!$A:$A,0)),"") | D117: =IFERROR(INDEX('Object Catalogue'!$K:$K,MATCH(A117,'Object Catalogue'!$A:$A,0)),"") | E117: =IFERROR(INDEX('Object Catalogue'!$O:$O,MATCH(A117,'Object Catalogue'!$A:$A,0)),"")
A118: EligibleCandidateLoad__c | B118: =IFERROR(INDEX('Object Catalogue'!$B:$B,MATCH(A118,'Object Catalogue'!$A:$A,0)),"") | C118: =IFERROR(INDEX('Object Catalogue'!$H:$H,MATCH(A118,'Object Catalogue'!$A:$A,0)),"") | D118: =IFERROR(INDEX('Object Catalogue'!$K:$K,MATCH(A118,'Object Catalogue'!$A:$A,0)),"") | E118: =IFERROR(INDEX('Object Catalogue'!$O:$O,MATCH(A118,'Object Catalogue'!$A:$A,0)),"")
A119: ExamResultsLoad__c | B119: =IFERROR(INDEX('Object Catalogue'!$B:$B,MATCH(A119,'Object Catalogue'!$A:$A,0)),"") | C119: =IFERROR(INDEX('Object Catalogue'!$H:$H,MATCH(A119,'Object Catalogue'!$A:$A,0)),"") | D119: =IFERROR(INDEX('Object Catalogue'!$K:$K,MATCH(A119,'Object Catalogue'!$A:$A,0)),"") | E119: =IFERROR(INDEX('Object Catalogue'!$O:$O,MATCH(A119,'Object Catalogue'!$A:$A,0)),"")
A120: ExamResults__c | B120: =IFERROR(INDEX('Object Catalogue'!$B:$B,MATCH(A120,'Object Catalogue'!$A:$A,0)),"") | C120: =IFERROR(INDEX('Object Catalogue'!$H:$H,MATCH(A120,'Object Catalogue'!$A:$A,0)),"") | D120: =IFERROR(INDEX('Object Catalogue'!$K:$K,MATCH(A120,'Object Catalogue'!$A:$A,0)),"") | E120: =IFERROR(INDEX('Object Catalogue'!$O:$O,MATCH(A120,'Object Catalogue'!$A:$A,0)),"")
A121: ExamTypeRequirements__c | B121: =IFERROR(INDEX('Object Catalogue'!$B:$B,MATCH(A121,'Object Catalogue'!$A:$A,0)),"") | C121: =IFERROR(INDEX('Object Catalogue'!$H:$H,MATCH(A121,'Object Catalogue'!$A:$A,0)),"") | D121: =IFERROR(INDEX('Object Catalogue'!$K:$K,MATCH(A121,'Object Catalogue'!$A:$A,0)),"") | E121: =IFERROR(INDEX('Object Catalogue'!$O:$O,MATCH(A121,'Object Catalogue'!$A:$A,0)),"")
A122: ExamTypes__c | B122: =IFERROR(INDEX('Object Catalogue'!$B:$B,MATCH(A122,'Object Catalogue'!$A:$A,0)),"") | C122: =IFERROR(INDEX('Object Catalogue'!$H:$H,MATCH(A122,'Object Catalogue'!$A:$A,0)),"") | D122: =IFERROR(INDEX('Object Catalogue'!$K:$K,MATCH(A122,'Object Catalogue'!$A:$A,0)),"") | E122: =IFERROR(INDEX('Object Catalogue'!$O:$O,MATCH(A122,'Object Catalogue'!$A:$A,0)),"")
A123: ExamsRequired__c | B123: =IFERROR(INDEX('Object Catalogue'!$B:$B,MATCH(A123,'Object Catalogue'!$A:$A,0)),"") | C123: =IFERROR(INDEX('Object Catalogue'!$H:$H,MATCH(A123,'Object Catalogue'!$A:$A,0)),"") | D123: =IFERROR(INDEX('Object Catalogue'!$K:$K,MATCH(A123,'Object Catalogue'!$A:$A,0)),"") | E123: =IFERROR(INDEX('Object Catalogue'!$O:$O,MATCH(A123,'Object Catalogue'!$A:$A,0)),"")
A124: FieldprintResults__c | B124: =IFERROR(INDEX('Object Catalogue'!$B:$B,MATCH(A124,'Object Catalogue'!$A:$A,0)),"") | C124: =IFERROR(INDEX('Object Catalogue'!$H:$H,MATCH(A124,'Object Catalogue'!$A:$A,0)),"") | D124: =IFERROR(INDEX('Object Catalogue'!$K:$K,MATCH(A124,'Object Catalogue'!$A:$A,0)),"") | E124: =IFERROR(INDEX('Object Catalogue'!$O:$O,MATCH(A124,'Object Catalogue'!$A:$A,0)),"")
A125: InstructorSubject__c | B125: =IFERROR(INDEX('Object Catalogue'!$B:$B,MATCH(A125,'Object Catalogue'!$A:$A,0)),"") | C125: =IFERROR(INDEX('Object Catalogue'!$H:$H,MATCH(A125,'Object Catalogue'!$A:$A,0)),"") | D125: =IFERROR(INDEX('Object Catalogue'!$K:$K,MATCH(A125,'Object Catalogue'!$A:$A,0)),"") | E125: =IFERROR(INDEX('Object Catalogue'!$O:$O,MATCH(A125,'Object Catalogue'!$A:$A,0)),"")
... A129: Subject__c | B129: =IFERROR(INDEX('Object Catalogue'!$B:$B,MATCH(A129,'Object Catalogue'!$A:$A,0)),"") | C129: =IFERROR(INDEX('Object Catalogue'!$H:$H,MATCH(A129,'Object Catalogue'!$A:$A,0)),"") | D129: =IFERROR(INDEX('Object Catalogue'!$K:$K,MATCH(A129,'Object Catalogue'!$A:$A,0)),"") | E129: =IFERROR(INDEX('Object Catalogue'!$O:$O,MATCH(A129,'Object Catalogue'!$A:$A,0)),"")

Sheet ERD - Payments & Finance
A1: ERD: Payments & Finance
A2: Transactions, line items, PaymentConnect payments, fees, deposits and reconciliation.
A3: ‹ Back to README
A4: Legend: solid line = master-detail (child owned by parent) · dashed line = lookup · crow's foot = "many" side · boxes with attribute rows = objects in this domain (Label, Fields, CodeRefs) · plain boxes = objects from other domains or managed packages. Lookups to User are omitted.
A76: Objects in this domain (16) | F76: Shown with 22 related objects from other domains.
A77: Object API Name | B77: Label | C77: Fields | D77: Relationship Fields | E77: Code References
A78: CashierCode__c | B78: =IFERROR(INDEX('Object Catalogue'!$B:$B,MATCH(A78,'Object Catalogue'!$A:$A,0)),"") | C78: =IFERROR(INDEX('Object Catalogue'!$H:$H,MATCH(A78,'Object Catalogue'!$A:$A,0)),"") | D78: =IFERROR(INDEX('Object Catalogue'!$K:$K,MATCH(A78,'Object Catalogue'!$A:$A,0)),"") | E78: =IFERROR(INDEX('Object Catalogue'!$O:$O,MATCH(A78,'Object Catalogue'!$A:$A,0)),"")
A79: CollectionsAllocation__c | B79: =IFERROR(INDEX('Object Catalogue'!$B:$B,MATCH(A79,'Object Catalogue'!$A:$A,0)),"") | C79: =IFERROR(INDEX('Object Catalogue'!$H:$H,MATCH(A79,'Object Catalogue'!$A:$A,0)),"") | D79: =IFERROR(INDEX('Object Catalogue'!$K:$K,MATCH(A79,'Object Catalogue'!$A:$A,0)),"") | E79: =IFERROR(INDEX('Object Catalogue'!$O:$O,MATCH(A79,'Object Catalogue'!$A:$A,0)),"")
A80: DFIRegistration__c | B80: =IFERROR(INDEX('Object Catalogue'!$B:$B,MATCH(A80,'Object Catalogue'!$A:$A,0)),"") | C80: =IFERROR(INDEX('Object Catalogue'!$H:$H,MATCH(A80,'Object Catalogue'!$A:$A,0)),"") | D80: =IFERROR(INDEX('Object Catalogue'!$K:$K,MATCH(A80,'Object Catalogue'!$A:$A,0)),"") | E80: =IFERROR(INDEX('Object Catalogue'!$O:$O,MATCH(A80,'Object Catalogue'!$A:$A,0)),"")
A81: Deposits__c | B81: =IFERROR(INDEX('Object Catalogue'!$B:$B,MATCH(A81,'Object Catalogue'!$A:$A,0)),"") | C81: =IFERROR(INDEX('Object Catalogue'!$H:$H,MATCH(A81,'Object Catalogue'!$A:$A,0)),"") | D81: =IFERROR(INDEX('Object Catalogue'!$K:$K,MATCH(A81,'Object Catalogue'!$A:$A,0)),"") | E81: =IFERROR(INDEX('Object Catalogue'!$O:$O,MATCH(A81,'Object Catalogue'!$A:$A,0)),"")
A82: FeeSchedule__c | B82: =IFERROR(INDEX('Object Catalogue'!$B:$B,MATCH(A82,'Object Catalogue'!$A:$A,0)),"") | C82: =IFERROR(INDEX('Object Catalogue'!$H:$H,MATCH(A82,'Object Catalogue'!$A:$A,0)),"") | D82: =IFERROR(INDEX('Object Catalogue'!$K:$K,MATCH(A82,'Object Catalogue'!$A:$A,0)),"") | E82: =IFERROR(INDEX('Object Catalogue'!$O:$O,MATCH(A82,'Object Catalogue'!$A:$A,0)),"")
A83: FiscalForm__c | B83: =IFERROR(INDEX('Object Catalogue'!$B:$B,MATCH(A83,'Object Catalogue'!$A:$A,0)),"") | C83: =IFERROR(INDEX('Object Catalogue'!$H:$H,MATCH(A83,'Object Catalogue'!$A:$A,0)),"") | D83: =IFERROR(INDEX('Object Catalogue'!$K:$K,MATCH(A83,'Object Catalogue'!$A:$A,0)),"") | E83: =IFERROR(INDEX('Object Catalogue'!$O:$O,MATCH(A83,'Object Catalogue'!$A:$A,0)),"")
A84: HPEAPRequest__c | B84: =IFERROR(INDEX('Object Catalogue'!$B:$B,MATCH(A84,'Object Catalogue'!$A:$A,0)),"") | C84: =IFERROR(INDEX('Object Catalogue'!$H:$H,MATCH(A84,'Object Catalogue'!$A:$A,0)),"") | D84: =IFERROR(INDEX('Object Catalogue'!$K:$K,MATCH(A84,'Object Catalogue'!$A:$A,0)),"") | E84: =IFERROR(INDEX('Object Catalogue'!$O:$O,MATCH(A84,'Object Catalogue'!$A:$A,0)),"")
A85: HardwareFees__c | B85: =IFERROR(INDEX('Object Catalogue'!$B:$B,MATCH(A85,'Object Catalogue'!$A:$A,0)),"") | C85: =IFERROR(INDEX('Object Catalogue'!$H:$H,MATCH(A85,'Object Catalogue'!$A:$A,0)),"") | D85: =IFERROR(INDEX('Object Catalogue'!$K:$K,MATCH(A85,'Object Catalogue'!$A:$A,0)),"") | E85: =IFERROR(INDEX('Object Catalogue'!$O:$O,MATCH(A85,'Object Catalogue'!$A:$A,0)),"")
A86: LicenseTypeCashierCode__c | B86: =IFERROR(INDEX('Object Catalogue'!$B:$B,MATCH(A86,'Object Catalogue'!$A:$A,0)),"") | C86: =IFERROR(INDEX('Object Catalogue'!$H:$H,MATCH(A86,'Object Catalogue'!$A:$A,0)),"") | D86: =IFERROR(INDEX('Object Catalogue'!$K:$K,MATCH(A86,'Object Catalogue'!$A:$A,0)),"") | E86: =IFERROR(INDEX('Object Catalogue'!$O:$O,MATCH(A86,'Object Catalogue'!$A:$A,0)),"")
A87: PaymentReconciliation__c | B87: =IFERROR(INDEX('Object Catalogue'!$B:$B,MATCH(A87,'Object Catalogue'!$A:$A,0)),"") | C87: =IFERROR(INDEX('Object Catalogue'!$H:$H,MATCH(A87,'Object Catalogue'!$A:$A,0)),"") | D87: =IFERROR(INDEX('Object Catalogue'!$K:$K,MATCH(A87,'Object Catalogue'!$A:$A,0)),"") | E87: =IFERROR(INDEX('Object Catalogue'!$O:$O,MATCH(A87,'Object Catalogue'!$A:$A,0)),"")
A88: Reconciliation_Batch__c | B88: =IFERROR(INDEX('Object Catalogue'!$B:$B,MATCH(A88,'Object Catalogue'!$A:$A,0)),"") | C88: =IFERROR(INDEX('Object Catalogue'!$H:$H,MATCH(A88,'Object Catalogue'!$A:$A,0)),"") | D88: =IFERROR(INDEX('Object Catalogue'!$K:$K,MATCH(A88,'Object Catalogue'!$A:$A,0)),"") | E88: =IFERROR(INDEX('Object Catalogue'!$O:$O,MATCH(A88,'Object Catalogue'!$A:$A,0)),"")
A89: ServicesFees__c | B89: =IFERROR(INDEX('Object Catalogue'!$B:$B,MATCH(A89,'Object Catalogue'!$A:$A,0)),"") | C89: =IFERROR(INDEX('Object Catalogue'!$H:$H,MATCH(A89,'Object Catalogue'!$A:$A,0)),"") | D89: =IFERROR(INDEX('Object Catalogue'!$K:$K,MATCH(A89,'Object Catalogue'!$A:$A,0)),"") | E89: =IFERROR(INDEX('Object Catalogue'!$O:$O,MATCH(A89,'Object Catalogue'!$A:$A,0)),"")
... A93: pymt__PaymentX__c | B93: =IFERROR(INDEX('Object Catalogue'!$B:$B,MATCH(A93,'Object Catalogue'!$A:$A,0)),"") | C93: =IFERROR(INDEX('Object Catalogue'!$H:$H,MATCH(A93,'Object Catalogue'!$A:$A,0)),"") | D93: =IFERROR(INDEX('Object Catalogue'!$K:$K,MATCH(A93,'Object Catalogue'!$A:$A,0)),"") | E93: =IFERROR(INDEX('Object Catalogue'!$O:$O,MATCH(A93,'Object Catalogue'!$A:$A,0)),"")

Sheet ERD - Securities
A1: ERD: Securities: Filings & Exams
A2: Securities registrations (broker-dealer, investment adviser, offerings) and compliance examinations.
A3: ‹ Back to README
A4: Legend: solid line = master-detail (child owned by parent) · dashed line = lookup · crow's foot = "many" side · boxes with attribute rows = objects in this domain (Label, Fields, CodeRefs) · plain boxes = objects from other domains or managed packages. Lookups to User are omitted.
A51: Objects in this domain (8) | F51: Shown with 6 related objects from other domains.
A52: Object API Name | B52: Label | C52: Fields | D52: Relationship Fields | E52: Code References
